{"now": "2026-07-16 11:23", "session": "开盘中", "sessionLegacy": "早盘", "defaultCapital": 10000, "feeRates": {"sub": 0.0015, "sell": 0.0008, "buy": 0.0003, "redeem": 0.005}, "thresholds": {"premium": 0, "discount": -1.5}, "summary": {"premiumCount": 10, "discountCount": 2, "posCount": 21, "negCount": 29, "avgPremium": 1.29}, "premiumArb": [{"full_code": "SZ164906", "code6": "164906", "name": "中概互联网LOF", "price": 0.986, "change": 3.46, "est": 0.959, "premium": 2.82, "est_date": "2026-07-15", "ref_premium": -0.27, "status": "open", "status_text": "正常申购", "redeem_status": "open", "redeem_status_text": "正常赎回", "quota": null, "big_quota": null, "fund_type": "", "is_qdii": true, "confirm_days": 2, "confirm_days_label": "T+2", "yituo6": true, "yituo6_label": "支持", "quota_label": "无限制", "premium_cycle_label": "约4天", "premium_cycle_detail": "T+2+转托管", "discount_cycle_label": "约4天", "discount_cycle_detail": "T+0买入/T+2赎", "capital": 10000, "premium_profit_gross": 282.0, "premium_profit_net": 259.0, "discount_profit_gross": 282.0, "discount_profit_net": 229.0, "arb_cycle_label": "约4天", "expected_profit": 259.0, "arb_type": "premium"}, {"full_code": "SH501043", "code6": "501043", "name": "沪深300LOF", "price": 1.64, "change": -0.61, "est": 1.626, "premium": 0.86, "est_date": "2026-07-16", "ref_premium": null, "status": "open", "status_text": "正常申购", "redeem_status": "open", "redeem_status_text": "正常赎回", "quota": null, "big_quota": null, "fund_type": "", "is_qdii": false, "confirm_days": 1, "confirm_days_label": "T+1", "yituo6": false, "yituo6_label": "仅深市", "quota_label": "无限制", "premium_cycle_label": "约3天", "premium_cycle_detail": "T+1+转托管", "discount_cycle_label": "约3天", "discount_cycle_detail": "T+0买入/T+1赎", "capital": 10000, "premium_profit_gross": 86.0, "premium_profit_net": 63.0, "discount_profit_gross": 86.0, "discount_profit_net": 33.0, "arb_cycle_label": "约3天", "expected_profit": 63.0, "arb_type": "premium"}, {"full_code": "SZ163407", "code6": "163407", "name": "兴全沪深300LOF", "price": 2.675, "change": -0.07, "est": 2.659, "premium": 0.6, "est_date": "2026-07-16", "ref_premium": null, "status": "limited", "status_text": "限制大额", "redeem_status": "open", "redeem_status_text": "正常赎回", "quota": 10000000.0, "big_quota": null, "fund_type": "", "is_qdii": false, "confirm_days": 1, "confirm_days_label": "T+1", "yituo6": true, "yituo6_label": "支持", "quota_label": "1000万", "premium_cycle_label": "约3天", "premium_cycle_detail": "T+1+转托管", "discount_cycle_label": "约3天", "discount_cycle_detail": "T+0买入/T+1赎", "capital": 10000, "premium_profit_gross": 60.0, "premium_profit_net": 37.0, "discount_profit_gross": 60.0, "discount_profit_net": 7.0, "arb_cycle_label": "约3天", "expected_profit": 37.0, "arb_type": "premium"}, {"full_code": "SZ161812", "code6": "161812", "name": "深证100LOF", "price": 1.46, "change": 0.0, "est": 1.453, "premium": 0.48, "est_date": "2026-07-16", "ref_premium": null, "status": "open", "status_text": "正常申购", "redeem_status": "open", "redeem_status_text": "正常赎回", "quota": null, "big_quota": null, "fund_type": "", "is_qdii": false, "confirm_days": 1, "confirm_days_label": "T+1", "yituo6": true, "yituo6_label": "支持", "quota_label": "无限制", "premium_cycle_label": "约3天", "premium_cycle_detail": "T+1+转托管", "discount_cycle_label": "约3天", "discount_cycle_detail": "T+0买入/T+1赎", "capital": 10000, "premium_profit_gross": 48.0, "premium_profit_net": 25.0, "discount_profit_gross": 48.0, "discount_profit_net": -5.0, "arb_cycle_label": "约3天", "expected_profit": 25.0, "arb_type": "premium"}, {"full_code": "SZ160632", "code6": "160632", "name": "酒LOF", "price": 0.262, "change": 1.16, "est": 0.261, "premium": 0.38, "est_date": "2026-07-16", "ref_premium": null, "status": "limited", "status_text": "限制大额", "redeem_status": "open", "redeem_status_text": "正常赎回", "quota": 200000.0, "big_quota": null, "fund_type": "", "is_qdii": false, "confirm_days": 1, "confirm_days_label": "T+1", "yituo6": true, "yituo6_label": "支持", "quota_label": "20万", "premium_cycle_label": "约3天", "premium_cycle_detail": "T+1+转托管", "discount_cycle_label": "约3天", "discount_cycle_detail": "T+0买入/T+1赎", "capital": 10000, "premium_profit_gross": 38.0, "premium_profit_net": 15.0, "discount_profit_gross": 38.0, "discount_profit_net": -15.0, "arb_cycle_label": "约3天", "expected_profit": 15.0, "arb_type": "premium"}, {"full_code": "SZ160639", "code6": "160639", "name": "高铁LOF", "price": 0.81, "change": 0.62, "est": 0.807, "premium": 0.37, "est_date": "2026-07-16", "ref_premium": null, "status": "open", "status_text": "正常申购", "redeem_status": "open", "redeem_status_text": "正常赎回", "quota": null, "big_quota": null, "fund_type": "", "is_qdii": false, "confirm_days": 1, "confirm_days_label": "T+1", "yituo6": true, "yituo6_label": "支持", "quota_label": "无限制", "premium_cycle_label": "约3天", "premium_cycle_detail": "T+1+转托管", "discount_cycle_label": "约3天", "discount_cycle_detail": "T+0买入/T+1赎", "capital": 10000, "premium_profit_gross": 37.0, "premium_profit_net": 14.0, "discount_profit_gross": 37.0, "discount_profit_net": -16.0, "arb_cycle_label": "约3天", "expected_profit": 14.0, "arb_type": "premium"}, {"full_code": "SZ163109", "code6": "163109", "name": "申万深成LOF", "price": 0.81, "change": -1.34, "est": 0.807, "premium": 0.37, "est_date": "2026-07-16", "ref_premium": null, "status": "open", "status_text": "正常申购", "redeem_status": "open", "redeem_status_text": "正常赎回", "quota": null, "big_quota": null, "fund_type": "", "is_qdii": false, "confirm_days": 1, "confirm_days_label": "T+1", "yituo6": true, "yituo6_label": "支持", "quota_label": "无限制", "premium_cycle_label": "约3天", "premium_cycle_detail": "T+1+转托管", "discount_cycle_label": "约3天", "discount_cycle_detail": "T+0买入/T+1赎", "capital": 10000, "premium_profit_gross": 37.0, "premium_profit_net": 14.0, "discount_profit_gross": 37.0, "discount_profit_net": -16.0, "arb_cycle_label": "约3天", "expected_profit": 14.0, "arb_type": "premium"}, {"full_code": "SZ161005", "code6": "161005", "name": "富国天惠LOF", "price": 3.165, "change": -0.5, "est": 3.157, "premium": 0.25, "est_date": "2026-07-16", "ref_premium": null, "status": "limited", "status_text": "限制大额", "redeem_status": "open", "redeem_status_text": "正常赎回", "quota": 20000.0, "big_quota": null, "fund_type": "", "is_qdii": false, "confirm_days": 1, "confirm_days_label": "T+1", "yituo6": true, "yituo6_label": "推荐", "quota_label": "2万", "premium_cycle_label": "约3天", "premium_cycle_detail": "T+1+转托管", "discount_cycle_label": "约3天", "discount_cycle_detail": "T+0买入/T+1赎", "capital": 10000, "premium_profit_gross": 25.0, "premium_profit_net": 2.0, "discount_profit_gross": 25.0, "discount_profit_net": -28.0, "arb_cycle_label": "约3天", "expected_profit": 2.0, "arb_type": "premium"}, {"full_code": "SZ168204", "code6": "168204", "name": "煤炭LOF", "price": 1.96, "change": -1.75, "est": 1.957, "premium": 0.15, "est_date": "2026-07-16", "ref_premium": null, "status": "open", "status_text": "正常申购", "redeem_status": "open", "redeem_status_text": "正常赎回", "quota": null, "big_quota": null, "fund_type": "", "is_qdii": false, "confirm_days": 1, "confirm_days_label": "T+1", "yituo6": true, "yituo6_label": "支持", "quota_label": "无限制", "premium_cycle_label": "约3天", "premium_cycle_detail": "T+1+转托管", "discount_cycle_label": "约3天", "discount_cycle_detail": "T+0买入/T+1赎", "capital": 10000, "premium_profit_gross": 15.0, "premium_profit_net": -8.0, "discount_profit_gross": 15.0, "discount_profit_net": -38.0, "arb_cycle_label": "约3天", "expected_profit": -8.0, "arb_type": "premium"}, {"full_code": "SZ163113", "code6": "163113", "name": "申万证券LOF", "price": 0.946, "change": -0.94, "est": 0.945, "premium": 0.11, "est_date": "2026-07-16", "ref_premium": null, "status": "open", "status_text": "正常申购", "redeem_status": "open", "redeem_status_text": "正常赎回", "quota": null, "big_quota": null, "fund_type": "", "is_qdii": false, "confirm_days": 1, "confirm_days_label": "T+1", "yituo6": true, "yituo6_label": "支持", "quota_label": "无限制", "premium_cycle_label": "约3天", "premium_cycle_detail": "T+1+转托管", "discount_cycle_label": "约3天", "discount_cycle_detail": "T+0买入/T+1赎", "capital": 10000, "premium_profit_gross": 11.0, "premium_profit_net": -12.0, "discount_profit_gross": 11.0, "discount_profit_net": -42.0, "arb_cycle_label": "约3天", "expected_profit": -12.0, "arb_type": "premium"}], "discountArb": [{"full_code": "SZ168401", "code6": "168401", "name": "红土创新精选LOF", "price": 7.007, "change": -4.18, "est": 7.204, "premium": -2.73, "est_date": "2026-07-16", "ref_premium": null, "status": "open", "status_text": "正常申购", "redeem_status": "open", "redeem_status_text": "正常赎回", "quota": null, "big_quota": null, "fund_type": "", "is_qdii": false, "confirm_days": 1, "confirm_days_label": "T+1", "yituo6": true, "yituo6_label": "支持", "quota_label": "无限制", "premium_cycle_label": "约3天", "premium_cycle_detail": "T+1+转托管", "discount_cycle_label": "约3天", "discount_cycle_detail": "T+0买入/T+1赎", "capital": 10000, "premium_profit_gross": 273.0, "premium_profit_net": 250.0, "discount_profit_gross": 273.0, "discount_profit_net": 220.0, "arb_cycle_label": "约3天", "expected_profit": 220.0, "arb_type": "discount"}, {"full_code": "SZ160644", "code6": "160644", "name": "港美互联网LOF", "price": 1.796, "change": -2.71, "est": 1.842, "premium": -2.5, "est_date": "2026-07-15", "ref_premium": -3.29, "status": "closed", "status_text": "暂停申购", "redeem_status": "open", "redeem_status_text": "正常赎回", "quota": 10000.0, "big_quota": null, "fund_type": "", "is_qdii": true, "confirm_days": 2, "confirm_days_label": "T+2", "yituo6": true, "yituo6_label": "推荐", "quota_label": "1万", "premium_cycle_label": "约4天", "premium_cycle_detail": "T+2+转托管", "discount_cycle_label": "约4天", "discount_cycle_detail": "T+0买入/T+2赎", "capital": 10000.0, "premium_profit_gross": 250.0, "premium_profit_net": 227.0, "discount_profit_gross": 250.0, "discount_profit_net": 197.0, "arb_cycle_label": "约4天", "expected_profit": 197.0, "arb_type": "discount"}], "blocked": [{"full_code": "SH501225", "code6": "501225", "name": "全球芯片LOF", "price": 4.058, "change": -3.03, "est": 3.264, "premium": 24.33, "est_date": "2026-07-15", "ref_premium": 25.18, "status": "closed", "status_text": "暂停申购", "redeem_status": "open", "redeem_status_text": "正常赎回", "quota": 100.0, "big_quota": null, "fund_type": "", "is_qdii": true, "confirm_days": 2, "confirm_days_label": "T+2", "yituo6": false, "yituo6_label": "仅深市", "quota_label": "100元", "premium_cycle_label": "约4天", "premium_cycle_detail": "T+2+转托管", "discount_cycle_label": "约4天", "discount_cycle_detail": "T+0买入/T+2赎", "capital": 100.0, "premium_profit_gross": 24.33, "premium_profit_net": 24.1, "discount_profit_gross": 24.33, "discount_profit_net": 23.8, "block_reason": "溢价但不可申购"}, {"full_code": "SZ161226", "code6": "161226", "name": "国投白银LOF", "price": 1.817, "change": -1.14, "est": 1.593, "premium": 14.06, "est_date": "2026-07-16", "ref_premium": 15.57, "status": "closed", "status_text": "暂停申购", "redeem_status": "open", "redeem_status_text": "正常赎回", "quota": 100.0, "big_quota": null, "fund_type": "", "is_qdii": false, "confirm_days": 1, "confirm_days_label": "T+1", "yituo6": true, "yituo6_label": "推荐", "quota_label": "100元", "premium_cycle_label": "约3天", "premium_cycle_detail": "T+1+转托管", "discount_cycle_label": "约3天", "discount_cycle_detail": "T+0买入/T+1赎", "capital": 100.0, "premium_profit_gross": 14.06, "premium_profit_net": 13.83, "discount_profit_gross": 14.06, "discount_profit_net": 13.53, "block_reason": "溢价但不可申购"}, {"full_code": "SZ161129", "code6": "161129", "name": "原油LOF易方达", "price": 1.809, "change": -2.22, "est": 1.588, "premium": 13.92, "est_date": "2026-07-15", "ref_premium": 13.68, "status": "closed", "status_text": "暂停申购", "redeem_status": "open", "redeem_status_text": "正常赎回", "quota": 10.0, "big_quota": null, "fund_type": "", "is_qdii": true, "confirm_days": 2, "confirm_days_label": "T+2", "yituo6": true, "yituo6_label": "推荐", "quota_label": "10元", "premium_cycle_label": "约4天", "premium_cycle_detail": "T+2+转托管", "discount_cycle_label": "约4天", "discount_cycle_detail": "T+0买入/T+2赎", "capital": 10.0, "premium_profit_gross": 1.39, "premium_profit_net": 1.37, "discount_profit_gross": 1.39, "discount_profit_net": 1.34, "block_reason": "溢价但不可申购"}, {"full_code": "SH501018", "code6": "501018", "name": "南方原油LOF", "price": 1.868, "change": -2.25, "est": 1.662, "premium": 12.39, "est_date": "2026-07-15", "ref_premium": 12.28, "status": "closed", "status_text": "暂停申购", "redeem_status": "open", "redeem_status_text": "正常赎回", "quota": 0.0, "big_quota": null, "fund_type": "", "is_qdii": true, "confirm_days": 2, "confirm_days_label": "T+2", "yituo6": false, "yituo6_label": "仅深市", "quota_label": "无限制", "premium_cycle_label": "约4天", "premium_cycle_detail": "T+2+转托管", "discount_cycle_label": "约4天", "discount_cycle_detail": "T+0买入/T+2赎", "capital": 10000, "premium_profit_gross": 1239.0, "premium_profit_net": 1216.0, "discount_profit_gross": 1239.0, "discount_profit_net": 1186.0, "block_reason": "溢价但不可申购"}, {"full_code": "SZ160723", "code6": "160723", "name": "嘉实原油LOF", "price": 2.087, "change": -2.29, "est": 1.907, "premium": 9.44, "est_date": "2026-07-15", "ref_premium": 9.17, "status": "closed", "status_text": "暂停申购", "redeem_status": "open", "redeem_status_text": "正常赎回", "quota": 5.0, "big_quota": null, "fund_type": "", "is_qdii": true, "confirm_days": 2, "confirm_days_label": "T+2", "yituo6": true, "yituo6_label": "推荐", "quota_label": "5元", "premium_cycle_label": "约4天", "premium_cycle_detail": "T+2+转托管", "discount_cycle_label": "约4天", "discount_cycle_detail": "T+0买入/T+2赎", "capital": 5.0, "premium_profit_gross": 0.47, "premium_profit_net": 0.46, "discount_profit_gross": 0.47, "discount_profit_net": 0.45, "block_reason": "溢价但不可申购"}, {"full_code": "SZ161130", "code6": "161130", "name": "纳斯达克100LOF", "price": 4.609, "change": -0.37, "est": 4.45, "premium": 3.57, "est_date": "2026-07-15", "ref_premium": 3.61, "status": "closed", "status_text": "暂停申购", "redeem_status": "open", "redeem_status_text": "正常赎回", "quota": 10.0, "big_quota": null, "fund_type": "", "is_qdii": true, "confirm_days": 2, "confirm_days_label": "T+2", "yituo6": true, "yituo6_label": "推荐", "quota_label": "10元", "premium_cycle_label": "约4天", "premium_cycle_detail": "T+2+转托管", "discount_cycle_label": "约4天", "discount_cycle_detail": "T+0买入/T+2赎", "capital": 10.0, "premium_profit_gross": 0.36, "premium_profit_net": 0.33, "discount_profit_gross": 0.36, "discount_profit_net": 0.3, "block_reason": "溢价但不可申购"}, {"full_code": "SZ161128", "code6": "161128", "name": "标普信息科技LOF", "price": 6.768, "change": -0.62, "est": 6.547, "premium": 3.38, "est_date": "2026-07-15", "ref_premium": 3.37, "status": "closed", "status_text": "暂停申购", "redeem_status": "open", "redeem_status_text": "正常赎回", "quota": 10.0, "big_quota": null, "fund_type": "", "is_qdii": true, "confirm_days": 2, "confirm_days_label": "T+2", "yituo6": true, "yituo6_label": "推荐", "quota_label": "10元", "premium_cycle_label": "约4天", "premium_cycle_detail": "T+2+转托管", "discount_cycle_label": "约4天", "discount_cycle_detail": "T+0买入/T+2赎", "capital": 10.0, "premium_profit_gross": 0.34, "premium_profit_net": 0.31, "discount_profit_gross": 0.34, "discount_profit_net": 0.28, "block_reason": "溢价但不可申购"}, {"full_code": "SZ161125", "code6": "161125", "name": "标普500LOF", "price": 3.204, "change": 0.28, "est": 3.117, "premium": 2.79, "est_date": "2026-07-15", "ref_premium": 2.79, "status": "closed", "status_text": "暂停申购", "redeem_status": "open", "redeem_status_text": "正常赎回", "quota": 10.0, "big_quota": null, "fund_type": "", "is_qdii": true, "confirm_days": 2, "confirm_days_label": "T+2", "yituo6": true, "yituo6_label": "推荐", "quota_label": "10元", "premium_cycle_label": "约4天", "premium_cycle_detail": "T+2+转托管", "discount_cycle_label": "约4天", "discount_cycle_detail": "T+0买入/T+2赎", "capital": 10.0, "premium_profit_gross": 0.28, "premium_profit_net": 0.26, "discount_profit_gross": 0.28, "discount_profit_net": 0.23, "block_reason": "溢价但不可申购"}, {"full_code": "SZ162719", "code6": "162719", "name": "石油LOF", "price": 2.692, "change": -1.21, "est": 2.683, "premium": 0.34, "est_date": "2026-07-15", "ref_premium": 0.32, "status": "closed", "status_text": "暂停申购", "redeem_status": "open", "redeem_status_text": "正常赎回", "quota": 10.0, "big_quota": null, "fund_type": "", "is_qdii": true, "confirm_days": 2, "confirm_days_label": "T+2", "yituo6": true, "yituo6_label": "推荐", "quota_label": "10元", "premium_cycle_label": "约4天", "premium_cycle_detail": "T+2+转托管", "discount_cycle_label": "约4天", "discount_cycle_detail": "T+0买入/T+2赎", "capital": 10.0, "premium_profit_gross": 0.03, "premium_profit_net": 0.01, "discount_profit_gross": 0.03, "discount_profit_net": -0.02, "block_reason": "溢价但不可申购"}, {"full_code": "SZ160416", "code6": "160416", "name": "石油基金LOF", "price": 2.03, "change": -0.44, "est": 2.027, "premium": 0.15, "est_date": "2026-07-15", "ref_premium": 0.14, "status": "closed", "status_text": "暂停申购", "redeem_status": "open", "redeem_status_text": "正常赎回", "quota": 2.0, "big_quota": null, "fund_type": "", "is_qdii": true, "confirm_days": 2, "confirm_days_label": "T+2", "yituo6": true, "yituo6_label": "推荐", "quota_label": "2元", "premium_cycle_label": "约4天", "premium_cycle_detail": "T+2+转托管", "discount_cycle_label": "约4天", "discount_cycle_detail": "T+0买入/T+2赎", "capital": 2.0, "premium_profit_gross": 0.0, "premium_profit_net": -0.0, "discount_profit_gross": 0.0, "discount_profit_net": -0.01, "block_reason": "溢价但不可申购"}, {"full_code": "SZ162411", "code6": "162411", "name": "华宝油气LOF", "price": 0.874, "change": -0.68, "est": 0.873, "premium": 0.11, "est_date": "2026-07-15", "ref_premium": 0.0, "status": "closed", "status_text": "暂停申购", "redeem_status": "open", "redeem_status_text": "正常赎回", "quota": 10.0, "big_quota": null, "fund_type": "", "is_qdii": true, "confirm_days": 2, "confirm_days_label": "T+2", "yituo6": true, "yituo6_label": "推荐", "quota_label": "10元", "premium_cycle_label": "约4天", "premium_cycle_detail": "T+2+转托管", "discount_cycle_label": "约4天", "discount_cycle_detail": "T+0买入/T+2赎", "capital": 10.0, "premium_profit_gross": 0.01, "premium_profit_net": -0.01, "discount_profit_gross": 0.01, "discount_profit_net": -0.04, "block_reason": "溢价但不可申购"}], "allRows": [{"full_code": "SH501225", "code6": "501225", "name": "全球芯片LOF", "price": 4.058, "change": -3.03, "est": 3.264, "premium": 24.33, "est_date": "2026-07-15", "ref_premium": 25.18, "status": "closed", "status_text": "暂停申购", "redeem_status": "open", "redeem_status_text": "正常赎回", "quota": 100.0, "big_quota": null, "fund_type": "", "is_qdii": true, "confirm_days": 2, "confirm_days_label": "T+2", "yituo6": false, "yituo6_label": "仅深市", "quota_label": "100元", "premium_cycle_label": "约4天", "premium_cycle_detail": "T+2+转托管", "discount_cycle_label": "约4天", "discount_cycle_detail": "T+0买入/T+2赎", "capital": 100.0, "premium_profit_gross": 24.33, "premium_profit_net": 24.1, "discount_profit_gross": 24.33, "discount_profit_net": 23.8}, {"full_code": "SZ161226", "code6": "161226", "name": "国投白银LOF", "price": 1.817, "change": -1.14, "est": 1.593, "premium": 14.06, "est_date": "2026-07-16", "ref_premium": 15.57, "status": "closed", "status_text": "暂停申购", "redeem_status": "open", "redeem_status_text": "正常赎回", "quota": 100.0, "big_quota": null, "fund_type": "", "is_qdii": false, "confirm_days": 1, "confirm_days_label": "T+1", "yituo6": true, "yituo6_label": "推荐", "quota_label": "100元", "premium_cycle_label": "约3天", "premium_cycle_detail": "T+1+转托管", "discount_cycle_label": "约3天", "discount_cycle_detail": "T+0买入/T+1赎", "capital": 100.0, "premium_profit_gross": 14.06, "premium_profit_net": 13.83, "discount_profit_gross": 14.06, "discount_profit_net": 13.53}, {"full_code": "SZ161129", "code6": "161129", "name": "原油LOF易方达", "price": 1.809, "change": -2.22, "est": 1.588, "premium": 13.92, "est_date": "2026-07-15", "ref_premium": 13.68, "status": "closed", "status_text": "暂停申购", "redeem_status": "open", "redeem_status_text": "正常赎回", "quota": 10.0, "big_quota": null, "fund_type": "", "is_qdii": true, "confirm_days": 2, "confirm_days_label": "T+2", "yituo6": true, "yituo6_label": "推荐", "quota_label": "10元", "premium_cycle_label": "约4天", "premium_cycle_detail": "T+2+转托管", "discount_cycle_label": "约4天", "discount_cycle_detail": "T+0买入/T+2赎", "capital": 10.0, "premium_profit_gross": 1.39, "premium_profit_net": 1.37, "discount_profit_gross": 1.39, "discount_profit_net": 1.34}, {"full_code": "SH501018", "code6": "501018", "name": "南方原油LOF", "price": 1.868, "change": -2.25, "est": 1.662, "premium": 12.39, "est_date": "2026-07-15", "ref_premium": 12.28, "status": "closed", "status_text": "暂停申购", "redeem_status": "open", "redeem_status_text": "正常赎回", "quota": 0.0, "big_quota": null, "fund_type": "", "is_qdii": true, "confirm_days": 2, "confirm_days_label": "T+2", "yituo6": false, "yituo6_label": "仅深市", "quota_label": "无限制", "premium_cycle_label": "约4天", "premium_cycle_detail": "T+2+转托管", "discount_cycle_label": "约4天", "discount_cycle_detail": "T+0买入/T+2赎", "capital": 10000, "premium_profit_gross": 1239.0, "premium_profit_net": 1216.0, "discount_profit_gross": 1239.0, "discount_profit_net": 1186.0}, {"full_code": "SZ160723", "code6": "160723", "name": "嘉实原油LOF", "price": 2.087, "change": -2.29, "est": 1.907, "premium": 9.44, "est_date": "2026-07-15", "ref_premium": 9.17, "status": "closed", "status_text": "暂停申购", "redeem_status": "open", "redeem_status_text": "正常赎回", "quota": 5.0, "big_quota": null, "fund_type": "", "is_qdii": true, "confirm_days": 2, "confirm_days_label": "T+2", "yituo6": true, "yituo6_label": "推荐", "quota_label": "5元", "premium_cycle_label": "约4天", "premium_cycle_detail": "T+2+转托管", "discount_cycle_label": "约4天", "discount_cycle_detail": "T+0买入/T+2赎", "capital": 5.0, "premium_profit_gross": 0.47, "premium_profit_net": 0.46, "discount_profit_gross": 0.47, "discount_profit_net": 0.45}, {"full_code": "SZ161130", "code6": "161130", "name": "纳斯达克100LOF", "price": 4.609, "change": -0.37, "est": 4.45, "premium": 3.57, "est_date": "2026-07-15", "ref_premium": 3.61, "status": "closed", "status_text": "暂停申购", "redeem_status": "open", "redeem_status_text": "正常赎回", "quota": 10.0, "big_quota": null, "fund_type": "", "is_qdii": true, "confirm_days": 2, "confirm_days_label": "T+2", "yituo6": true, "yituo6_label": "推荐", "quota_label": "10元", "premium_cycle_label": "约4天", "premium_cycle_detail": "T+2+转托管", "discount_cycle_label": "约4天", "discount_cycle_detail": "T+0买入/T+2赎", "capital": 10.0, "premium_profit_gross": 0.36, "premium_profit_net": 0.33, "discount_profit_gross": 0.36, "discount_profit_net": 0.3}, {"full_code": "SZ161128", "code6": "161128", "name": "标普信息科技LOF", "price": 6.768, "change": -0.62, "est": 6.547, "premium": 3.38, "est_date": "2026-07-15", "ref_premium": 3.37, "status": "closed", "status_text": "暂停申购", "redeem_status": "open", "redeem_status_text": "正常赎回", "quota": 10.0, "big_quota": null, "fund_type": "", "is_qdii": true, "confirm_days": 2, "confirm_days_label": "T+2", "yituo6": true, "yituo6_label": "推荐", "quota_label": "10元", "premium_cycle_label": "约4天", "premium_cycle_detail": "T+2+转托管", "discount_cycle_label": "约4天", "discount_cycle_detail": "T+0买入/T+2赎", "capital": 10.0, "premium_profit_gross": 0.34, "premium_profit_net": 0.31, "discount_profit_gross": 0.34, "discount_profit_net": 0.28}, {"full_code": "SZ164906", "code6": "164906", "name": "中概互联网LOF", "price": 0.986, "change": 3.46, "est": 0.959, "premium": 2.82, "est_date": "2026-07-15", "ref_premium": -0.27, "status": "open", "status_text": "正常申购", "redeem_status": "open", "redeem_status_text": "正常赎回", "quota": null, "big_quota": null, "fund_type": "", "is_qdii": true, "confirm_days": 2, "confirm_days_label": "T+2", "yituo6": true, "yituo6_label": "支持", "quota_label": "无限制", "premium_cycle_label": "约4天", "premium_cycle_detail": "T+2+转托管", "discount_cycle_label": "约4天", "discount_cycle_detail": "T+0买入/T+2赎", "capital": 10000, "premium_profit_gross": 282.0, "premium_profit_net": 259.0, "discount_profit_gross": 282.0, "discount_profit_net": 229.0, "arb_cycle_label": "约4天", "expected_profit": 259.0, "arb_type": "premium"}, {"full_code": "SZ161125", "code6": "161125", "name": "标普500LOF", "price": 3.204, "change": 0.28, "est": 3.117, "premium": 2.79, "est_date": "2026-07-15", "ref_premium": 2.79, "status": "closed", "status_text": "暂停申购", "redeem_status": "open", "redeem_status_text": "正常赎回", "quota": 10.0, "big_quota": null, "fund_type": "", "is_qdii": true, "confirm_days": 2, "confirm_days_label": "T+2", "yituo6": true, "yituo6_label": "推荐", "quota_label": "10元", "premium_cycle_label": "约4天", "premium_cycle_detail": "T+2+转托管", "discount_cycle_label": "约4天", "discount_cycle_detail": "T+0买入/T+2赎", "capital": 10.0, "premium_profit_gross": 0.28, "premium_profit_net": 0.26, "discount_profit_gross": 0.28, "discount_profit_net": 0.23}, {"full_code": "SH501043", "code6": "501043", "name": "沪深300LOF", "price": 1.64, "change": -0.61, "est": 1.626, "premium": 0.86, "est_date": "2026-07-16", "ref_premium": null, "status": "open", "status_text": "正常申购", "redeem_status": "open", "redeem_status_text": "正常赎回", "quota": null, "big_quota": null, "fund_type": "", "is_qdii": false, "confirm_days": 1, "confirm_days_label": "T+1", "yituo6": false, "yituo6_label": "仅深市", "quota_label": "无限制", "premium_cycle_label": "约3天", "premium_cycle_detail": "T+1+转托管", "discount_cycle_label": "约3天", "discount_cycle_detail": "T+0买入/T+1赎", "capital": 10000, "premium_profit_gross": 86.0, "premium_profit_net": 63.0, "discount_profit_gross": 86.0, "discount_profit_net": 33.0, "arb_cycle_label": "约3天", "expected_profit": 63.0, "arb_type": "premium"}, {"full_code": "SZ163407", "code6": "163407", "name": "兴全沪深300LOF", "price": 2.675, "change": -0.07, "est": 2.659, "premium": 0.6, "est_date": "2026-07-16", "ref_premium": null, "status": "limited", "status_text": "限制大额", "redeem_status": "open", "redeem_status_text": "正常赎回", "quota": 10000000.0, "big_quota": null, "fund_type": "", "is_qdii": false, "confirm_days": 1, "confirm_days_label": "T+1", "yituo6": true, "yituo6_label": "支持", "quota_label": "1000万", "premium_cycle_label": "约3天", "premium_cycle_detail": "T+1+转托管", "discount_cycle_label": "约3天", "discount_cycle_detail": "T+0买入/T+1赎", "capital": 10000, "premium_profit_gross": 60.0, "premium_profit_net": 37.0, "discount_profit_gross": 60.0, "discount_profit_net": 7.0, "arb_cycle_label": "约3天", "expected_profit": 37.0, "arb_type": "premium"}, {"full_code": "SZ161812", "code6": "161812", "name": "深证100LOF", "price": 1.46, "change": 0.0, "est": 1.453, "premium": 0.48, "est_date": "2026-07-16", "ref_premium": null, "status": "open", "status_text": "正常申购", "redeem_status": "open", "redeem_status_text": "正常赎回", "quota": null, "big_quota": null, "fund_type": "", "is_qdii": false, "confirm_days": 1, "confirm_days_label": "T+1", "yituo6": true, "yituo6_label": "支持", "quota_label": "无限制", "premium_cycle_label": "约3天", "premium_cycle_detail": "T+1+转托管", "discount_cycle_label": "约3天", "discount_cycle_detail": "T+0买入/T+1赎", "capital": 10000, "premium_profit_gross": 48.0, "premium_profit_net": 25.0, "discount_profit_gross": 48.0, "discount_profit_net": -5.0, "arb_cycle_label": "约3天", "expected_profit": 25.0, "arb_type": "premium"}, {"full_code": "SZ160632", "code6": "160632", "name": "酒LOF", "price": 0.262, "change": 1.16, "est": 0.261, "premium": 0.38, "est_date": "2026-07-16", "ref_premium": null, "status": "limited", "status_text": "限制大额", "redeem_status": "open", "redeem_status_text": "正常赎回", "quota": 200000.0, "big_quota": null, "fund_type": "", "is_qdii": false, "confirm_days": 1, "confirm_days_label": "T+1", "yituo6": true, "yituo6_label": "支持", "quota_label": "20万", "premium_cycle_label": "约3天", "premium_cycle_detail": "T+1+转托管", "discount_cycle_label": "约3天", "discount_cycle_detail": "T+0买入/T+1赎", "capital": 10000, "premium_profit_gross": 38.0, "premium_profit_net": 15.0, "discount_profit_gross": 38.0, "discount_profit_net": -15.0, "arb_cycle_label": "约3天", "expected_profit": 15.0, "arb_type": "premium"}, {"full_code": "SZ160639", "code6": "160639", "name": "高铁LOF", "price": 0.81, "change": 0.62, "est": 0.807, "premium": 0.37, "est_date": "2026-07-16", "ref_premium": null, "status": "open", "status_text": "正常申购", "redeem_status": "open", "redeem_status_text": "正常赎回", "quota": null, "big_quota": null, "fund_type": "", "is_qdii": false, "confirm_days": 1, "confirm_days_label": "T+1", "yituo6": true, "yituo6_label": "支持", "quota_label": "无限制", "premium_cycle_label": "约3天", "premium_cycle_detail": "T+1+转托管", "discount_cycle_label": "约3天", "discount_cycle_detail": "T+0买入/T+1赎", "capital": 10000, "premium_profit_gross": 37.0, "premium_profit_net": 14.0, "discount_profit_gross": 37.0, "discount_profit_net": -16.0, "arb_cycle_label": "约3天", "expected_profit": 14.0, "arb_type": "premium"}, {"full_code": "SZ163109", "code6": "163109", "name": "申万深成LOF", "price": 0.81, "change": -1.34, "est": 0.807, "premium": 0.37, "est_date": "2026-07-16", "ref_premium": null, "status": "open", "status_text": "正常申购", "redeem_status": "open", "redeem_status_text": "正常赎回", "quota": null, "big_quota": null, "fund_type": "", "is_qdii": false, "confirm_days": 1, "confirm_days_label": "T+1", "yituo6": true, "yituo6_label": "支持", "quota_label": "无限制", "premium_cycle_label": "约3天", "premium_cycle_detail": "T+1+转托管", "discount_cycle_label": "约3天", "discount_cycle_detail": "T+0买入/T+1赎", "capital": 10000, "premium_profit_gross": 37.0, "premium_profit_net": 14.0, "discount_profit_gross": 37.0, "discount_profit_net": -16.0, "arb_cycle_label": "约3天", "expected_profit": 14.0, "arb_type": "premium"}, {"full_code": "SZ162719", "code6": "162719", "name": "石油LOF", "price": 2.692, "change": -1.21, "est": 2.683, "premium": 0.34, "est_date": "2026-07-15", "ref_premium": 0.32, "status": "closed", "status_text": "暂停申购", "redeem_status": "open", "redeem_status_text": "正常赎回", "quota": 10.0, "big_quota": null, "fund_type": "", "is_qdii": true, "confirm_days": 2, "confirm_days_label": "T+2", "yituo6": true, "yituo6_label": "推荐", "quota_label": "10元", "premium_cycle_label": "约4天", "premium_cycle_detail": "T+2+转托管", "discount_cycle_label": "约4天", "discount_cycle_detail": "T+0买入/T+2赎", "capital": 10.0, "premium_profit_gross": 0.03, "premium_profit_net": 0.01, "discount_profit_gross": 0.03, "discount_profit_net": -0.02}, {"full_code": "SZ161005", "code6": "161005", "name": "富国天惠LOF", "price": 3.165, "change": -0.5, "est": 3.157, "premium": 0.25, "est_date": "2026-07-16", "ref_premium": null, "status": "limited", "status_text": "限制大额", "redeem_status": "open", "redeem_status_text": "正常赎回", "quota": 20000.0, "big_quota": null, "fund_type": "", "is_qdii": false, "confirm_days": 1, "confirm_days_label": "T+1", "yituo6": true, "yituo6_label": "推荐", "quota_label": "2万", "premium_cycle_label": "约3天", "premium_cycle_detail": "T+1+转托管", "discount_cycle_label": "约3天", "discount_cycle_detail": "T+0买入/T+1赎", "capital": 10000, "premium_profit_gross": 25.0, "premium_profit_net": 2.0, "discount_profit_gross": 25.0, "discount_profit_net": -28.0, "arb_cycle_label": "约3天", "expected_profit": 2.0, "arb_type": "premium"}, {"full_code": "SZ160416", "code6": "160416", "name": "石油基金LOF", "price": 2.03, "change": -0.44, "est": 2.027, "premium": 0.15, "est_date": "2026-07-15", "ref_premium": 0.14, "status": "closed", "status_text": "暂停申购", "redeem_status": "open", "redeem_status_text": "正常赎回", "quota": 2.0, "big_quota": null, "fund_type": "", "is_qdii": true, "confirm_days": 2, "confirm_days_label": "T+2", "yituo6": true, "yituo6_label": "推荐", "quota_label": "2元", "premium_cycle_label": "约4天", "premium_cycle_detail": "T+2+转托管", "discount_cycle_label": "约4天", "discount_cycle_detail": "T+0买入/T+2赎", "capital": 2.0, "premium_profit_gross": 0.0, "premium_profit_net": -0.0, "discount_profit_gross": 0.0, "discount_profit_net": -0.01}, {"full_code": "SZ168204", "code6": "168204", "name": "煤炭LOF", "price": 1.96, "change": -1.75, "est": 1.957, "premium": 0.15, "est_date": "2026-07-16", "ref_premium": null, "status": "open", "status_text": "正常申购", "redeem_status": "open", "redeem_status_text": "正常赎回", "quota": null, "big_quota": null, "fund_type": "", "is_qdii": false, "confirm_days": 1, "confirm_days_label": "T+1", "yituo6": true, "yituo6_label": "支持", "quota_label": "无限制", "premium_cycle_label": "约3天", "premium_cycle_detail": "T+1+转托管", "discount_cycle_label": "约3天", "discount_cycle_detail": "T+0买入/T+1赎", "capital": 10000, "premium_profit_gross": 15.0, "premium_profit_net": -8.0, "discount_profit_gross": 15.0, "discount_profit_net": -38.0, "arb_cycle_label": "约3天", "expected_profit": -8.0, "arb_type": "premium"}, {"full_code": "SZ162411", "code6": "162411", "name": "华宝油气LOF", "price": 0.874, "change": -0.68, "est": 0.873, "premium": 0.11, "est_date": "2026-07-15", "ref_premium": 0.0, "status": "closed", "status_text": "暂停申购", "redeem_status": "open", "redeem_status_text": "正常赎回", "quota": 10.0, "big_quota": null, "fund_type": "", "is_qdii": true, "confirm_days": 2, "confirm_days_label": "T+2", "yituo6": true, "yituo6_label": "推荐", "quota_label": "10元", "premium_cycle_label": "约4天", "premium_cycle_detail": "T+2+转托管", "discount_cycle_label": "约4天", "discount_cycle_detail": "T+0买入/T+2赎", "capital": 10.0, "premium_profit_gross": 0.01, "premium_profit_net": -0.01, "discount_profit_gross": 0.01, "discount_profit_net": -0.04}, {"full_code": "SZ163113", "code6": "163113", "name": "申万证券LOF", "price": 0.946, "change": -0.94, "est": 0.945, "premium": 0.11, "est_date": "2026-07-16", "ref_premium": null, "status": "open", "status_text": "正常申购", "redeem_status": "open", "redeem_status_text": "正常赎回", "quota": null, "big_quota": null, "fund_type": "", "is_qdii": false, "confirm_days": 1, "confirm_days_label": "T+1", "yituo6": true, "yituo6_label": "支持", "quota_label": "无限制", "premium_cycle_label": "约3天", "premium_cycle_detail": "T+1+转托管", "discount_cycle_label": "约3天", "discount_cycle_detail": "T+0买入/T+1赎", "capital": 10000, "premium_profit_gross": 11.0, "premium_profit_net": -12.0, "discount_profit_gross": 11.0, "discount_profit_net": -42.0, "arb_cycle_label": "约3天", "expected_profit": -12.0, "arb_type": "premium"}, {"full_code": "SH501025", "code6": "501025", "name": "香港银行LOF", "price": 1.753, "change": 0.4, "est": 1.754, "premium": -0.06, "est_date": "2026-07-16", "ref_premium": null, "status": "open", "status_text": "正常申购", "redeem_status": "open", "redeem_status_text": "正常赎回", "quota": null, "big_quota": null, "fund_type": "", "is_qdii": true, "confirm_days": 1, "confirm_days_label": "T+1", "yituo6": false, "yituo6_label": "仅深市", "quota_label": "无限制", "premium_cycle_label": "约3天", "premium_cycle_detail": "T+1+转托管", "discount_cycle_label": "约3天", "discount_cycle_detail": "T+0买入/T+1赎", "capital": 10000, "premium_profit_gross": 6.0, "premium_profit_net": -17.0, "discount_profit_gross": 6.0, "discount_profit_net": -47.0}, {"full_code": "SZ161227", "code6": "161227", "name": "国投深证100LOF", "price": 1.718, "change": -0.87, "est": 1.719, "premium": -0.06, "est_date": "2026-07-16", "ref_premium": null, "status": "open", "status_text": "正常申购", "redeem_status": "open", "redeem_status_text": "正常赎回", "quota": null, "big_quota": null, "fund_type": "", "is_qdii": false, "confirm_days": 1, "confirm_days_label": "T+1", "yituo6": true, "yituo6_label": "支持", "quota_label": "无限制", "premium_cycle_label": "约3天", "premium_cycle_detail": "T+1+转托管", "discount_cycle_label": "约3天", "discount_cycle_detail": "T+0买入/T+1赎", "capital": 10000, "premium_profit_gross": 6.0, "premium_profit_net": -17.0, "discount_profit_gross": 6.0, "discount_profit_net": -47.0}, {"full_code": "SZ161725", "code6": "161725", "name": "白酒基金LOF", "price": 0.538, "change": 0.56, "est": 0.539, "premium": -0.19, "est_date": "2026-07-16", "ref_premium": null, "status": "limited", "status_text": "限制大额", "redeem_status": "open", "redeem_status_text": "正常赎回", "quota": 500000.0, "big_quota": null, "fund_type": "", "is_qdii": false, "confirm_days": 1, "confirm_days_label": "T+1", "yituo6": true, "yituo6_label": "支持", "quota_label": "50万", "premium_cycle_label": "约3天", "premium_cycle_detail": "T+1+转托管", "discount_cycle_label": "约3天", "discount_cycle_detail": "T+0买入/T+1赎", "capital": 10000, "premium_profit_gross": 19.0, "premium_profit_net": -4.0, "discount_profit_gross": 19.0, "discount_profit_net": -34.0}, {"full_code": "SZ160140", "code6": "160140", "name": "美国REIT精选LOF", "price": 1.46, "change": -0.14, "est": 1.463, "premium": -0.21, "est_date": "2026-07-15", "ref_premium": -0.18, "status": "open", "status_text": "正常申购", "redeem_status": "open", "redeem_status_text": "正常赎回", "quota": null, "big_quota": null, "fund_type": "", "is_qdii": true, "confirm_days": 2, "confirm_days_label": "T+2", "yituo6": true, "yituo6_label": "支持", "quota_label": "无限制", "premium_cycle_label": "约4天", "premium_cycle_detail": "T+2+转托管", "discount_cycle_label": "约4天", "discount_cycle_detail": "T+0买入/T+2赎", "capital": 10000, "premium_profit_gross": 21.0, "premium_profit_net": -2.0, "discount_profit_gross": 21.0, "discount_profit_net": -32.0}, {"full_code": "SZ160225", "code6": "160225", "name": "新能源汽车LOF", "price": 1.771, "change": -0.73, "est": 1.778, "premium": -0.39, "est_date": "2026-07-16", "ref_premium": null, "status": "open", "status_text": "正常申购", "redeem_status": "open", "redeem_status_text": "正常赎回", "quota": null, "big_quota": null, "fund_type": "", "is_qdii": false, "confirm_days": 1, "confirm_days_label": "T+1", "yituo6": true, "yituo6_label": "支持", "quota_label": "无限制", "premium_cycle_label": "约3天", "premium_cycle_detail": "T+1+转托管", "discount_cycle_label": "约3天", "discount_cycle_detail": "T+0买入/T+1赎", "capital": 10000, "premium_profit_gross": 39.0, "premium_profit_net": 16.0, "discount_profit_gross": 39.0, "discount_profit_net": -14.0}, {"full_code": "SZ164705", "code6": "164705", "name": "恒生LOF", "price": 1.125, "change": 1.63, "est": 1.13, "premium": -0.44, "est_date": "2026-07-16", "ref_premium": null, "status": "open", "status_text": "正常申购", "redeem_status": "open", "redeem_status_text": "正常赎回", "quota": null, "big_quota": null, "fund_type": "", "is_qdii": true, "confirm_days": 1, "confirm_days_label": "T+1", "yituo6": true, "yituo6_label": "支持", "quota_label": "无限制", "premium_cycle_label": "约3天", "premium_cycle_detail": "T+1+转托管", "discount_cycle_label": "约3天", "discount_cycle_detail": "T+0买入/T+1赎", "capital": 10000, "premium_profit_gross": 44.0, "premium_profit_net": 21.0, "discount_profit_gross": 44.0, "discount_profit_net": -9.0}, {"full_code": "SH501312", "code6": "501312", "name": "海外科技LOF", "price": 2.292, "change": -0.91, "est": 2.303, "premium": -0.48, "est_date": "2026-07-15", "ref_premium": -0.46, "status": "limited", "status_text": "限制大额", "redeem_status": "open", "redeem_status_text": "正常赎回", "quota": 20.0, "big_quota": null, "fund_type": "", "is_qdii": true, "confirm_days": 2, "confirm_days_label": "T+2", "yituo6": false, "yituo6_label": "仅深市", "quota_label": "20元", "premium_cycle_label": "约4天", "premium_cycle_detail": "T+2+转托管", "discount_cycle_label": "约4天", "discount_cycle_detail": "T+0买入/T+2赎", "capital": 20.0, "premium_profit_gross": 0.1, "premium_profit_net": 0.05, "discount_profit_gross": 0.1, "discount_profit_net": -0.01}, {"full_code": "SZ161726", "code6": "161726", "name": "生物医药LOF", "price": 0.415, "change": 1.47, "est": 0.417, "premium": -0.48, "est_date": "2026-07-16", "ref_premium": null, "status": "open", "status_text": "正常申购", "redeem_status": "open", "redeem_status_text": "正常赎回", "quota": null, "big_quota": null, "fund_type": "", "is_qdii": true, "confirm_days": 2, "confirm_days_label": "T+2", "yituo6": true, "yituo6_label": "支持", "quota_label": "无限制", "premium_cycle_label": "约4天", "premium_cycle_detail": "T+2+转托管", "discount_cycle_label": "约4天", "discount_cycle_detail": "T+0买入/T+2赎", "capital": 10000, "premium_profit_gross": 48.0, "premium_profit_net": 25.0, "discount_profit_gross": 48.0, "discount_profit_net": -5.0}, {"full_code": "SH502000", "code6": "502000", "name": "500增强LOF", "price": 2.093, "change": -1.51, "est": 2.104, "premium": -0.52, "est_date": "2026-07-16", "ref_premium": null, "status": "open", "status_text": "正常申购", "redeem_status": "open", "redeem_status_text": "正常赎回", "quota": null, "big_quota": null, "fund_type": "", "is_qdii": false, "confirm_days": 1, "confirm_days_label": "T+1", "yituo6": false, "yituo6_label": "仅深市", "quota_label": "无限制", "premium_cycle_label": "约3天", "premium_cycle_detail": "T+1+转托管", "discount_cycle_label": "约3天", "discount_cycle_detail": "T+0买入/T+1赎", "capital": 10000, "premium_profit_gross": 52.0, "premium_profit_net": 29.0, "discount_profit_gross": 52.0, "discount_profit_net": -1.0}, {"full_code": "SH501300", "code6": "501300", "name": "美元债LOF", "price": 0.935, "change": 0.11, "est": 0.94, "premium": -0.53, "est_date": "2026-07-15", "ref_premium": -0.57, "status": "limited", "status_text": "限制大额", "redeem_status": "open", "redeem_status_text": "正常赎回", "quota": 50000000.0, "big_quota": null, "fund_type": "", "is_qdii": true, "confirm_days": 2, "confirm_days_label": "T+2", "yituo6": false, "yituo6_label": "仅深市", "quota_label": "5000万", "premium_cycle_label": "约4天", "premium_cycle_detail": "T+2+转托管", "discount_cycle_label": "约4天", "discount_cycle_detail": "T+0买入/T+2赎", "capital": 10000, "premium_profit_gross": 53.0, "premium_profit_net": 30.0, "discount_profit_gross": 53.0, "discount_profit_net": 0.0}, {"full_code": "SH501302", "code6": "501302", "name": "恒生指数基金LOF", "price": 1.135, "change": 1.98, "est": 1.141, "premium": -0.53, "est_date": "2026-07-16", "ref_premium": null, "status": "open", "status_text": "正常申购", "redeem_status": "open", "redeem_status_text": "正常赎回", "quota": null, "big_quota": null, "fund_type": "", "is_qdii": true, "confirm_days": 1, "confirm_days_label": "T+1", "yituo6": false, "yituo6_label": "仅深市", "quota_label": "无限制", "premium_cycle_label": "约3天", "premium_cycle_detail": "T+1+转托管", "discount_cycle_label": "约3天", "discount_cycle_detail": "T+0买入/T+1赎", "capital": 10000, "premium_profit_gross": 53.0, "premium_profit_net": 30.0, "discount_profit_gross": 53.0, "discount_profit_net": 0.0}, {"full_code": "SZ161124", "code6": "161124", "name": "港股小盘LOF", "price": 0.9, "change": 0.67, "est": 0.905, "premium": -0.55, "est_date": "2026-07-16", "ref_premium": null, "status": "limited", "status_text": "限制大额", "redeem_status": "open", "redeem_status_text": "正常赎回", "quota": 3000.0, "big_quota": null, "fund_type": "", "is_qdii": true, "confirm_days": 1, "confirm_days_label": "T+1", "yituo6": true, "yituo6_label": "推荐", "quota_label": "3000元", "premium_cycle_label": "约3天", "premium_cycle_detail": "T+1+转托管", "discount_cycle_label": "约3天", "discount_cycle_detail": "T+0买入/T+1赎", "capital": 3000.0, "premium_profit_gross": 16.5, "premium_profit_net": 9.6, "discount_profit_gross": 16.5, "discount_profit_net": 0.6}, {"full_code": "SZ163208", "code6": "163208", "name": "全球油气能源LOF", "price": 1.261, "change": -0.86, "est": 1.268, "premium": -0.55, "est_date": "2026-07-15", "ref_premium": -0.52, "status": "closed", "status_text": "暂停申购", "redeem_status": "open", "redeem_status_text": "正常赎回", "quota": 500.0, "big_quota": null, "fund_type": "", "is_qdii": true, "confirm_days": 2, "confirm_days_label": "T+2", "yituo6": true, "yituo6_label": "推荐", "quota_label": "500元", "premium_cycle_label": "约4天", "premium_cycle_detail": "T+2+转托管", "discount_cycle_label": "约4天", "discount_cycle_detail": "T+0买入/T+2赎", "capital": 500.0, "premium_profit_gross": 2.75, "premium_profit_net": 1.6, "discount_profit_gross": 2.75, "discount_profit_net": 0.1}, {"full_code": "SZ161127", "code6": "161127", "name": "标普生物科技LOF", "price": 2.063, "change": -0.48, "est": 2.075, "premium": -0.58, "est_date": "2026-07-15", "ref_premium": -0.57, "status": "closed", "status_text": "暂停申购", "redeem_status": "open", "redeem_status_text": "正常赎回", "quota": 10.0, "big_quota": null, "fund_type": "", "is_qdii": true, "confirm_days": 2, "confirm_days_label": "T+2", "yituo6": true, "yituo6_label": "推荐", "quota_label": "10元", "premium_cycle_label": "约4天", "premium_cycle_detail": "T+2+转托管", "discount_cycle_label": "约4天", "discount_cycle_detail": "T+0买入/T+2赎", "capital": 10.0, "premium_profit_gross": 0.06, "premium_profit_net": 0.03, "discount_profit_gross": 0.06, "discount_profit_net": 0.0}, {"full_code": "SZ162415", "code6": "162415", "name": "美国消费LOF", "price": 2.861, "change": 0.49, "est": 2.879, "premium": -0.63, "est_date": "2026-07-15", "ref_premium": -0.62, "status": "limited", "status_text": "限制大额", "redeem_status": "open", "redeem_status_text": "正常赎回", "quota": 1000.0, "big_quota": null, "fund_type": "", "is_qdii": true, "confirm_days": 2, "confirm_days_label": "T+2", "yituo6": true, "yituo6_label": "推荐", "quota_label": "1000元", "premium_cycle_label": "约4天", "premium_cycle_detail": "T+2+转托管", "discount_cycle_label": "约4天", "discount_cycle_detail": "T+0买入/T+2赎", "capital": 1000.0, "premium_profit_gross": 6.3, "premium_profit_net": 4.0, "discount_profit_gross": 6.3, "discount_profit_net": 1.0}, {"full_code": "SZ161032", "code6": "161032", "name": "煤炭龙头LOF", "price": 2.099, "change": -2.37, "est": 2.113, "premium": -0.66, "est_date": "2026-07-16", "ref_premium": null, "status": "open", "status_text": "正常申购", "redeem_status": "open", "redeem_status_text": "正常赎回", "quota": null, "big_quota": null, "fund_type": "", "is_qdii": false, "confirm_days": 1, "confirm_days_label": "T+1", "yituo6": true, "yituo6_label": "支持", "quota_label": "无限制", "premium_cycle_label": "约3天", "premium_cycle_detail": "T+1+转托管", "discount_cycle_label": "约3天", "discount_cycle_detail": "T+0买入/T+1赎", "capital": 10000, "premium_profit_gross": 66.0, "premium_profit_net": 43.0, "discount_profit_gross": 66.0, "discount_profit_net": 13.0}, {"full_code": "SZ161815", "code6": "161815", "name": "抗通胀LOF", "price": 1.023, "change": -0.68, "est": 1.03, "premium": -0.68, "est_date": "2026-07-15", "ref_premium": -0.65, "status": "open", "status_text": "正常申购", "redeem_status": "open", "redeem_status_text": "正常赎回", "quota": null, "big_quota": null, "fund_type": "", "is_qdii": true, "confirm_days": 2, "confirm_days_label": "T+2", "yituo6": true, "yituo6_label": "支持", "quota_label": "无限制", "premium_cycle_label": "约4天", "premium_cycle_detail": "T+2+转托管", "discount_cycle_label": "约4天", "discount_cycle_detail": "T+0买入/T+2赎", "capital": 10000, "premium_profit_gross": 68.0, "premium_profit_net": 45.0, "discount_profit_gross": 68.0, "discount_profit_net": 15.0}, {"full_code": "SZ162412", "code6": "162412", "name": "医疗基金LOF", "price": 0.583, "change": 1.22, "est": 0.587, "premium": -0.68, "est_date": "2026-07-16", "ref_premium": null, "status": "open", "status_text": "正常申购", "redeem_status": "open", "redeem_status_text": "正常赎回", "quota": null, "big_quota": null, "fund_type": "", "is_qdii": true, "confirm_days": 2, "confirm_days_label": "T+2", "yituo6": true, "yituo6_label": "支持", "quota_label": "无限制", "premium_cycle_label": "约4天", "premium_cycle_detail": "T+2+转托管", "discount_cycle_label": "约4天", "discount_cycle_detail": "T+0买入/T+2赎", "capital": 10000, "premium_profit_gross": 68.0, "premium_profit_net": 45.0, "discount_profit_gross": 68.0, "discount_profit_net": 15.0}, {"full_code": "SZ160719", "code6": "160719", "name": "嘉实黄金LOF", "price": 1.799, "change": -0.06, "est": 1.813, "premium": -0.77, "est_date": "2026-07-15", "ref_premium": -0.78, "status": "closed", "status_text": "暂停申购", "redeem_status": "open", "redeem_status_text": "正常赎回", "quota": 5.0, "big_quota": null, "fund_type": "", "is_qdii": true, "confirm_days": 2, "confirm_days_label": "T+2", "yituo6": true, "yituo6_label": "推荐", "quota_label": "5元", "premium_cycle_label": "约4天", "premium_cycle_detail": "T+2+转托管", "discount_cycle_label": "约4天", "discount_cycle_detail": "T+0买入/T+2赎", "capital": 5.0, "premium_profit_gross": 0.04, "premium_profit_net": 0.03, "discount_profit_gross": 0.04, "discount_profit_net": 0.01}, {"full_code": "SZ161116", "code6": "161116", "name": "黄金主题LOF", "price": 1.498, "change": 0.0, "est": 1.511, "premium": -0.86, "est_date": "2026-07-15", "ref_premium": -0.86, "status": "closed", "status_text": "暂停申购", "redeem_status": "open", "redeem_status_text": "正常赎回", "quota": 10.0, "big_quota": null, "fund_type": "", "is_qdii": true, "confirm_days": 2, "confirm_days_label": "T+2", "yituo6": true, "yituo6_label": "推荐", "quota_label": "10元", "premium_cycle_label": "约4天", "premium_cycle_detail": "T+2+转托管", "discount_cycle_label": "约4天", "discount_cycle_detail": "T+0买入/T+2赎", "capital": 10.0, "premium_profit_gross": 0.09, "premium_profit_net": 0.06, "discount_profit_gross": 0.09, "discount_profit_net": 0.03}, {"full_code": "SZ160924", "code6": "160924", "name": "恒生指数LOF", "price": 0.991, "change": 1.43, "est": 1.0, "premium": -0.9, "est_date": "2026-07-16", "ref_premium": null, "status": "open", "status_text": "正常申购", "redeem_status": "open", "redeem_status_text": "正常赎回", "quota": null, "big_quota": null, "fund_type": "", "is_qdii": true, "confirm_days": 1, "confirm_days_label": "T+1", "yituo6": true, "yituo6_label": "支持", "quota_label": "无限制", "premium_cycle_label": "约3天", "premium_cycle_detail": "T+1+转托管", "discount_cycle_label": "约3天", "discount_cycle_detail": "T+0买入/T+1赎", "capital": 10000, "premium_profit_gross": 90.0, "premium_profit_net": 67.0, "discount_profit_gross": 90.0, "discount_profit_net": 37.0}, {"full_code": "SZ161831", "code6": "161831", "name": "恒生国企LOF", "price": 0.724, "change": 2.12, "est": 0.731, "premium": -0.96, "est_date": "2026-07-16", "ref_premium": null, "status": "open", "status_text": "正常申购", "redeem_status": "open", "redeem_status_text": "正常赎回", "quota": null, "big_quota": null, "fund_type": "", "is_qdii": true, "confirm_days": 1, "confirm_days_label": "T+1", "yituo6": true, "yituo6_label": "支持", "quota_label": "无限制", "premium_cycle_label": "约3天", "premium_cycle_detail": "T+1+转托管", "discount_cycle_label": "约3天", "discount_cycle_detail": "T+0买入/T+1赎", "capital": 10000, "premium_profit_gross": 96.0, "premium_profit_net": 73.0, "discount_profit_gross": 96.0, "discount_profit_net": 43.0}, {"full_code": "SZ160717", "code6": "160717", "name": "H股LOF", "price": 0.715, "change": 1.56, "est": 0.722, "premium": -0.97, "est_date": "2026-07-16", "ref_premium": null, "status": "open", "status_text": "正常申购", "redeem_status": "open", "redeem_status_text": "正常赎回", "quota": null, "big_quota": null, "fund_type": "", "is_qdii": true, "confirm_days": 1, "confirm_days_label": "T+1", "yituo6": true, "yituo6_label": "支持", "quota_label": "无限制", "premium_cycle_label": "约3天", "premium_cycle_detail": "T+1+转托管", "discount_cycle_label": "约3天", "discount_cycle_detail": "T+0买入/T+1赎", "capital": 10000, "premium_profit_gross": 97.0, "premium_profit_net": 74.0, "discount_profit_gross": 97.0, "discount_profit_net": 44.0}, {"full_code": "SZ164701", "code6": "164701", "name": "黄金LOF", "price": 1.567, "change": -0.06, "est": 1.584, "premium": -1.07, "est_date": "2026-07-15", "ref_premium": -1.07, "status": "limited", "status_text": "限制大额", "redeem_status": "open", "redeem_status_text": "正常赎回", "quota": 500.0, "big_quota": null, "fund_type": "", "is_qdii": true, "confirm_days": 2, "confirm_days_label": "T+2", "yituo6": true, "yituo6_label": "推荐", "quota_label": "500元", "premium_cycle_label": "约4天", "premium_cycle_detail": "T+2+转托管", "discount_cycle_label": "约4天", "discount_cycle_detail": "T+0买入/T+2赎", "capital": 500.0, "premium_profit_gross": 5.35, "premium_profit_net": 4.2, "discount_profit_gross": 5.35, "discount_profit_net": 2.7}, {"full_code": "SZ165513", "code6": "165513", "name": "中信保诚商品LOF", "price": 0.946, "change": -0.21, "est": 0.957, "premium": -1.15, "est_date": "2026-07-15", "ref_premium": -1.08, "status": "open", "status_text": "正常申购", "redeem_status": "open", "redeem_status_text": "正常赎回", "quota": null, "big_quota": null, "fund_type": "", "is_qdii": true, "confirm_days": 2, "confirm_days_label": "T+2", "yituo6": true, "yituo6_label": "支持", "quota_label": "无限制", "premium_cycle_label": "约4天", "premium_cycle_detail": "T+2+转托管", "discount_cycle_label": "约4天", "discount_cycle_detail": "T+0买入/T+2赎", "capital": 10000, "premium_profit_gross": 115.0, "premium_profit_net": 92.0, "discount_profit_gross": 115.0, "discount_profit_net": 62.0}, {"full_code": "SZ164824", "code6": "164824", "name": "印度基金LOF", "price": 1.283, "change": -0.23, "est": 1.298, "premium": -1.16, "est_date": "2026-07-15", "ref_premium": -1.14, "status": "limited", "status_text": "限制大额", "redeem_status": "open", "redeem_status_text": "正常赎回", "quota": 500000.0, "big_quota": null, "fund_type": "", "is_qdii": true, "confirm_days": 2, "confirm_days_label": "T+2", "yituo6": true, "yituo6_label": "支持", "quota_label": "50万", "premium_cycle_label": "约4天", "premium_cycle_detail": "T+2+转托管", "discount_cycle_label": "约4天", "discount_cycle_detail": "T+0买入/T+2赎", "capital": 10000, "premium_profit_gross": 116.0, "premium_profit_net": 93.0, "discount_profit_gross": 116.0, "discount_profit_net": 63.0}, {"full_code": "SZ160216", "code6": "160216", "name": "国泰商品LOF", "price": 0.608, "change": -0.82, "est": 0.617, "premium": -1.46, "est_date": "2026-07-15", "ref_premium": -1.5, "status": "limited", "status_text": "限制大额", "redeem_status": "open", "redeem_status_text": "正常赎回", "quota": 300000.0, "big_quota": null, "fund_type": "", "is_qdii": true, "confirm_days": 2, "confirm_days_label": "T+2", "yituo6": true, "yituo6_label": "支持", "quota_label": "30万", "premium_cycle_label": "约4天", "premium_cycle_detail": "T+2+转托管", "discount_cycle_label": "约4天", "discount_cycle_detail": "T+0买入/T+2赎", "capital": 10000, "premium_profit_gross": 146.0, "premium_profit_net": 123.0, "discount_profit_gross": 146.0, "discount_profit_net": 93.0}, {"full_code": "SZ160644", "code6": "160644", "name": "港美互联网LOF", "price": 1.796, "change": -2.71, "est": 1.842, "premium": -2.5, "est_date": "2026-07-15", "ref_premium": -3.29, "status": "closed", "status_text": "暂停申购", "redeem_status": "open", "redeem_status_text": "正常赎回", "quota": 10000.0, "big_quota": null, "fund_type": "", "is_qdii": true, "confirm_days": 2, "confirm_days_label": "T+2", "yituo6": true, "yituo6_label": "推荐", "quota_label": "1万", "premium_cycle_label": "约4天", "premium_cycle_detail": "T+2+转托管", "discount_cycle_label": "约4天", "discount_cycle_detail": "T+0买入/T+2赎", "capital": 10000.0, "premium_profit_gross": 250.0, "premium_profit_net": 227.0, "discount_profit_gross": 250.0, "discount_profit_net": 197.0, "arb_cycle_label": "约4天", "expected_profit": 197.0, "arb_type": "discount"}, {"full_code": "SZ168401", "code6": "168401", "name": "红土创新精选LOF", "price": 7.007, "change": -4.18, "est": 7.204, "premium": -2.73, "est_date": "2026-07-16", "ref_premium": null, "status": "open", "status_text": "正常申购", "redeem_status": "open", "redeem_status_text": "正常赎回", "quota": null, "big_quota": null, "fund_type": "", "is_qdii": false, "confirm_days": 1, "confirm_days_label": "T+1", "yituo6": true, "yituo6_label": "支持", "quota_label": "无限制", "premium_cycle_label": "约3天", "premium_cycle_detail": "T+1+转托管", "discount_cycle_label": "约3天", "discount_cycle_detail": "T+0买入/T+1赎", "capital": 10000, "premium_profit_gross": 273.0, "premium_profit_net": 250.0, "discount_profit_gross": 273.0, "discount_profit_net": 220.0, "arb_cycle_label": "约3天", "expected_profit": 220.0, "arb_type": "discount"}, {"full_code": "SZ160706", "code6": "160706", "name": "沪深300LOF", "price": 1.216, "change": -0.9, "est": 1.216, "premium": 0.0, "est_date": "2026-07-16", "ref_premium": null, "status": "open", "status_text": "正常申购", "redeem_status": "open", "redeem_status_text": "正常赎回", "quota": null, "big_quota": null, "fund_type": "", "is_qdii": false, "confirm_days": 1, "confirm_days_label": "T+1", "yituo6": true, "yituo6_label": "支持", "quota_label": "无限制", "premium_cycle_label": "约3天", "premium_cycle_detail": "T+1+转托管", "discount_cycle_label": "约3天", "discount_cycle_detail": "T+0买入/T+1赎", "capital": 10000, "premium_profit_gross": 0.0, "premium_profit_net": -23.0, "discount_profit_gross": 0.0, "discount_profit_net": -53.0}, {"full_code": "SZ161126", "code6": "161126", "name": "标普医疗保健LOF", "price": 1.96, "change": 0.0, "est": 1.96, "premium": 0.0, "est_date": "2026-07-15", "ref_premium": -0.06, "status": "closed", "status_text": "暂停申购", "redeem_status": "open", "redeem_status_text": "正常赎回", "quota": 10.0, "big_quota": null, "fund_type": "", "is_qdii": true, "confirm_days": 2, "confirm_days_label": "T+2", "yituo6": true, "yituo6_label": "推荐", "quota_label": "10元", "premium_cycle_label": "约4天", "premium_cycle_detail": "T+2+转托管", "discount_cycle_label": "约4天", "discount_cycle_detail": "T+0买入/T+2赎", "capital": 10.0, "premium_profit_gross": 0.0, "premium_profit_net": -0.02, "discount_profit_gross": 0.0, "discount_profit_net": -0.05}, {"full_code": "SZ167301", "code6": "167301", "name": "保险主题LOF", "price": 1.027, "change": -0.87, "est": 1.027, "premium": 0.0, "est_date": "2026-07-16", "ref_premium": null, "status": "open", "status_text": "正常申购", "redeem_status": "open", "redeem_status_text": "正常赎回", "quota": null, "big_quota": null, "fund_type": "", "is_qdii": false, "confirm_days": 1, "confirm_days_label": "T+1", "yituo6": true, "yituo6_label": "支持", "quota_label": "无限制", "premium_cycle_label": "约3天", "premium_cycle_detail": "T+1+转托管", "discount_cycle_label": "约3天", "discount_cycle_detail": "T+0买入/T+1赎", "capital": 10000, "premium_profit_gross": 0.0, "premium_profit_net": -23.0, "discount_profit_gross": 0.0, "discount_profit_net": -53.0}], "prevPremiums": {"SH501225": 24.88, "SH501018": 17.38, "SZ160723": 15.46, "SZ161129": 13.98, "SZ160644": 11.85, "SZ161128": 3.48, "SZ161130": 3.05, "SZ162719": 2.82, "SZ161226": 2.19, "SZ160416": 0.71, "SZ163208": 0.46, "SZ162411": 0.44, "SH501312": 0.43, "SZ161125": 0.11, "SZ160216": -0.07, "SZ161831": -0.1, "SZ160717": -0.19, "SZ164705": -0.19, "SH501043": -0.25, "SZ161815": -0.28, "SZ160924": -0.32, "SH501300": -0.34, "SH501302": -0.41, "SZ161126": -0.43, "SZ161127": -0.49, "SZ161116": -0.51, "SZ162415": -0.51, "SH501025": -0.53, "SZ164701": -0.62, "SZ160140": -0.67, "SZ165513": -0.72, "SZ160719": -0.72, "SZ164824": -0.76, "SZ161124": -0.77, "SZ164906": -0.78}}