{"now": "2026-07-23 14:52", "session": "开盘中", "sessionLegacy": "午盘", "defaultCapital": 10000, "feeRates": {"sub": 0.0015, "sell": 0.0008, "buy": 0.0003, "redeem": 0.005}, "thresholds": {"premium": 0, "discount": -1.5}, "summary": {"premiumCount": 3, "discountCount": 1, "posCount": 17, "negCount": 34, "avgPremium": 1.72}, "premiumArb": [{"full_code": "SZ161812", "code6": "161812", "name": "深证100LOF", "price": 1.447, "change": 1.47, "est": 1.429, "premium": 1.26, "est_date": "2026-07-23", "ref_premium": null, "status": "open", "status_text": "正常申购", "redeem_status": "open", "redeem_status_text": "正常赎回", "quota": null, "big_quota": null, "fund_type": "", "is_qdii": false, "confirm_days": 1, "confirm_days_label": "T+1", "yituo6": true, "yituo6_label": "支持", "quota_label": "无限制", "premium_cycle_label": "约3天", "premium_cycle_detail": "T+1+转托管", "discount_cycle_label": "约3天", "discount_cycle_detail": "T+0买入/T+1赎", "capital": 10000, "premium_profit_gross": 126.0, "premium_profit_net": 103.0, "discount_profit_gross": 126.0, "discount_profit_net": 73.0, "arb_cycle_label": "约3天", "expected_profit": 103.0, "arb_type": "premium"}, {"full_code": "SZ161005", "code6": "161005", "name": "富国天惠LOF", "price": 3.127, "change": 0.68, "est": 3.103, "premium": 0.77, "est_date": "2026-07-23", "ref_premium": null, "status": "limited", "status_text": "限制大额", "redeem_status": "open", "redeem_status_text": "正常赎回", "quota": 20000.0, "big_quota": null, "fund_type": "", "is_qdii": false, "confirm_days": 1, "confirm_days_label": "T+1", "yituo6": true, "yituo6_label": "推荐", "quota_label": "2万", "premium_cycle_label": "约3天", "premium_cycle_detail": "T+1+转托管", "discount_cycle_label": "约3天", "discount_cycle_detail": "T+0买入/T+1赎", "capital": 10000, "premium_profit_gross": 77.0, "premium_profit_net": 54.0, "discount_profit_gross": 77.0, "discount_profit_net": 24.0, "arb_cycle_label": "约3天", "expected_profit": 54.0, "arb_type": "premium"}, {"full_code": "SZ164906", "code6": "164906", "name": "中概互联网LOF", "price": 0.952, "change": 0.95, "est": 0.949, "premium": 0.32, "est_date": "2026-07-22", "ref_premium": -0.44, "status": "open", "status_text": "正常申购", "redeem_status": "open", "redeem_status_text": "正常赎回", "quota": null, "big_quota": null, "fund_type": "", "is_qdii": true, "confirm_days": 2, "confirm_days_label": "T+2", "yituo6": true, "yituo6_label": "支持", "quota_label": "无限制", "premium_cycle_label": "约4天", "premium_cycle_detail": "T+2+转托管", "discount_cycle_label": "约4天", "discount_cycle_detail": "T+0买入/T+2赎", "capital": 10000, "premium_profit_gross": 32.0, "premium_profit_net": 9.0, "discount_profit_gross": 32.0, "discount_profit_net": -21.0, "arb_cycle_label": "约4天", "expected_profit": 9.0, "arb_type": "premium"}], "discountArb": [{"full_code": "SZ168401", "code6": "168401", "name": "红土创新精选LOF", "price": 6.196, "change": -2.19, "est": 6.332, "premium": -2.15, "est_date": "2026-07-23", "ref_premium": null, "status": "open", "status_text": "正常申购", "redeem_status": "open", "redeem_status_text": "正常赎回", "quota": null, "big_quota": null, "fund_type": "", "is_qdii": false, "confirm_days": 1, "confirm_days_label": "T+1", "yituo6": true, "yituo6_label": "支持", "quota_label": "无限制", "premium_cycle_label": "约3天", "premium_cycle_detail": "T+1+转托管", "discount_cycle_label": "约3天", "discount_cycle_detail": "T+0买入/T+1赎", "capital": 10000, "premium_profit_gross": 215.0, "premium_profit_net": 192.0, "discount_profit_gross": 215.0, "discount_profit_net": 162.0, "arb_cycle_label": "约3天", "expected_profit": 162.0, "arb_type": "discount"}], "blocked": [{"full_code": "SH501225", "code6": "501225", "name": "全球芯片LOF", "price": 3.989, "change": -2.18, "est": 3.233, "premium": 23.38, "est_date": "2026-07-22", "ref_premium": 24.57, "status": "closed", "status_text": "暂停申购", "redeem_status": "open", "redeem_status_text": "正常赎回", "quota": 100.0, "big_quota": null, "fund_type": "", "is_qdii": true, "confirm_days": 2, "confirm_days_label": "T+2", "yituo6": false, "yituo6_label": "仅深市", "quota_label": "100元", "premium_cycle_label": "约4天", "premium_cycle_detail": "T+2+转托管", "discount_cycle_label": "约4天", "discount_cycle_detail": "T+0买入/T+2赎", "capital": 100.0, "premium_profit_gross": 23.38, "premium_profit_net": 23.15, "discount_profit_gross": 23.38, "discount_profit_net": 22.85, "block_reason": "溢价但不可申购"}, {"full_code": "SZ161129", "code6": "161129", "name": "原油LOF易方达", "price": 2.12, "change": 5.0, "est": 1.726, "premium": 22.83, "est_date": "2026-07-22", "ref_premium": 22.6, "status": "closed", "status_text": "暂停申购", "redeem_status": "open", "redeem_status_text": "正常赎回", "quota": 10.0, "big_quota": null, "fund_type": "", "is_qdii": true, "confirm_days": 2, "confirm_days_label": "T+2", "yituo6": true, "yituo6_label": "推荐", "quota_label": "10元", "premium_cycle_label": "约4天", "premium_cycle_detail": "T+2+转托管", "discount_cycle_label": "约4天", "discount_cycle_detail": "T+0买入/T+2赎", "capital": 10.0, "premium_profit_gross": 2.28, "premium_profit_net": 2.26, "discount_profit_gross": 2.28, "discount_profit_net": 2.23, "block_reason": "溢价但不可申购"}, {"full_code": "SH501018", "code6": "501018", "name": "南方原油LOF", "price": 2.158, "change": 2.08, "est": 1.799, "premium": 19.96, "est_date": "2026-07-22", "ref_premium": 19.37, "status": "closed", "status_text": "暂停申购", "redeem_status": "open", "redeem_status_text": "正常赎回", "quota": 0.0, "big_quota": null, "fund_type": "", "is_qdii": true, "confirm_days": 2, "confirm_days_label": "T+2", "yituo6": false, "yituo6_label": "仅深市", "quota_label": "无限制", "premium_cycle_label": "约4天", "premium_cycle_detail": "T+2+转托管", "discount_cycle_label": "约4天", "discount_cycle_detail": "T+0买入/T+2赎", "capital": 10000, "premium_profit_gross": 1996.0, "premium_profit_net": 1973.0, "discount_profit_gross": 1996.0, "discount_profit_net": 1943.0, "block_reason": "溢价但不可申购"}, {"full_code": "SZ160723", "code6": "160723", "name": "嘉实原油LOF", "price": 2.421, "change": 4.22, "est": 2.049, "premium": 18.16, "est_date": "2026-07-22", "ref_premium": 18.05, "status": "closed", "status_text": "暂停申购", "redeem_status": "open", "redeem_status_text": "正常赎回", "quota": 5.0, "big_quota": null, "fund_type": "", "is_qdii": true, "confirm_days": 2, "confirm_days_label": "T+2", "yituo6": true, "yituo6_label": "推荐", "quota_label": "5元", "premium_cycle_label": "约4天", "premium_cycle_detail": "T+2+转托管", "discount_cycle_label": "约4天", "discount_cycle_detail": "T+0买入/T+2赎", "capital": 5.0, "premium_profit_gross": 0.91, "premium_profit_net": 0.9, "discount_profit_gross": 0.91, "discount_profit_net": 0.88, "block_reason": "溢价但不可申购"}, {"full_code": "SZ161226", "code6": "161226", "name": "国投白银LOF", "price": 1.892, "change": -0.53, "est": 1.667, "premium": 13.5, "est_date": "2026-07-23", "ref_premium": 14.4, "status": "closed", "status_text": "暂停申购", "redeem_status": "open", "redeem_status_text": "正常赎回", "quota": 100.0, "big_quota": null, "fund_type": "", "is_qdii": false, "confirm_days": 1, "confirm_days_label": "T+1", "yituo6": true, "yituo6_label": "推荐", "quota_label": "100元", "premium_cycle_label": "约3天", "premium_cycle_detail": "T+1+转托管", "discount_cycle_label": "约3天", "discount_cycle_detail": "T+0买入/T+1赎", "capital": 100.0, "premium_profit_gross": 13.5, "premium_profit_net": 13.27, "discount_profit_gross": 13.5, "discount_profit_net": 12.97, "block_reason": "溢价但不可申购"}, {"full_code": "SZ161130", "code6": "161130", "name": "纳斯达克100LOF", "price": 4.511, "change": 0.13, "est": 4.378, "premium": 3.04, "est_date": "2026-07-22", "ref_premium": 3.07, "status": "closed", "status_text": "暂停申购", "redeem_status": "open", "redeem_status_text": "正常赎回", "quota": 10.0, "big_quota": null, "fund_type": "", "is_qdii": true, "confirm_days": 2, "confirm_days_label": "T+2", "yituo6": true, "yituo6_label": "推荐", "quota_label": "10元", "premium_cycle_label": "约4天", "premium_cycle_detail": "T+2+转托管", "discount_cycle_label": "约4天", "discount_cycle_detail": "T+0买入/T+2赎", "capital": 10.0, "premium_profit_gross": 0.3, "premium_profit_net": 0.28, "discount_profit_gross": 0.3, "discount_profit_net": 0.25, "block_reason": "溢价但不可申购"}, {"full_code": "SZ161128", "code6": "161128", "name": "标普信息科技LOF", "price": 6.694, "change": 0.98, "est": 6.524, "premium": 2.61, "est_date": "2026-07-22", "ref_premium": 2.65, "status": "closed", "status_text": "暂停申购", "redeem_status": "open", "redeem_status_text": "正常赎回", "quota": 10.0, "big_quota": null, "fund_type": "", "is_qdii": true, "confirm_days": 2, "confirm_days_label": "T+2", "yituo6": true, "yituo6_label": "推荐", "quota_label": "10元", "premium_cycle_label": "约4天", "premium_cycle_detail": "T+2+转托管", "discount_cycle_label": "约4天", "discount_cycle_detail": "T+0买入/T+2赎", "capital": 10.0, "premium_profit_gross": 0.26, "premium_profit_net": 0.24, "discount_profit_gross": 0.26, "discount_profit_net": 0.21, "block_reason": "溢价但不可申购"}, {"full_code": "SZ161125", "code6": "161125", "name": "标普500LOF", "price": 3.151, "change": -0.19, "est": 3.089, "premium": 2.01, "est_date": "2026-07-22", "ref_premium": 2.02, "status": "closed", "status_text": "暂停申购", "redeem_status": "open", "redeem_status_text": "正常赎回", "quota": 10.0, "big_quota": null, "fund_type": "", "is_qdii": true, "confirm_days": 2, "confirm_days_label": "T+2", "yituo6": true, "yituo6_label": "推荐", "quota_label": "10元", "premium_cycle_label": "约4天", "premium_cycle_detail": "T+2+转托管", "discount_cycle_label": "约4天", "discount_cycle_detail": "T+0买入/T+2赎", "capital": 10.0, "premium_profit_gross": 0.2, "premium_profit_net": 0.18, "discount_profit_gross": 0.2, "discount_profit_net": 0.15, "block_reason": "溢价但不可申购"}, {"full_code": "SZ162411", "code6": "162411", "name": "华宝油气LOF", "price": 0.945, "change": 1.18, "est": 0.932, "premium": 1.39, "est_date": "2026-07-22", "ref_premium": 1.44, "status": "closed", "status_text": "暂停申购", "redeem_status": "open", "redeem_status_text": "正常赎回", "quota": 10.0, "big_quota": null, "fund_type": "", "is_qdii": true, "confirm_days": 2, "confirm_days_label": "T+2", "yituo6": true, "yituo6_label": "推荐", "quota_label": "10元", "premium_cycle_label": "约4天", "premium_cycle_detail": "T+2+转托管", "discount_cycle_label": "约4天", "discount_cycle_detail": "T+0买入/T+2赎", "capital": 10.0, "premium_profit_gross": 0.14, "premium_profit_net": 0.12, "discount_profit_gross": 0.14, "discount_profit_net": 0.09, "block_reason": "溢价但不可申购"}, {"full_code": "SZ162719", "code6": "162719", "name": "石油LOF", "price": 2.869, "change": 1.16, "est": 2.852, "premium": 0.6, "est_date": "2026-07-22", "ref_premium": 0.65, "status": "closed", "status_text": "暂停申购", "redeem_status": "open", "redeem_status_text": "正常赎回", "quota": 10.0, "big_quota": null, "fund_type": "", "is_qdii": true, "confirm_days": 2, "confirm_days_label": "T+2", "yituo6": true, "yituo6_label": "推荐", "quota_label": "10元", "premium_cycle_label": "约4天", "premium_cycle_detail": "T+2+转托管", "discount_cycle_label": "约4天", "discount_cycle_detail": "T+0买入/T+2赎", "capital": 10.0, "premium_profit_gross": 0.06, "premium_profit_net": 0.04, "discount_profit_gross": 0.06, "discount_profit_net": 0.01, "block_reason": "溢价但不可申购"}, {"full_code": "SZ160416", "code6": "160416", "name": "石油基金LOF", "price": 2.121, "change": 1.19, "est": 2.114, "premium": 0.33, "est_date": "2026-07-22", "ref_premium": 0.42, "status": "closed", "status_text": "暂停申购", "redeem_status": "open", "redeem_status_text": "正常赎回", "quota": 2.0, "big_quota": null, "fund_type": "", "is_qdii": true, "confirm_days": 2, "confirm_days_label": "T+2", "yituo6": true, "yituo6_label": "推荐", "quota_label": "2元", "premium_cycle_label": "约4天", "premium_cycle_detail": "T+2+转托管", "discount_cycle_label": "约4天", "discount_cycle_detail": "T+0买入/T+2赎", "capital": 2.0, "premium_profit_gross": 0.01, "premium_profit_net": 0.0, "discount_profit_gross": 0.01, "discount_profit_net": -0.0, "block_reason": "溢价但不可申购"}, {"full_code": "SZ163208", "code6": "163208", "name": "全球油气能源LOF", "price": 1.337, "change": 1.52, "est": 1.333, "premium": 0.3, "est_date": "2026-07-22", "ref_premium": 0.33, "status": "closed", "status_text": "暂停申购", "redeem_status": "open", "redeem_status_text": "正常赎回", "quota": 500.0, "big_quota": null, "fund_type": "", "is_qdii": true, "confirm_days": 2, "confirm_days_label": "T+2", "yituo6": true, "yituo6_label": "推荐", "quota_label": "500元", "premium_cycle_label": "约4天", "premium_cycle_detail": "T+2+转托管", "discount_cycle_label": "约4天", "discount_cycle_detail": "T+0买入/T+2赎", "capital": 500.0, "premium_profit_gross": 1.5, "premium_profit_net": 0.35, "discount_profit_gross": 1.5, "discount_profit_net": -1.15, "block_reason": "溢价但不可申购"}, {"full_code": "SZ161116", "code6": "161116", "name": "黄金主题LOF", "price": 1.543, "change": -0.19, "est": 1.54, "premium": 0.19, "est_date": "2026-07-22", "ref_premium": 0.22, "status": "closed", "status_text": "暂停申购", "redeem_status": "open", "redeem_status_text": "正常赎回", "quota": 10.0, "big_quota": null, "fund_type": "", "is_qdii": true, "confirm_days": 2, "confirm_days_label": "T+2", "yituo6": true, "yituo6_label": "推荐", "quota_label": "10元", "premium_cycle_label": "约4天", "premium_cycle_detail": "T+2+转托管", "discount_cycle_label": "约4天", "discount_cycle_detail": "T+0买入/T+2赎", "capital": 10.0, "premium_profit_gross": 0.02, "premium_profit_net": -0.0, "discount_profit_gross": 0.02, "discount_profit_net": -0.03, "block_reason": "溢价但不可申购"}, {"full_code": "SZ160644", "code6": "160644", "name": "港美互联网LOF", "price": 1.75, "change": 3.18, "est": 1.748, "premium": 0.11, "est_date": "2026-07-22", "ref_premium": -0.58, "status": "closed", "status_text": "暂停申购", "redeem_status": "open", "redeem_status_text": "正常赎回", "quota": 10000.0, "big_quota": null, "fund_type": "", "is_qdii": true, "confirm_days": 2, "confirm_days_label": "T+2", "yituo6": true, "yituo6_label": "推荐", "quota_label": "1万", "premium_cycle_label": "约4天", "premium_cycle_detail": "T+2+转托管", "discount_cycle_label": "约4天", "discount_cycle_detail": "T+0买入/T+2赎", "capital": 10000.0, "premium_profit_gross": 11.0, "premium_profit_net": -12.0, "discount_profit_gross": 11.0, "discount_profit_net": -42.0, "block_reason": "溢价但不可申购"}], "allRows": [{"full_code": "SH501225", "code6": "501225", "name": "全球芯片LOF", "price": 3.989, "change": -2.18, "est": 3.233, "premium": 23.38, "est_date": "2026-07-22", "ref_premium": 24.57, "status": "closed", "status_text": "暂停申购", "redeem_status": "open", "redeem_status_text": "正常赎回", "quota": 100.0, "big_quota": null, "fund_type": "", "is_qdii": true, "confirm_days": 2, "confirm_days_label": "T+2", "yituo6": false, "yituo6_label": "仅深市", "quota_label": "100元", "premium_cycle_label": "约4天", "premium_cycle_detail": "T+2+转托管", "discount_cycle_label": "约4天", "discount_cycle_detail": "T+0买入/T+2赎", "capital": 100.0, "premium_profit_gross": 23.38, "premium_profit_net": 23.15, "discount_profit_gross": 23.38, "discount_profit_net": 22.85}, {"full_code": "SZ161129", "code6": "161129", "name": "原油LOF易方达", "price": 2.12, "change": 5.0, "est": 1.726, "premium": 22.83, "est_date": "2026-07-22", "ref_premium": 22.6, "status": "closed", "status_text": "暂停申购", "redeem_status": "open", "redeem_status_text": "正常赎回", "quota": 10.0, "big_quota": null, "fund_type": "", "is_qdii": true, "confirm_days": 2, "confirm_days_label": "T+2", "yituo6": true, "yituo6_label": "推荐", "quota_label": "10元", "premium_cycle_label": "约4天", "premium_cycle_detail": "T+2+转托管", "discount_cycle_label": "约4天", "discount_cycle_detail": "T+0买入/T+2赎", "capital": 10.0, "premium_profit_gross": 2.28, "premium_profit_net": 2.26, "discount_profit_gross": 2.28, "discount_profit_net": 2.23}, {"full_code": "SH501018", "code6": "501018", "name": "南方原油LOF", "price": 2.158, "change": 2.08, "est": 1.799, "premium": 19.96, "est_date": "2026-07-22", "ref_premium": 19.37, "status": "closed", "status_text": "暂停申购", "redeem_status": "open", "redeem_status_text": "正常赎回", "quota": 0.0, "big_quota": null, "fund_type": "", "is_qdii": true, "confirm_days": 2, "confirm_days_label": "T+2", "yituo6": false, "yituo6_label": "仅深市", "quota_label": "无限制", "premium_cycle_label": "约4天", "premium_cycle_detail": "T+2+转托管", "discount_cycle_label": "约4天", "discount_cycle_detail": "T+0买入/T+2赎", "capital": 10000, "premium_profit_gross": 1996.0, "premium_profit_net": 1973.0, "discount_profit_gross": 1996.0, "discount_profit_net": 1943.0}, {"full_code": "SZ160723", "code6": "160723", "name": "嘉实原油LOF", "price": 2.421, "change": 4.22, "est": 2.049, "premium": 18.16, "est_date": "2026-07-22", "ref_premium": 18.05, "status": "closed", "status_text": "暂停申购", "redeem_status": "open", "redeem_status_text": "正常赎回", "quota": 5.0, "big_quota": null, "fund_type": "", "is_qdii": true, "confirm_days": 2, "confirm_days_label": "T+2", "yituo6": true, "yituo6_label": "推荐", "quota_label": "5元", "premium_cycle_label": "约4天", "premium_cycle_detail": "T+2+转托管", "discount_cycle_label": "约4天", "discount_cycle_detail": "T+0买入/T+2赎", "capital": 5.0, "premium_profit_gross": 0.91, "premium_profit_net": 0.9, "discount_profit_gross": 0.91, "discount_profit_net": 0.88}, {"full_code": "SZ161226", "code6": "161226", "name": "国投白银LOF", "price": 1.892, "change": -0.53, "est": 1.667, "premium": 13.5, "est_date": "2026-07-23", "ref_premium": 14.4, "status": "closed", "status_text": "暂停申购", "redeem_status": "open", "redeem_status_text": "正常赎回", "quota": 100.0, "big_quota": null, "fund_type": "", "is_qdii": false, "confirm_days": 1, "confirm_days_label": "T+1", "yituo6": true, "yituo6_label": "推荐", "quota_label": "100元", "premium_cycle_label": "约3天", "premium_cycle_detail": "T+1+转托管", "discount_cycle_label": "约3天", "discount_cycle_detail": "T+0买入/T+1赎", "capital": 100.0, "premium_profit_gross": 13.5, "premium_profit_net": 13.27, "discount_profit_gross": 13.5, "discount_profit_net": 12.97}, {"full_code": "SZ161130", "code6": "161130", "name": "纳斯达克100LOF", "price": 4.511, "change": 0.13, "est": 4.378, "premium": 3.04, "est_date": "2026-07-22", "ref_premium": 3.07, "status": "closed", "status_text": "暂停申购", "redeem_status": "open", "redeem_status_text": "正常赎回", "quota": 10.0, "big_quota": null, "fund_type": "", "is_qdii": true, "confirm_days": 2, "confirm_days_label": "T+2", "yituo6": true, "yituo6_label": "推荐", "quota_label": "10元", "premium_cycle_label": "约4天", "premium_cycle_detail": "T+2+转托管", "discount_cycle_label": "约4天", "discount_cycle_detail": "T+0买入/T+2赎", "capital": 10.0, "premium_profit_gross": 0.3, "premium_profit_net": 0.28, "discount_profit_gross": 0.3, "discount_profit_net": 0.25}, {"full_code": "SZ161128", "code6": "161128", "name": "标普信息科技LOF", "price": 6.694, "change": 0.98, "est": 6.524, "premium": 2.61, "est_date": "2026-07-22", "ref_premium": 2.65, "status": "closed", "status_text": "暂停申购", "redeem_status": "open", "redeem_status_text": "正常赎回", "quota": 10.0, "big_quota": null, "fund_type": "", "is_qdii": true, "confirm_days": 2, "confirm_days_label": "T+2", "yituo6": true, "yituo6_label": "推荐", "quota_label": "10元", "premium_cycle_label": "约4天", "premium_cycle_detail": "T+2+转托管", "discount_cycle_label": "约4天", "discount_cycle_detail": "T+0买入/T+2赎", "capital": 10.0, "premium_profit_gross": 0.26, "premium_profit_net": 0.24, "discount_profit_gross": 0.26, "discount_profit_net": 0.21}, {"full_code": "SZ161125", "code6": "161125", "name": "标普500LOF", "price": 3.151, "change": -0.19, "est": 3.089, "premium": 2.01, "est_date": "2026-07-22", "ref_premium": 2.02, "status": "closed", "status_text": "暂停申购", "redeem_status": "open", "redeem_status_text": "正常赎回", "quota": 10.0, "big_quota": null, "fund_type": "", "is_qdii": true, "confirm_days": 2, "confirm_days_label": "T+2", "yituo6": true, "yituo6_label": "推荐", "quota_label": "10元", "premium_cycle_label": "约4天", "premium_cycle_detail": "T+2+转托管", "discount_cycle_label": "约4天", "discount_cycle_detail": "T+0买入/T+2赎", "capital": 10.0, "premium_profit_gross": 0.2, "premium_profit_net": 0.18, "discount_profit_gross": 0.2, "discount_profit_net": 0.15}, {"full_code": "SZ162411", "code6": "162411", "name": "华宝油气LOF", "price": 0.945, "change": 1.18, "est": 0.932, "premium": 1.39, "est_date": "2026-07-22", "ref_premium": 1.44, "status": "closed", "status_text": "暂停申购", "redeem_status": "open", "redeem_status_text": "正常赎回", "quota": 10.0, "big_quota": null, "fund_type": "", "is_qdii": true, "confirm_days": 2, "confirm_days_label": "T+2", "yituo6": true, "yituo6_label": "推荐", "quota_label": "10元", "premium_cycle_label": "约4天", "premium_cycle_detail": "T+2+转托管", "discount_cycle_label": "约4天", "discount_cycle_detail": "T+0买入/T+2赎", "capital": 10.0, "premium_profit_gross": 0.14, "premium_profit_net": 0.12, "discount_profit_gross": 0.14, "discount_profit_net": 0.09}, {"full_code": "SZ161812", "code6": "161812", "name": "深证100LOF", "price": 1.447, "change": 1.47, "est": 1.429, "premium": 1.26, "est_date": "2026-07-23", "ref_premium": null, "status": "open", "status_text": "正常申购", "redeem_status": "open", "redeem_status_text": "正常赎回", "quota": null, "big_quota": null, "fund_type": "", "is_qdii": false, "confirm_days": 1, "confirm_days_label": "T+1", "yituo6": true, "yituo6_label": "支持", "quota_label": "无限制", "premium_cycle_label": "约3天", "premium_cycle_detail": "T+1+转托管", "discount_cycle_label": "约3天", "discount_cycle_detail": "T+0买入/T+1赎", "capital": 10000, "premium_profit_gross": 126.0, "premium_profit_net": 103.0, "discount_profit_gross": 126.0, "discount_profit_net": 73.0, "arb_cycle_label": "约3天", "expected_profit": 103.0, "arb_type": "premium"}, {"full_code": "SZ161005", "code6": "161005", "name": "富国天惠LOF", "price": 3.127, "change": 0.68, "est": 3.103, "premium": 0.77, "est_date": "2026-07-23", "ref_premium": null, "status": "limited", "status_text": "限制大额", "redeem_status": "open", "redeem_status_text": "正常赎回", "quota": 20000.0, "big_quota": null, "fund_type": "", "is_qdii": false, "confirm_days": 1, "confirm_days_label": "T+1", "yituo6": true, "yituo6_label": "推荐", "quota_label": "2万", "premium_cycle_label": "约3天", "premium_cycle_detail": "T+1+转托管", "discount_cycle_label": "约3天", "discount_cycle_detail": "T+0买入/T+1赎", "capital": 10000, "premium_profit_gross": 77.0, "premium_profit_net": 54.0, "discount_profit_gross": 77.0, "discount_profit_net": 24.0, "arb_cycle_label": "约3天", "expected_profit": 54.0, "arb_type": "premium"}, {"full_code": "SZ162719", "code6": "162719", "name": "石油LOF", "price": 2.869, "change": 1.16, "est": 2.852, "premium": 0.6, "est_date": "2026-07-22", "ref_premium": 0.65, "status": "closed", "status_text": "暂停申购", "redeem_status": "open", "redeem_status_text": "正常赎回", "quota": 10.0, "big_quota": null, "fund_type": "", "is_qdii": true, "confirm_days": 2, "confirm_days_label": "T+2", "yituo6": true, "yituo6_label": "推荐", "quota_label": "10元", "premium_cycle_label": "约4天", "premium_cycle_detail": "T+2+转托管", "discount_cycle_label": "约4天", "discount_cycle_detail": "T+0买入/T+2赎", "capital": 10.0, "premium_profit_gross": 0.06, "premium_profit_net": 0.04, "discount_profit_gross": 0.06, "discount_profit_net": 0.01}, {"full_code": "SZ160416", "code6": "160416", "name": "石油基金LOF", "price": 2.121, "change": 1.19, "est": 2.114, "premium": 0.33, "est_date": "2026-07-22", "ref_premium": 0.42, "status": "closed", "status_text": "暂停申购", "redeem_status": "open", "redeem_status_text": "正常赎回", "quota": 2.0, "big_quota": null, "fund_type": "", "is_qdii": true, "confirm_days": 2, "confirm_days_label": "T+2", "yituo6": true, "yituo6_label": "推荐", "quota_label": "2元", "premium_cycle_label": "约4天", "premium_cycle_detail": "T+2+转托管", "discount_cycle_label": "约4天", "discount_cycle_detail": "T+0买入/T+2赎", "capital": 2.0, "premium_profit_gross": 0.01, "premium_profit_net": 0.0, "discount_profit_gross": 0.01, "discount_profit_net": -0.0}, {"full_code": "SZ164906", "code6": "164906", "name": "中概互联网LOF", "price": 0.952, "change": 0.95, "est": 0.949, "premium": 0.32, "est_date": "2026-07-22", "ref_premium": -0.44, "status": "open", "status_text": "正常申购", "redeem_status": "open", "redeem_status_text": "正常赎回", "quota": null, "big_quota": null, "fund_type": "", "is_qdii": true, "confirm_days": 2, "confirm_days_label": "T+2", "yituo6": true, "yituo6_label": "支持", "quota_label": "无限制", "premium_cycle_label": "约4天", "premium_cycle_detail": "T+2+转托管", "discount_cycle_label": "约4天", "discount_cycle_detail": "T+0买入/T+2赎", "capital": 10000, "premium_profit_gross": 32.0, "premium_profit_net": 9.0, "discount_profit_gross": 32.0, "discount_profit_net": -21.0, "arb_cycle_label": "约4天", "expected_profit": 9.0, "arb_type": "premium"}, {"full_code": "SZ163208", "code6": "163208", "name": "全球油气能源LOF", "price": 1.337, "change": 1.52, "est": 1.333, "premium": 0.3, "est_date": "2026-07-22", "ref_premium": 0.33, "status": "closed", "status_text": "暂停申购", "redeem_status": "open", "redeem_status_text": "正常赎回", "quota": 500.0, "big_quota": null, "fund_type": "", "is_qdii": true, "confirm_days": 2, "confirm_days_label": "T+2", "yituo6": true, "yituo6_label": "推荐", "quota_label": "500元", "premium_cycle_label": "约4天", "premium_cycle_detail": "T+2+转托管", "discount_cycle_label": "约4天", "discount_cycle_detail": "T+0买入/T+2赎", "capital": 500.0, "premium_profit_gross": 1.5, "premium_profit_net": 0.35, "discount_profit_gross": 1.5, "discount_profit_net": -1.15}, {"full_code": "SZ161116", "code6": "161116", "name": "黄金主题LOF", "price": 1.543, "change": -0.19, "est": 1.54, "premium": 0.19, "est_date": "2026-07-22", "ref_premium": 0.22, "status": "closed", "status_text": "暂停申购", "redeem_status": "open", "redeem_status_text": "正常赎回", "quota": 10.0, "big_quota": null, "fund_type": "", "is_qdii": true, "confirm_days": 2, "confirm_days_label": "T+2", "yituo6": true, "yituo6_label": "推荐", "quota_label": "10元", "premium_cycle_label": "约4天", "premium_cycle_detail": "T+2+转托管", "discount_cycle_label": "约4天", "discount_cycle_detail": "T+0买入/T+2赎", "capital": 10.0, "premium_profit_gross": 0.02, "premium_profit_net": -0.0, "discount_profit_gross": 0.02, "discount_profit_net": -0.03}, {"full_code": "SZ160644", "code6": "160644", "name": "港美互联网LOF", "price": 1.75, "change": 3.18, "est": 1.748, "premium": 0.11, "est_date": "2026-07-22", "ref_premium": -0.58, "status": "closed", "status_text": "暂停申购", "redeem_status": "open", "redeem_status_text": "正常赎回", "quota": 10000.0, "big_quota": null, "fund_type": "", "is_qdii": true, "confirm_days": 2, "confirm_days_label": "T+2", "yituo6": true, "yituo6_label": "推荐", "quota_label": "1万", "premium_cycle_label": "约4天", "premium_cycle_detail": "T+2+转托管", "discount_cycle_label": "约4天", "discount_cycle_detail": "T+0买入/T+2赎", "capital": 10000.0, "premium_profit_gross": 11.0, "premium_profit_net": -12.0, "discount_profit_gross": 11.0, "discount_profit_net": -42.0}, {"full_code": "SZ161126", "code6": "161126", "name": "标普医疗保健LOF", "price": 1.941, "change": -1.37, "est": 1.942, "premium": -0.05, "est_date": "2026-07-22", "ref_premium": 0.0, "status": "closed", "status_text": "暂停申购", "redeem_status": "open", "redeem_status_text": "正常赎回", "quota": 10.0, "big_quota": null, "fund_type": "", "is_qdii": true, "confirm_days": 2, "confirm_days_label": "T+2", "yituo6": true, "yituo6_label": "推荐", "quota_label": "10元", "premium_cycle_label": "约4天", "premium_cycle_detail": "T+2+转托管", "discount_cycle_label": "约4天", "discount_cycle_detail": "T+0买入/T+2赎", "capital": 10.0, "premium_profit_gross": 0.01, "premium_profit_net": -0.02, "discount_profit_gross": 0.01, "discount_profit_net": -0.05}, {"full_code": "SZ164705", "code6": "164705", "name": "恒生LOF", "price": 1.129, "change": 1.26, "est": 1.13, "premium": -0.09, "est_date": "2026-07-23", "ref_premium": null, "status": "open", "status_text": "正常申购", "redeem_status": "open", "redeem_status_text": "正常赎回", "quota": null, "big_quota": null, "fund_type": "", "is_qdii": true, "confirm_days": 1, "confirm_days_label": "T+1", "yituo6": true, "yituo6_label": "支持", "quota_label": "无限制", "premium_cycle_label": "约3天", "premium_cycle_detail": "T+1+转托管", "discount_cycle_label": "约3天", "discount_cycle_detail": "T+0买入/T+1赎", "capital": 10000, "premium_profit_gross": 9.0, "premium_profit_net": -14.0, "discount_profit_gross": 9.0, "discount_profit_net": -44.0}, {"full_code": "SH501043", "code6": "501043", "name": "沪深300LOF", "price": 1.624, "change": 0.62, "est": 1.626, "premium": -0.12, "est_date": "2026-07-23", "ref_premium": null, "status": "open", "status_text": "正常申购", "redeem_status": "open", "redeem_status_text": "正常赎回", "quota": null, "big_quota": null, "fund_type": "", "is_qdii": false, "confirm_days": 1, "confirm_days_label": "T+1", "yituo6": false, "yituo6_label": "仅深市", "quota_label": "无限制", "premium_cycle_label": "约3天", "premium_cycle_detail": "T+1+转托管", "discount_cycle_label": "约3天", "discount_cycle_detail": "T+0买入/T+1赎", "capital": 10000, "premium_profit_gross": 12.0, "premium_profit_net": -11.0, "discount_profit_gross": 12.0, "discount_profit_net": -41.0}, {"full_code": "SZ160706", "code6": "160706", "name": "沪深300LOF", "price": 1.214, "change": 0.33, "est": 1.216, "premium": -0.16, "est_date": "2026-07-23", "ref_premium": null, "status": "open", "status_text": "正常申购", "redeem_status": "open", "redeem_status_text": "正常赎回", "quota": null, "big_quota": null, "fund_type": "", "is_qdii": false, "confirm_days": 1, "confirm_days_label": "T+1", "yituo6": true, "yituo6_label": "支持", "quota_label": "无限制", "premium_cycle_label": "约3天", "premium_cycle_detail": "T+1+转托管", "discount_cycle_label": "约3天", "discount_cycle_detail": "T+0买入/T+1赎", "capital": 10000, "premium_profit_gross": 16.0, "premium_profit_net": -7.0, "discount_profit_gross": 16.0, "discount_profit_net": -37.0}, {"full_code": "SZ167301", "code6": "167301", "name": "保险主题LOF", "price": 1.082, "change": 0.37, "est": 1.084, "premium": -0.18, "est_date": "2026-07-23", "ref_premium": null, "status": "open", "status_text": "正常申购", "redeem_status": "open", "redeem_status_text": "正常赎回", "quota": null, "big_quota": null, "fund_type": "", "is_qdii": false, "confirm_days": 1, "confirm_days_label": "T+1", "yituo6": true, "yituo6_label": "支持", "quota_label": "无限制", "premium_cycle_label": "约3天", "premium_cycle_detail": "T+1+转托管", "discount_cycle_label": "约3天", "discount_cycle_detail": "T+0买入/T+1赎", "capital": 10000, "premium_profit_gross": 18.0, "premium_profit_net": -5.0, "discount_profit_gross": 18.0, "discount_profit_net": -35.0}, {"full_code": "SH502000", "code6": "502000", "name": "500增强LOF", "price": 1.979, "change": -0.5, "est": 1.983, "premium": -0.2, "est_date": "2026-07-23", "ref_premium": null, "status": "open", "status_text": "正常申购", "redeem_status": "open", "redeem_status_text": "正常赎回", "quota": null, "big_quota": null, "fund_type": "", "is_qdii": false, "confirm_days": 1, "confirm_days_label": "T+1", "yituo6": false, "yituo6_label": "仅深市", "quota_label": "无限制", "premium_cycle_label": "约3天", "premium_cycle_detail": "T+1+转托管", "discount_cycle_label": "约3天", "discount_cycle_detail": "T+0买入/T+1赎", "capital": 10000, "premium_profit_gross": 20.0, "premium_profit_net": -3.0, "discount_profit_gross": 20.0, "discount_profit_net": -33.0}, {"full_code": "SZ161124", "code6": "161124", "name": "港股小盘LOF", "price": 0.894, "change": 0.9, "est": 0.896, "premium": -0.22, "est_date": "2026-07-23", "ref_premium": null, "status": "limited", "status_text": "限制大额", "redeem_status": "open", "redeem_status_text": "正常赎回", "quota": 3000.0, "big_quota": null, "fund_type": "", "is_qdii": true, "confirm_days": 1, "confirm_days_label": "T+1", "yituo6": true, "yituo6_label": "推荐", "quota_label": "3000元", "premium_cycle_label": "约3天", "premium_cycle_detail": "T+1+转托管", "discount_cycle_label": "约3天", "discount_cycle_detail": "T+0买入/T+1赎", "capital": 3000.0, "premium_profit_gross": 6.6, "premium_profit_net": -0.3, "discount_profit_gross": 6.6, "discount_profit_net": -9.3}, {"full_code": "SZ160225", "code6": "160225", "name": "新能源汽车LOF", "price": 1.759, "change": 2.75, "est": 1.763, "premium": -0.23, "est_date": "2026-07-23", "ref_premium": null, "status": "open", "status_text": "正常申购", "redeem_status": "open", "redeem_status_text": "正常赎回", "quota": null, "big_quota": null, "fund_type": "", "is_qdii": false, "confirm_days": 1, "confirm_days_label": "T+1", "yituo6": true, "yituo6_label": "支持", "quota_label": "无限制", "premium_cycle_label": "约3天", "premium_cycle_detail": "T+1+转托管", "discount_cycle_label": "约3天", "discount_cycle_detail": "T+0买入/T+1赎", "capital": 10000, "premium_profit_gross": 23.0, "premium_profit_net": 0.0, "discount_profit_gross": 23.0, "discount_profit_net": -30.0}, {"full_code": "SZ161726", "code6": "161726", "name": "生物医药LOF", "price": 0.398, "change": -0.25, "est": 0.399, "premium": -0.25, "est_date": "2026-07-23", "ref_premium": null, "status": "open", "status_text": "正常申购", "redeem_status": "open", "redeem_status_text": "正常赎回", "quota": null, "big_quota": null, "fund_type": "", "is_qdii": true, "confirm_days": 2, "confirm_days_label": "T+2", "yituo6": true, "yituo6_label": "支持", "quota_label": "无限制", "premium_cycle_label": "约4天", "premium_cycle_detail": "T+2+转托管", "discount_cycle_label": "约4天", "discount_cycle_detail": "T+0买入/T+2赎", "capital": 10000, "premium_profit_gross": 25.0, "premium_profit_net": 2.0, "discount_profit_gross": 25.0, "discount_profit_net": -28.0}, {"full_code": "SZ161815", "code6": "161815", "name": "抗通胀LOF", "price": 1.062, "change": 0.76, "est": 1.065, "premium": -0.28, "est_date": "2026-07-22", "ref_premium": -0.25, "status": "open", "status_text": "正常申购", "redeem_status": "open", "redeem_status_text": "正常赎回", "quota": null, "big_quota": null, "fund_type": "", "is_qdii": true, "confirm_days": 2, "confirm_days_label": "T+2", "yituo6": true, "yituo6_label": "支持", "quota_label": "无限制", "premium_cycle_label": "约4天", "premium_cycle_detail": "T+2+转托管", "discount_cycle_label": "约4天", "discount_cycle_detail": "T+0买入/T+2赎", "capital": 10000, "premium_profit_gross": 28.0, "premium_profit_net": 5.0, "discount_profit_gross": 28.0, "discount_profit_net": -25.0}, {"full_code": "SZ161127", "code6": "161127", "name": "标普生物科技LOF", "price": 2.015, "change": -0.93, "est": 2.022, "premium": -0.35, "est_date": "2026-07-22", "ref_premium": -0.32, "status": "closed", "status_text": "暂停申购", "redeem_status": "open", "redeem_status_text": "正常赎回", "quota": 10.0, "big_quota": null, "fund_type": "", "is_qdii": true, "confirm_days": 2, "confirm_days_label": "T+2", "yituo6": true, "yituo6_label": "推荐", "quota_label": "10元", "premium_cycle_label": "约4天", "premium_cycle_detail": "T+2+转托管", "discount_cycle_label": "约4天", "discount_cycle_detail": "T+0买入/T+2赎", "capital": 10.0, "premium_profit_gross": 0.04, "premium_profit_net": 0.01, "discount_profit_gross": 0.04, "discount_profit_net": -0.02}, {"full_code": "SZ162412", "code6": "162412", "name": "医疗基金LOF", "price": 0.567, "change": -0.87, "est": 0.569, "premium": -0.35, "est_date": "2026-07-23", "ref_premium": null, "status": "open", "status_text": "正常申购", "redeem_status": "open", "redeem_status_text": "正常赎回", "quota": null, "big_quota": null, "fund_type": "", "is_qdii": true, "confirm_days": 2, "confirm_days_label": "T+2", "yituo6": true, "yituo6_label": "支持", "quota_label": "无限制", "premium_cycle_label": "约4天", "premium_cycle_detail": "T+2+转托管", "discount_cycle_label": "约4天", "discount_cycle_detail": "T+0买入/T+2赎", "capital": 10000, "premium_profit_gross": 35.0, "premium_profit_net": 12.0, "discount_profit_gross": 35.0, "discount_profit_net": -18.0}, {"full_code": "SZ161725", "code6": "161725", "name": "白酒基金LOF", "price": 0.549, "change": -1.26, "est": 0.551, "premium": -0.36, "est_date": "2026-07-23", "ref_premium": null, "status": "limited", "status_text": "限制大额", "redeem_status": "open", "redeem_status_text": "正常赎回", "quota": 500000.0, "big_quota": null, "fund_type": "", "is_qdii": false, "confirm_days": 1, "confirm_days_label": "T+1", "yituo6": true, "yituo6_label": "支持", "quota_label": "50万", "premium_cycle_label": "约3天", "premium_cycle_detail": "T+1+转托管", "discount_cycle_label": "约3天", "discount_cycle_detail": "T+0买入/T+1赎", "capital": 10000, "premium_profit_gross": 36.0, "premium_profit_net": 13.0, "discount_profit_gross": 36.0, "discount_profit_net": -17.0}, {"full_code": "SZ160632", "code6": "160632", "name": "酒LOF", "price": 0.266, "change": -0.75, "est": 0.267, "premium": -0.37, "est_date": "2026-07-23", "ref_premium": null, "status": "limited", "status_text": "限制大额", "redeem_status": "open", "redeem_status_text": "正常赎回", "quota": 200000.0, "big_quota": null, "fund_type": "", "is_qdii": false, "confirm_days": 1, "confirm_days_label": "T+1", "yituo6": true, "yituo6_label": "支持", "quota_label": "20万", "premium_cycle_label": "约3天", "premium_cycle_detail": "T+1+转托管", "discount_cycle_label": "约3天", "discount_cycle_detail": "T+0买入/T+1赎", "capital": 10000, "premium_profit_gross": 37.0, "premium_profit_net": 14.0, "discount_profit_gross": 37.0, "discount_profit_net": -16.0}, {"full_code": "SZ163109", "code6": "163109", "name": "申万深成LOF", "price": 0.78, "change": 0.26, "est": 0.783, "premium": -0.38, "est_date": "2026-07-23", "ref_premium": null, "status": "open", "status_text": "正常申购", "redeem_status": "open", "redeem_status_text": "正常赎回", "quota": null, "big_quota": null, "fund_type": "", "is_qdii": false, "confirm_days": 1, "confirm_days_label": "T+1", "yituo6": true, "yituo6_label": "支持", "quota_label": "无限制", "premium_cycle_label": "约3天", "premium_cycle_detail": "T+1+转托管", "discount_cycle_label": "约3天", "discount_cycle_detail": "T+0买入/T+1赎", "capital": 10000, "premium_profit_gross": 38.0, "premium_profit_net": 15.0, "discount_profit_gross": 38.0, "discount_profit_net": -15.0}, {"full_code": "SZ161831", "code6": "161831", "name": "恒生国企LOF", "price": 0.723, "change": 1.4, "est": 0.726, "premium": -0.41, "est_date": "2026-07-23", "ref_premium": null, "status": "open", "status_text": "正常申购", "redeem_status": "open", "redeem_status_text": "正常赎回", "quota": null, "big_quota": null, "fund_type": "", "is_qdii": true, "confirm_days": 1, "confirm_days_label": "T+1", "yituo6": true, "yituo6_label": "支持", "quota_label": "无限制", "premium_cycle_label": "约3天", "premium_cycle_detail": "T+1+转托管", "discount_cycle_label": "约3天", "discount_cycle_detail": "T+0买入/T+1赎", "capital": 10000, "premium_profit_gross": 41.0, "premium_profit_net": 18.0, "discount_profit_gross": 41.0, "discount_profit_net": -12.0}, {"full_code": "SZ164701", "code6": "164701", "name": "黄金LOF", "price": 1.604, "change": 0.19, "est": 1.613, "premium": -0.56, "est_date": "2026-07-22", "ref_premium": -0.5, "status": "limited", "status_text": "限制大额", "redeem_status": "open", "redeem_status_text": "正常赎回", "quota": 500.0, "big_quota": null, "fund_type": "", "is_qdii": true, "confirm_days": 2, "confirm_days_label": "T+2", "yituo6": true, "yituo6_label": "推荐", "quota_label": "500元", "premium_cycle_label": "约4天", "premium_cycle_detail": "T+2+转托管", "discount_cycle_label": "约4天", "discount_cycle_detail": "T+0买入/T+2赎", "capital": 500.0, "premium_profit_gross": 2.8, "premium_profit_net": 1.65, "discount_profit_gross": 2.8, "discount_profit_net": 0.15}, {"full_code": "SZ160924", "code6": "160924", "name": "恒生指数LOF", "price": 0.995, "change": 1.32, "est": 1.001, "premium": -0.6, "est_date": "2026-07-23", "ref_premium": null, "status": "open", "status_text": "正常申购", "redeem_status": "open", "redeem_status_text": "正常赎回", "quota": null, "big_quota": null, "fund_type": "", "is_qdii": true, "confirm_days": 1, "confirm_days_label": "T+1", "yituo6": true, "yituo6_label": "支持", "quota_label": "无限制", "premium_cycle_label": "约3天", "premium_cycle_detail": "T+1+转托管", "discount_cycle_label": "约3天", "discount_cycle_detail": "T+0买入/T+1赎", "capital": 10000, "premium_profit_gross": 60.0, "premium_profit_net": 37.0, "discount_profit_gross": 60.0, "discount_profit_net": 7.0}, {"full_code": "SH501302", "code6": "501302", "name": "恒生指数基金LOF", "price": 1.135, "change": 1.52, "est": 1.142, "premium": -0.61, "est_date": "2026-07-23", "ref_premium": null, "status": "open", "status_text": "正常申购", "redeem_status": "open", "redeem_status_text": "正常赎回", "quota": null, "big_quota": null, "fund_type": "", "is_qdii": true, "confirm_days": 1, "confirm_days_label": "T+1", "yituo6": false, "yituo6_label": "仅深市", "quota_label": "无限制", "premium_cycle_label": "约3天", "premium_cycle_detail": "T+1+转托管", "discount_cycle_label": "约3天", "discount_cycle_detail": "T+0买入/T+1赎", "capital": 10000, "premium_profit_gross": 61.0, "premium_profit_net": 38.0, "discount_profit_gross": 61.0, "discount_profit_net": 8.0}, {"full_code": "SZ163113", "code6": "163113", "name": "申万证券LOF", "price": 0.953, "change": 0.42, "est": 0.959, "premium": -0.63, "est_date": "2026-07-23", "ref_premium": null, "status": "open", "status_text": "正常申购", "redeem_status": "open", "redeem_status_text": "正常赎回", "quota": null, "big_quota": null, "fund_type": "", "is_qdii": false, "confirm_days": 1, "confirm_days_label": "T+1", "yituo6": true, "yituo6_label": "支持", "quota_label": "无限制", "premium_cycle_label": "约3天", "premium_cycle_detail": "T+1+转托管", "discount_cycle_label": "约3天", "discount_cycle_detail": "T+0买入/T+1赎", "capital": 10000, "premium_profit_gross": 63.0, "premium_profit_net": 40.0, "discount_profit_gross": 63.0, "discount_profit_net": 10.0}, {"full_code": "SZ160717", "code6": "160717", "name": "H股LOF", "price": 0.714, "change": 1.13, "est": 0.719, "premium": -0.7, "est_date": "2026-07-23", "ref_premium": null, "status": "open", "status_text": "正常申购", "redeem_status": "open", "redeem_status_text": "正常赎回", "quota": null, "big_quota": null, "fund_type": "", "is_qdii": true, "confirm_days": 1, "confirm_days_label": "T+1", "yituo6": true, "yituo6_label": "支持", "quota_label": "无限制", "premium_cycle_label": "约3天", "premium_cycle_detail": "T+1+转托管", "discount_cycle_label": "约3天", "discount_cycle_detail": "T+0买入/T+1赎", "capital": 10000, "premium_profit_gross": 70.0, "premium_profit_net": 47.0, "discount_profit_gross": 70.0, "discount_profit_net": 17.0}, {"full_code": "SZ161227", "code6": "161227", "name": "国投深证100LOF", "price": 1.674, "change": 0.24, "est": 1.686, "premium": -0.71, "est_date": "2026-07-23", "ref_premium": null, "status": "open", "status_text": "正常申购", "redeem_status": "open", "redeem_status_text": "正常赎回", "quota": null, "big_quota": null, "fund_type": "", "is_qdii": false, "confirm_days": 1, "confirm_days_label": "T+1", "yituo6": true, "yituo6_label": "支持", "quota_label": "无限制", "premium_cycle_label": "约3天", "premium_cycle_detail": "T+1+转托管", "discount_cycle_label": "约3天", "discount_cycle_detail": "T+0买入/T+1赎", "capital": 10000, "premium_profit_gross": 71.0, "premium_profit_net": 48.0, "discount_profit_gross": 71.0, "discount_profit_net": 18.0}, {"full_code": "SZ165513", "code6": "165513", "name": "中信保诚商品LOF", "price": 0.968, "change": 0.21, "est": 0.975, "premium": -0.72, "est_date": "2026-07-22", "ref_premium": -0.7, "status": "open", "status_text": "正常申购", "redeem_status": "open", "redeem_status_text": "正常赎回", "quota": null, "big_quota": null, "fund_type": "", "is_qdii": true, "confirm_days": 2, "confirm_days_label": "T+2", "yituo6": true, "yituo6_label": "支持", "quota_label": "无限制", "premium_cycle_label": "约4天", "premium_cycle_detail": "T+2+转托管", "discount_cycle_label": "约4天", "discount_cycle_detail": "T+0买入/T+2赎", "capital": 10000, "premium_profit_gross": 72.0, "premium_profit_net": 49.0, "discount_profit_gross": 72.0, "discount_profit_net": 19.0}, {"full_code": "SZ161032", "code6": "161032", "name": "煤炭龙头LOF", "price": 2.242, "change": 1.13, "est": 2.259, "premium": -0.75, "est_date": "2026-07-23", "ref_premium": null, "status": "open", "status_text": "正常申购", "redeem_status": "open", "redeem_status_text": "正常赎回", "quota": null, "big_quota": null, "fund_type": "", "is_qdii": false, "confirm_days": 1, "confirm_days_label": "T+1", "yituo6": true, "yituo6_label": "支持", "quota_label": "无限制", "premium_cycle_label": "约3天", "premium_cycle_detail": "T+1+转托管", "discount_cycle_label": "约3天", "discount_cycle_detail": "T+0买入/T+1赎", "capital": 10000, "premium_profit_gross": 75.0, "premium_profit_net": 52.0, "discount_profit_gross": 75.0, "discount_profit_net": 22.0}, {"full_code": "SH501312", "code6": "501312", "name": "海外科技LOF", "price": 2.218, "change": -0.05, "est": 2.235, "premium": -0.76, "est_date": "2026-07-22", "ref_premium": -0.7, "status": "limited", "status_text": "限制大额", "redeem_status": "open", "redeem_status_text": "正常赎回", "quota": 20.0, "big_quota": null, "fund_type": "", "is_qdii": true, "confirm_days": 2, "confirm_days_label": "T+2", "yituo6": false, "yituo6_label": "仅深市", "quota_label": "20元", "premium_cycle_label": "约4天", "premium_cycle_detail": "T+2+转托管", "discount_cycle_label": "约4天", "discount_cycle_detail": "T+0买入/T+2赎", "capital": 20.0, "premium_profit_gross": 0.15, "premium_profit_net": 0.11, "discount_profit_gross": 0.15, "discount_profit_net": 0.05}, {"full_code": "SZ163407", "code6": "163407", "name": "兴全沪深300LOF", "price": 2.751, "change": 0.36, "est": 2.772, "premium": -0.76, "est_date": "2026-07-23", "ref_premium": null, "status": "limited", "status_text": "限制大额", "redeem_status": "open", "redeem_status_text": "正常赎回", "quota": 10000000.0, "big_quota": null, "fund_type": "", "is_qdii": false, "confirm_days": 1, "confirm_days_label": "T+1", "yituo6": true, "yituo6_label": "支持", "quota_label": "1000万", "premium_cycle_label": "约3天", "premium_cycle_detail": "T+1+转托管", "discount_cycle_label": "约3天", "discount_cycle_detail": "T+0买入/T+1赎", "capital": 10000, "premium_profit_gross": 76.0, "premium_profit_net": 53.0, "discount_profit_gross": 76.0, "discount_profit_net": 23.0}, {"full_code": "SZ160639", "code6": "160639", "name": "高铁LOF", "price": 0.829, "change": 1.59, "est": 0.836, "premium": -0.84, "est_date": "2026-07-23", "ref_premium": null, "status": "open", "status_text": "正常申购", "redeem_status": "open", "redeem_status_text": "正常赎回", "quota": null, "big_quota": null, "fund_type": "", "is_qdii": false, "confirm_days": 1, "confirm_days_label": "T+1", "yituo6": true, "yituo6_label": "支持", "quota_label": "无限制", "premium_cycle_label": "约3天", "premium_cycle_detail": "T+1+转托管", "discount_cycle_label": "约3天", "discount_cycle_detail": "T+0买入/T+1赎", "capital": 10000, "premium_profit_gross": 84.0, "premium_profit_net": 61.0, "discount_profit_gross": 84.0, "discount_profit_net": 31.0}, {"full_code": "SH501300", "code6": "501300", "name": "美元债LOF", "price": 0.929, "change": -0.21, "est": 0.937, "premium": -0.85, "est_date": "2026-07-22", "ref_premium": -0.77, "status": "limited", "status_text": "限制大额", "redeem_status": "open", "redeem_status_text": "正常赎回", "quota": 50000000.0, "big_quota": null, "fund_type": "", "is_qdii": true, "confirm_days": 2, "confirm_days_label": "T+2", "yituo6": false, "yituo6_label": "仅深市", "quota_label": "5000万", "premium_cycle_label": "约4天", "premium_cycle_detail": "T+2+转托管", "discount_cycle_label": "约4天", "discount_cycle_detail": "T+0买入/T+2赎", "capital": 10000, "premium_profit_gross": 85.0, "premium_profit_net": 62.0, "discount_profit_gross": 85.0, "discount_profit_net": 32.0}, {"full_code": "SZ160719", "code6": "160719", "name": "嘉实黄金LOF", "price": 1.839, "change": 0.0, "est": 1.855, "premium": -0.86, "est_date": "2026-07-22", "ref_premium": -0.84, "status": "closed", "status_text": "暂停申购", "redeem_status": "open", "redeem_status_text": "正常赎回", "quota": 5.0, "big_quota": null, "fund_type": "", "is_qdii": true, "confirm_days": 2, "confirm_days_label": "T+2", "yituo6": true, "yituo6_label": "推荐", "quota_label": "5元", "premium_cycle_label": "约4天", "premium_cycle_detail": "T+2+转托管", "discount_cycle_label": "约4天", "discount_cycle_detail": "T+0买入/T+2赎", "capital": 5.0, "premium_profit_gross": 0.04, "premium_profit_net": 0.03, "discount_profit_gross": 0.04, "discount_profit_net": 0.02}, {"full_code": "SZ164824", "code6": "164824", "name": "印度基金LOF", "price": 1.275, "change": 0.0, "est": 1.286, "premium": -0.86, "est_date": "2026-07-22", "ref_premium": -0.83, "status": "limited", "status_text": "限制大额", "redeem_status": "open", "redeem_status_text": "正常赎回", "quota": 500000.0, "big_quota": null, "fund_type": "", "is_qdii": true, "confirm_days": 2, "confirm_days_label": "T+2", "yituo6": true, "yituo6_label": "支持", "quota_label": "50万", "premium_cycle_label": "约4天", "premium_cycle_detail": "T+2+转托管", "discount_cycle_label": "约4天", "discount_cycle_detail": "T+0买入/T+2赎", "capital": 10000, "premium_profit_gross": 86.0, "premium_profit_net": 63.0, "discount_profit_gross": 86.0, "discount_profit_net": 33.0}, {"full_code": "SZ168204", "code6": "168204", "name": "煤炭LOF", "price": 2.07, "change": 1.07, "est": 2.089, "premium": -0.91, "est_date": "2026-07-23", "ref_premium": null, "status": "open", "status_text": "正常申购", "redeem_status": "open", "redeem_status_text": "正常赎回", "quota": null, "big_quota": null, "fund_type": "", "is_qdii": false, "confirm_days": 1, "confirm_days_label": "T+1", "yituo6": true, "yituo6_label": "支持", "quota_label": "无限制", "premium_cycle_label": "约3天", "premium_cycle_detail": "T+1+转托管", "discount_cycle_label": "约3天", "discount_cycle_detail": "T+0买入/T+1赎", "capital": 10000, "premium_profit_gross": 91.0, "premium_profit_net": 68.0, "discount_profit_gross": 91.0, "discount_profit_net": 38.0}, {"full_code": "SZ162415", "code6": "162415", "name": "美国消费LOF", "price": 2.784, "change": -0.96, "est": 2.811, "premium": -0.96, "est_date": "2026-07-22", "ref_premium": -0.91, "status": "limited", "status_text": "限制大额", "redeem_status": "open", "redeem_status_text": "正常赎回", "quota": 1000.0, "big_quota": null, "fund_type": "", "is_qdii": true, "confirm_days": 2, "confirm_days_label": "T+2", "yituo6": true, "yituo6_label": "推荐", "quota_label": "1000元", "premium_cycle_label": "约4天", "premium_cycle_detail": "T+2+转托管", "discount_cycle_label": "约4天", "discount_cycle_detail": "T+0买入/T+2赎", "capital": 1000.0, "premium_profit_gross": 9.6, "premium_profit_net": 7.3, "discount_profit_gross": 9.6, "discount_profit_net": 4.3}, {"full_code": "SZ160216", "code6": "160216", "name": "国泰商品LOF", "price": 0.622, "change": 0.48, "est": 0.63, "premium": -1.27, "est_date": "2026-07-22", "ref_premium": -1.2, "status": "limited", "status_text": "限制大额", "redeem_status": "open", "redeem_status_text": "正常赎回", "quota": 300000.0, "big_quota": null, "fund_type": "", "is_qdii": true, "confirm_days": 2, "confirm_days_label": "T+2", "yituo6": true, "yituo6_label": "支持", "quota_label": "30万", "premium_cycle_label": "约4天", "premium_cycle_detail": "T+2+转托管", "discount_cycle_label": "约4天", "discount_cycle_detail": "T+0买入/T+2赎", "capital": 10000, "premium_profit_gross": 127.0, "premium_profit_net": 104.0, "discount_profit_gross": 127.0, "discount_profit_net": 74.0}, {"full_code": "SZ168401", "code6": "168401", "name": "红土创新精选LOF", "price": 6.196, "change": -2.19, "est": 6.332, "premium": -2.15, "est_date": "2026-07-23", "ref_premium": null, "status": "open", "status_text": "正常申购", "redeem_status": "open", "redeem_status_text": "正常赎回", "quota": null, "big_quota": null, "fund_type": "", "is_qdii": false, "confirm_days": 1, "confirm_days_label": "T+1", "yituo6": true, "yituo6_label": "支持", "quota_label": "无限制", "premium_cycle_label": "约3天", "premium_cycle_detail": "T+1+转托管", "discount_cycle_label": "约3天", "discount_cycle_detail": "T+0买入/T+1赎", "capital": 10000, "premium_profit_gross": 215.0, "premium_profit_net": 192.0, "discount_profit_gross": 215.0, "discount_profit_net": 162.0, "arb_cycle_label": "约3天", "expected_profit": 162.0, "arb_type": "discount"}, {"full_code": "SH501025", "code6": "501025", "name": "香港银行LOF", "price": 1.824, "change": 2.41, "est": 1.824, "premium": 0.0, "est_date": "2026-07-23", "ref_premium": null, "status": "open", "status_text": "正常申购", "redeem_status": "open", "redeem_status_text": "正常赎回", "quota": null, "big_quota": null, "fund_type": "", "is_qdii": true, "confirm_days": 1, "confirm_days_label": "T+1", "yituo6": false, "yituo6_label": "仅深市", "quota_label": "无限制", "premium_cycle_label": "约3天", "premium_cycle_detail": "T+1+转托管", "discount_cycle_label": "约3天", "discount_cycle_detail": "T+0买入/T+1赎", "capital": 10000, "premium_profit_gross": 0.0, "premium_profit_net": -23.0, "discount_profit_gross": 0.0, "discount_profit_net": -53.0}, {"full_code": "SZ160140", "code6": "160140", "name": "美国REIT精选LOF", "price": 1.489, "change": -0.47, "est": 1.489, "premium": 0.0, "est_date": "2026-07-22", "ref_premium": 0.06, "status": "open", "status_text": "正常申购", "redeem_status": "open", "redeem_status_text": "正常赎回", "quota": null, "big_quota": null, "fund_type": "", "is_qdii": true, "confirm_days": 2, "confirm_days_label": "T+2", "yituo6": true, "yituo6_label": "支持", "quota_label": "无限制", "premium_cycle_label": "约4天", "premium_cycle_detail": "T+2+转托管", "discount_cycle_label": "约4天", "discount_cycle_detail": "T+0买入/T+2赎", "capital": 10000, "premium_profit_gross": 0.0, "premium_profit_net": -23.0, "discount_profit_gross": 0.0, "discount_profit_net": -53.0}], "prevPremiums": {"SH501225": 24.16, "SH501018": 22.23, "SZ160723": 21.31, "SZ161129": 19.03, "SZ160644": 15.47, "SZ161128": 2.9, "SZ161130": 2.25, "SZ162719": 1.97, "SZ161226": 1.93, "SZ160416": 1.05, "SZ163208": 1.05, "SZ162411": 1.04, "SH501312": 0.81, "SZ161125": 0.76, "SZ160216": 0.57, "SZ161831": 0.53, "SZ160717": 0.23, "SZ164705": -0.09, "SH501043": -0.1, "SZ161815": -0.13, "SZ160924": -0.16, "SH501300": -0.17, "SH501302": -0.28, "SZ161126": -0.28, "SZ161127": -0.31, "SZ161116": -0.33, "SZ162415": -0.33, "SH501025": -0.36, "SZ164701": -0.43, "SZ160140": -0.46, "SZ165513": -0.49, "SZ160719": -0.51, "SZ164824": -0.52, "SZ161124": -0.53, "SZ164906": -0.53}}