{"now": "2026-07-20 14:02", "session": "开盘中", "sessionLegacy": "午盘", "defaultCapital": 10000, "feeRates": {"sub": 0.0015, "sell": 0.0008, "buy": 0.0003, "redeem": 0.005}, "thresholds": {"premium": 0, "discount": -1.5}, "summary": {"premiumCount": 11, "discountCount": 1, "posCount": 23, "negCount": 30, "avgPremium": 2.11}, "premiumArb": [{"full_code": "SH502000", "code6": "502000", "name": "500增强LOF", "price": 1.966, "change": -2.67, "est": 1.894, "premium": 3.8, "est_date": "2026-07-20", "ref_premium": null, "status": "open", "status_text": "正常申购", "redeem_status": "open", "redeem_status_text": "正常赎回", "quota": null, "big_quota": null, "fund_type": "", "is_qdii": false, "confirm_days": 1, "confirm_days_label": "T+1", "yituo6": false, "yituo6_label": "仅深市", "quota_label": "无限制", "premium_cycle_label": "约3天", "premium_cycle_detail": "T+1+转托管", "discount_cycle_label": "约3天", "discount_cycle_detail": "T+0买入/T+1赎", "capital": 10000, "premium_profit_gross": 380.0, "premium_profit_net": 357.0, "discount_profit_gross": 380.0, "discount_profit_net": 327.0, "arb_cycle_label": "约3天", "expected_profit": 357.0, "arb_type": "premium"}, {"full_code": "SH501043", "code6": "501043", "name": "沪深300LOF", "price": 1.627, "change": -2.05, "est": 1.568, "premium": 3.76, "est_date": "2026-07-20", "ref_premium": null, "status": "open", "status_text": "正常申购", "redeem_status": "open", "redeem_status_text": "正常赎回", "quota": null, "big_quota": null, "fund_type": "", "is_qdii": false, "confirm_days": 1, "confirm_days_label": "T+1", "yituo6": false, "yituo6_label": "仅深市", "quota_label": "无限制", "premium_cycle_label": "约3天", "premium_cycle_detail": "T+1+转托管", "discount_cycle_label": "约3天", "discount_cycle_detail": "T+0买入/T+1赎", "capital": 10000, "premium_profit_gross": 376.0, "premium_profit_net": 353.0, "discount_profit_gross": 376.0, "discount_profit_net": 323.0, "arb_cycle_label": "约3天", "expected_profit": 353.0, "arb_type": "premium"}, {"full_code": "SZ160225", "code6": "160225", "name": "新能源汽车LOF", "price": 1.721, "change": -0.17, "est": 1.666, "premium": 3.3, "est_date": "2026-07-20", "ref_premium": null, "status": "open", "status_text": "正常申购", "redeem_status": "open", "redeem_status_text": "正常赎回", "quota": null, "big_quota": null, "fund_type": "", "is_qdii": false, "confirm_days": 1, "confirm_days_label": "T+1", "yituo6": true, "yituo6_label": "支持", "quota_label": "无限制", "premium_cycle_label": "约3天", "premium_cycle_detail": "T+1+转托管", "discount_cycle_label": "约3天", "discount_cycle_detail": "T+0买入/T+1赎", "capital": 10000, "premium_profit_gross": 330.0, "premium_profit_net": 307.0, "discount_profit_gross": 330.0, "discount_profit_net": 277.0, "arb_cycle_label": "约3天", "expected_profit": 307.0, "arb_type": "premium"}, {"full_code": "SZ161812", "code6": "161812", "name": "深证100LOF", "price": 1.42, "change": 0.07, "est": 1.376, "premium": 3.2, "est_date": "2026-07-20", "ref_premium": null, "status": "open", "status_text": "正常申购", "redeem_status": "open", "redeem_status_text": "正常赎回", "quota": null, "big_quota": null, "fund_type": "", "is_qdii": false, "confirm_days": 1, "confirm_days_label": "T+1", "yituo6": true, "yituo6_label": "支持", "quota_label": "无限制", "premium_cycle_label": "约3天", "premium_cycle_detail": "T+1+转托管", "discount_cycle_label": "约3天", "discount_cycle_detail": "T+0买入/T+1赎", "capital": 10000, "premium_profit_gross": 320.0, "premium_profit_net": 297.0, "discount_profit_gross": 320.0, "discount_profit_net": 267.0, "arb_cycle_label": "约3天", "expected_profit": 297.0, "arb_type": "premium"}, {"full_code": "SZ163109", "code6": "163109", "name": "申万深成LOF", "price": 0.764, "change": -1.67, "est": 0.75, "premium": 1.87, "est_date": "2026-07-20", "ref_premium": null, "status": "open", "status_text": "正常申购", "redeem_status": "open", "redeem_status_text": "正常赎回", "quota": null, "big_quota": null, "fund_type": "", "is_qdii": false, "confirm_days": 1, "confirm_days_label": "T+1", "yituo6": true, "yituo6_label": "支持", "quota_label": "无限制", "premium_cycle_label": "约3天", "premium_cycle_detail": "T+1+转托管", "discount_cycle_label": "约3天", "discount_cycle_detail": "T+0买入/T+1赎", "capital": 10000, "premium_profit_gross": 187.0, "premium_profit_net": 164.0, "discount_profit_gross": 187.0, "discount_profit_net": 134.0, "arb_cycle_label": "约3天", "expected_profit": 164.0, "arb_type": "premium"}, {"full_code": "SZ161227", "code6": "161227", "name": "国投深证100LOF", "price": 1.65, "change": -1.32, "est": 1.623, "premium": 1.66, "est_date": "2026-07-20", "ref_premium": null, "status": "open", "status_text": "正常申购", "redeem_status": "open", "redeem_status_text": "正常赎回", "quota": null, "big_quota": null, "fund_type": "", "is_qdii": false, "confirm_days": 1, "confirm_days_label": "T+1", "yituo6": true, "yituo6_label": "支持", "quota_label": "无限制", "premium_cycle_label": "约3天", "premium_cycle_detail": "T+1+转托管", "discount_cycle_label": "约3天", "discount_cycle_detail": "T+0买入/T+1赎", "capital": 10000, "premium_profit_gross": 166.0, "premium_profit_net": 143.0, "discount_profit_gross": 166.0, "discount_profit_net": 113.0, "arb_cycle_label": "约3天", "expected_profit": 143.0, "arb_type": "premium"}, {"full_code": "SZ160706", "code6": "160706", "name": "沪深300LOF", "price": 1.192, "change": 0.25, "est": 1.173, "premium": 1.62, "est_date": "2026-07-20", "ref_premium": null, "status": "open", "status_text": "正常申购", "redeem_status": "open", "redeem_status_text": "正常赎回", "quota": null, "big_quota": null, "fund_type": "", "is_qdii": false, "confirm_days": 1, "confirm_days_label": "T+1", "yituo6": true, "yituo6_label": "支持", "quota_label": "无限制", "premium_cycle_label": "约3天", "premium_cycle_detail": "T+1+转托管", "discount_cycle_label": "约3天", "discount_cycle_detail": "T+0买入/T+1赎", "capital": 10000, "premium_profit_gross": 162.0, "premium_profit_net": 139.0, "discount_profit_gross": 162.0, "discount_profit_net": 109.0, "arb_cycle_label": "约3天", "expected_profit": 139.0, "arb_type": "premium"}, {"full_code": "SZ164906", "code6": "164906", "name": "中概互联网LOF", "price": 0.97, "change": 2.43, "est": 0.955, "premium": 1.57, "est_date": "2026-07-17", "ref_premium": -0.09, "status": "open", "status_text": "正常申购", "redeem_status": "open", "redeem_status_text": "正常赎回", "quota": null, "big_quota": null, "fund_type": "", "is_qdii": true, "confirm_days": 2, "confirm_days_label": "T+2", "yituo6": true, "yituo6_label": "支持", "quota_label": "无限制", "premium_cycle_label": "约4天", "premium_cycle_detail": "T+2+转托管", "discount_cycle_label": "约4天", "discount_cycle_detail": "T+0买入/T+2赎", "capital": 10000, "premium_profit_gross": 157.0, "premium_profit_net": 134.0, "discount_profit_gross": 157.0, "discount_profit_net": 104.0, "arb_cycle_label": "约4天", "expected_profit": 134.0, "arb_type": "premium"}, {"full_code": "SH501025", "code6": "501025", "name": "香港银行LOF", "price": 1.822, "change": 3.52, "est": 1.8, "premium": 1.22, "est_date": "2026-07-20", "ref_premium": null, "status": "open", "status_text": "正常申购", "redeem_status": "open", "redeem_status_text": "正常赎回", "quota": null, "big_quota": null, "fund_type": "", "is_qdii": true, "confirm_days": 1, "confirm_days_label": "T+1", "yituo6": false, "yituo6_label": "仅深市", "quota_label": "无限制", "premium_cycle_label": "约3天", "premium_cycle_detail": "T+1+转托管", "discount_cycle_label": "约3天", "discount_cycle_detail": "T+0买入/T+1赎", "capital": 10000, "premium_profit_gross": 122.0, "premium_profit_net": 99.0, "discount_profit_gross": 122.0, "discount_profit_net": 69.0, "arb_cycle_label": "约3天", "expected_profit": 99.0, "arb_type": "premium"}, {"full_code": "SZ161815", "code6": "161815", "name": "抗通胀LOF", "price": 1.043, "change": 2.25, "est": 1.036, "premium": 0.68, "est_date": "2026-07-17", "ref_premium": 0.62, "status": "open", "status_text": "正常申购", "redeem_status": "open", "redeem_status_text": "正常赎回", "quota": null, "big_quota": null, "fund_type": "", "is_qdii": true, "confirm_days": 2, "confirm_days_label": "T+2", "yituo6": true, "yituo6_label": "支持", "quota_label": "无限制", "premium_cycle_label": "约4天", "premium_cycle_detail": "T+2+转托管", "discount_cycle_label": "约4天", "discount_cycle_detail": "T+0买入/T+2赎", "capital": 10000, "premium_profit_gross": 68.0, "premium_profit_net": 45.0, "discount_profit_gross": 68.0, "discount_profit_net": 15.0, "arb_cycle_label": "约4天", "expected_profit": 45.0, "arb_type": "premium"}, {"full_code": "SZ161005", "code6": "161005", "name": "富国天惠LOF", "price": 3.045, "change": -0.59, "est": 3.027, "premium": 0.59, "est_date": "2026-07-20", "ref_premium": null, "status": "limited", "status_text": "限制大额", "redeem_status": "open", "redeem_status_text": "正常赎回", "quota": 20000.0, "big_quota": null, "fund_type": "", "is_qdii": false, "confirm_days": 1, "confirm_days_label": "T+1", "yituo6": true, "yituo6_label": "推荐", "quota_label": "2万", "premium_cycle_label": "约3天", "premium_cycle_detail": "T+1+转托管", "discount_cycle_label": "约3天", "discount_cycle_detail": "T+0买入/T+1赎", "capital": 10000, "premium_profit_gross": 59.0, "premium_profit_net": 36.0, "discount_profit_gross": 59.0, "discount_profit_net": 6.0, "arb_cycle_label": "约3天", "expected_profit": 36.0, "arb_type": "premium"}], "discountArb": [{"full_code": "SZ168401", "code6": "168401", "name": "红土创新精选LOF", "price": 5.889, "change": -7.16, "est": 6.249, "premium": -5.76, "est_date": "2026-07-20", "ref_premium": null, "status": "open", "status_text": "正常申购", "redeem_status": "open", "redeem_status_text": "正常赎回", "quota": null, "big_quota": null, "fund_type": "", "is_qdii": false, "confirm_days": 1, "confirm_days_label": "T+1", "yituo6": true, "yituo6_label": "支持", "quota_label": "无限制", "premium_cycle_label": "约3天", "premium_cycle_detail": "T+1+转托管", "discount_cycle_label": "约3天", "discount_cycle_detail": "T+0买入/T+1赎", "capital": 10000, "premium_profit_gross": 576.0, "premium_profit_net": 553.0, "discount_profit_gross": 576.0, "discount_profit_net": 523.0, "arb_cycle_label": "约3天", "expected_profit": 523.0, "arb_type": "discount"}], "blocked": [{"full_code": "SZ161129", "code6": "161129", "name": "原油LOF易方达", "price": 1.987, "change": 9.54, "est": 1.618, "premium": 22.81, "est_date": "2026-07-17", "ref_premium": 21.92, "status": "closed", "status_text": "暂停申购", "redeem_status": "open", "redeem_status_text": "正常赎回", "quota": 10.0, "big_quota": null, "fund_type": "", "is_qdii": true, "confirm_days": 2, "confirm_days_label": "T+2", "yituo6": true, "yituo6_label": "推荐", "quota_label": "10元", "premium_cycle_label": "约4天", "premium_cycle_detail": "T+2+转托管", "discount_cycle_label": "约4天", "discount_cycle_detail": "T+0买入/T+2赎", "capital": 10.0, "premium_profit_gross": 2.28, "premium_profit_net": 2.26, "discount_profit_gross": 2.28, "discount_profit_net": 2.23, "block_reason": "溢价但不可申购"}, {"full_code": "SH501225", "code6": "501225", "name": "全球芯片LOF", "price": 3.637, "change": -0.19, "est": 3.037, "premium": 19.76, "est_date": "2026-07-17", "ref_premium": 20.61, "status": "closed", "status_text": "暂停申购", "redeem_status": "open", "redeem_status_text": "正常赎回", "quota": 100.0, "big_quota": null, "fund_type": "", "is_qdii": true, "confirm_days": 2, "confirm_days_label": "T+2", "yituo6": false, "yituo6_label": "仅深市", "quota_label": "100元", "premium_cycle_label": "约4天", "premium_cycle_detail": "T+2+转托管", "discount_cycle_label": "约4天", "discount_cycle_detail": "T+0买入/T+2赎", "capital": 100.0, "premium_profit_gross": 19.76, "premium_profit_net": 19.53, "discount_profit_gross": 19.76, "discount_profit_net": 19.23, "block_reason": "溢价但不可申购"}, {"full_code": "SH501018", "code6": "501018", "name": "南方原油LOF", "price": 2.026, "change": 8.92, "est": 1.694, "premium": 19.6, "est_date": "2026-07-17", "ref_premium": 19.77, "status": "closed", "status_text": "暂停申购", "redeem_status": "closed", "redeem_status_text": "暂停赎回", "quota": 0.0, "big_quota": null, "fund_type": "", "is_qdii": true, "confirm_days": 2, "confirm_days_label": "T+2", "yituo6": false, "yituo6_label": "仅深市", "quota_label": "无限制", "premium_cycle_label": "约4天", "premium_cycle_detail": "T+2+转托管", "discount_cycle_label": "约4天", "discount_cycle_detail": "T+0买入/T+2赎", "capital": 10000, "premium_profit_gross": 1960.0, "premium_profit_net": 1937.0, "discount_profit_gross": 1960.0, "discount_profit_net": 1907.0, "block_reason": "溢价但不可申购"}, {"full_code": "SZ160723", "code6": "160723", "name": "嘉实原油LOF", "price": 2.291, "change": 9.1, "est": 1.947, "premium": 17.67, "est_date": "2026-07-17", "ref_premium": 17.67, "status": "closed", "status_text": "暂停申购", "redeem_status": "open", "redeem_status_text": "正常赎回", "quota": 5.0, "big_quota": null, "fund_type": "", "is_qdii": true, "confirm_days": 2, "confirm_days_label": "T+2", "yituo6": true, "yituo6_label": "推荐", "quota_label": "5元", "premium_cycle_label": "约4天", "premium_cycle_detail": "T+2+转托管", "discount_cycle_label": "约4天", "discount_cycle_detail": "T+0买入/T+2赎", "capital": 5.0, "premium_profit_gross": 0.88, "premium_profit_net": 0.87, "discount_profit_gross": 0.88, "discount_profit_net": 0.86, "block_reason": "溢价但不可申购"}, {"full_code": "SZ161226", "code6": "161226", "name": "国投白银LOF", "price": 1.792, "change": 0.17, "est": 1.546, "premium": 15.91, "est_date": "2026-07-20", "ref_premium": 14.96, "status": "closed", "status_text": "暂停申购", "redeem_status": "open", "redeem_status_text": "正常赎回", "quota": 100.0, "big_quota": null, "fund_type": "", "is_qdii": false, "confirm_days": 1, "confirm_days_label": "T+1", "yituo6": true, "yituo6_label": "推荐", "quota_label": "100元", "premium_cycle_label": "约3天", "premium_cycle_detail": "T+1+转托管", "discount_cycle_label": "约3天", "discount_cycle_detail": "T+0买入/T+1赎", "capital": 100.0, "premium_profit_gross": 15.91, "premium_profit_net": 15.68, "discount_profit_gross": 15.91, "discount_profit_net": 15.38, "block_reason": "溢价但不可申购"}, {"full_code": "SZ161130", "code6": "161130", "name": "纳斯达克100LOF", "price": 4.47, "change": 0.13, "est": 4.321, "premium": 3.45, "est_date": "2026-07-17", "ref_premium": 3.48, "status": "closed", "status_text": "暂停申购", "redeem_status": "open", "redeem_status_text": "正常赎回", "quota": 10.0, "big_quota": null, "fund_type": "", "is_qdii": true, "confirm_days": 2, "confirm_days_label": "T+2", "yituo6": true, "yituo6_label": "推荐", "quota_label": "10元", "premium_cycle_label": "约4天", "premium_cycle_detail": "T+2+转托管", "discount_cycle_label": "约4天", "discount_cycle_detail": "T+0买入/T+2赎", "capital": 10.0, "premium_profit_gross": 0.34, "premium_profit_net": 0.32, "discount_profit_gross": 0.34, "discount_profit_net": 0.29, "block_reason": "溢价但不可申购"}, {"full_code": "SZ162719", "code6": "162719", "name": "石油LOF", "price": 2.846, "change": 4.98, "est": 2.769, "premium": 2.78, "est_date": "2026-07-17", "ref_premium": 2.84, "status": "closed", "status_text": "暂停申购", "redeem_status": "open", "redeem_status_text": "正常赎回", "quota": 10.0, "big_quota": null, "fund_type": "", "is_qdii": true, "confirm_days": 2, "confirm_days_label": "T+2", "yituo6": true, "yituo6_label": "推荐", "quota_label": "10元", "premium_cycle_label": "约4天", "premium_cycle_detail": "T+2+转托管", "discount_cycle_label": "约4天", "discount_cycle_detail": "T+0买入/T+2赎", "capital": 10.0, "premium_profit_gross": 0.28, "premium_profit_net": 0.25, "discount_profit_gross": 0.28, "discount_profit_net": 0.22, "block_reason": "溢价但不可申购"}, {"full_code": "SZ160416", "code6": "160416", "name": "石油基金LOF", "price": 2.117, "change": 4.39, "est": 2.063, "premium": 2.62, "est_date": "2026-07-17", "ref_premium": 2.65, "status": "closed", "status_text": "暂停申购", "redeem_status": "open", "redeem_status_text": "正常赎回", "quota": 2.0, "big_quota": null, "fund_type": "", "is_qdii": true, "confirm_days": 2, "confirm_days_label": "T+2", "yituo6": true, "yituo6_label": "推荐", "quota_label": "2元", "premium_cycle_label": "约4天", "premium_cycle_detail": "T+2+转托管", "discount_cycle_label": "约4天", "discount_cycle_detail": "T+0买入/T+2赎", "capital": 2.0, "premium_profit_gross": 0.05, "premium_profit_net": 0.05, "discount_profit_gross": 0.05, "discount_profit_net": 0.04, "block_reason": "溢价但不可申购"}, {"full_code": "SZ161125", "code6": "161125", "name": "标普500LOF", "price": 3.142, "change": -0.1, "est": 3.073, "premium": 2.25, "est_date": "2026-07-17", "ref_premium": 2.22, "status": "closed", "status_text": "暂停申购", "redeem_status": "open", "redeem_status_text": "正常赎回", "quota": 10.0, "big_quota": null, "fund_type": "", "is_qdii": true, "confirm_days": 2, "confirm_days_label": "T+2", "yituo6": true, "yituo6_label": "推荐", "quota_label": "10元", "premium_cycle_label": "约4天", "premium_cycle_detail": "T+2+转托管", "discount_cycle_label": "约4天", "discount_cycle_detail": "T+0买入/T+2赎", "capital": 10.0, "premium_profit_gross": 0.23, "premium_profit_net": 0.2, "discount_profit_gross": 0.23, "discount_profit_net": 0.17, "block_reason": "溢价但不可申购"}, {"full_code": "SZ161128", "code6": "161128", "name": "标普信息科技LOF", "price": 6.54, "change": 0.29, "est": 6.405, "premium": 2.11, "est_date": "2026-07-17", "ref_premium": 2.11, "status": "closed", "status_text": "暂停申购", "redeem_status": "open", "redeem_status_text": "正常赎回", "quota": 10.0, "big_quota": null, "fund_type": "", "is_qdii": true, "confirm_days": 2, "confirm_days_label": "T+2", "yituo6": true, "yituo6_label": "推荐", "quota_label": "10元", "premium_cycle_label": "约4天", "premium_cycle_detail": "T+2+转托管", "discount_cycle_label": "约4天", "discount_cycle_detail": "T+0买入/T+2赎", "capital": 10.0, "premium_profit_gross": 0.21, "premium_profit_net": 0.19, "discount_profit_gross": 0.21, "discount_profit_net": 0.16, "block_reason": "溢价但不可申购"}, {"full_code": "SZ162411", "code6": "162411", "name": "华宝油气LOF", "price": 0.92, "change": 4.9, "est": 0.901, "premium": 2.11, "est_date": "2026-07-17", "ref_premium": 2.13, "status": "closed", "status_text": "暂停申购", "redeem_status": "open", "redeem_status_text": "正常赎回", "quota": 10.0, "big_quota": null, "fund_type": "", "is_qdii": true, "confirm_days": 2, "confirm_days_label": "T+2", "yituo6": true, "yituo6_label": "推荐", "quota_label": "10元", "premium_cycle_label": "约4天", "premium_cycle_detail": "T+2+转托管", "discount_cycle_label": "约4天", "discount_cycle_detail": "T+0买入/T+2赎", "capital": 10.0, "premium_profit_gross": 0.21, "premium_profit_net": 0.19, "discount_profit_gross": 0.21, "discount_profit_net": 0.16, "block_reason": "溢价但不可申购"}, {"full_code": "SZ163208", "code6": "163208", "name": "全球油气能源LOF", "price": 1.314, "change": 3.79, "est": 1.292, "premium": 1.7, "est_date": "2026-07-17", "ref_premium": 1.67, "status": "closed", "status_text": "暂停申购", "redeem_status": "open", "redeem_status_text": "正常赎回", "quota": 500.0, "big_quota": null, "fund_type": "", "is_qdii": true, "confirm_days": 2, "confirm_days_label": "T+2", "yituo6": true, "yituo6_label": "推荐", "quota_label": "500元", "premium_cycle_label": "约4天", "premium_cycle_detail": "T+2+转托管", "discount_cycle_label": "约4天", "discount_cycle_detail": "T+0买入/T+2赎", "capital": 500.0, "premium_profit_gross": 8.5, "premium_profit_net": 7.35, "discount_profit_gross": 8.5, "discount_profit_net": 5.85, "block_reason": "溢价但不可申购"}], "allRows": [{"full_code": "SZ161129", "code6": "161129", "name": "原油LOF易方达", "price": 1.987, "change": 9.54, "est": 1.618, "premium": 22.81, "est_date": "2026-07-17", "ref_premium": 21.92, "status": "closed", "status_text": "暂停申购", "redeem_status": "open", "redeem_status_text": "正常赎回", "quota": 10.0, "big_quota": null, "fund_type": "", "is_qdii": true, "confirm_days": 2, "confirm_days_label": "T+2", "yituo6": true, "yituo6_label": "推荐", "quota_label": "10元", "premium_cycle_label": "约4天", "premium_cycle_detail": "T+2+转托管", "discount_cycle_label": "约4天", "discount_cycle_detail": "T+0买入/T+2赎", "capital": 10.0, "premium_profit_gross": 2.28, "premium_profit_net": 2.26, "discount_profit_gross": 2.28, "discount_profit_net": 2.23}, {"full_code": "SH501225", "code6": "501225", "name": "全球芯片LOF", "price": 3.637, "change": -0.19, "est": 3.037, "premium": 19.76, "est_date": "2026-07-17", "ref_premium": 20.61, "status": "closed", "status_text": "暂停申购", "redeem_status": "open", "redeem_status_text": "正常赎回", "quota": 100.0, "big_quota": null, "fund_type": "", "is_qdii": true, "confirm_days": 2, "confirm_days_label": "T+2", "yituo6": false, "yituo6_label": "仅深市", "quota_label": "100元", "premium_cycle_label": "约4天", "premium_cycle_detail": "T+2+转托管", "discount_cycle_label": "约4天", "discount_cycle_detail": "T+0买入/T+2赎", "capital": 100.0, "premium_profit_gross": 19.76, "premium_profit_net": 19.53, "discount_profit_gross": 19.76, "discount_profit_net": 19.23}, {"full_code": "SH501018", "code6": "501018", "name": "南方原油LOF", "price": 2.026, "change": 8.92, "est": 1.694, "premium": 19.6, "est_date": "2026-07-17", "ref_premium": 19.77, "status": "closed", "status_text": "暂停申购", "redeem_status": "closed", "redeem_status_text": "暂停赎回", "quota": 0.0, "big_quota": null, "fund_type": "", "is_qdii": true, "confirm_days": 2, "confirm_days_label": "T+2", "yituo6": false, "yituo6_label": "仅深市", "quota_label": "无限制", "premium_cycle_label": "约4天", "premium_cycle_detail": "T+2+转托管", "discount_cycle_label": "约4天", "discount_cycle_detail": "T+0买入/T+2赎", "capital": 10000, "premium_profit_gross": 1960.0, "premium_profit_net": 1937.0, "discount_profit_gross": 1960.0, "discount_profit_net": 1907.0}, {"full_code": "SZ160723", "code6": "160723", "name": "嘉实原油LOF", "price": 2.291, "change": 9.1, "est": 1.947, "premium": 17.67, "est_date": "2026-07-17", "ref_premium": 17.67, "status": "closed", "status_text": "暂停申购", "redeem_status": "open", "redeem_status_text": "正常赎回", "quota": 5.0, "big_quota": null, "fund_type": "", "is_qdii": true, "confirm_days": 2, "confirm_days_label": "T+2", "yituo6": true, "yituo6_label": "推荐", "quota_label": "5元", "premium_cycle_label": "约4天", "premium_cycle_detail": "T+2+转托管", "discount_cycle_label": "约4天", "discount_cycle_detail": "T+0买入/T+2赎", "capital": 5.0, "premium_profit_gross": 0.88, "premium_profit_net": 0.87, "discount_profit_gross": 0.88, "discount_profit_net": 0.86}, {"full_code": "SZ161226", "code6": "161226", "name": "国投白银LOF", "price": 1.792, "change": 0.17, "est": 1.546, "premium": 15.91, "est_date": "2026-07-20", "ref_premium": 14.96, "status": "closed", "status_text": "暂停申购", "redeem_status": "open", "redeem_status_text": "正常赎回", "quota": 100.0, "big_quota": null, "fund_type": "", "is_qdii": false, "confirm_days": 1, "confirm_days_label": "T+1", "yituo6": true, "yituo6_label": "推荐", "quota_label": "100元", "premium_cycle_label": "约3天", "premium_cycle_detail": "T+1+转托管", "discount_cycle_label": "约3天", "discount_cycle_detail": "T+0买入/T+1赎", "capital": 100.0, "premium_profit_gross": 15.91, "premium_profit_net": 15.68, "discount_profit_gross": 15.91, "discount_profit_net": 15.38}, {"full_code": "SH502000", "code6": "502000", "name": "500增强LOF", "price": 1.966, "change": -2.67, "est": 1.894, "premium": 3.8, "est_date": "2026-07-20", "ref_premium": null, "status": "open", "status_text": "正常申购", "redeem_status": "open", "redeem_status_text": "正常赎回", "quota": null, "big_quota": null, "fund_type": "", "is_qdii": false, "confirm_days": 1, "confirm_days_label": "T+1", "yituo6": false, "yituo6_label": "仅深市", "quota_label": "无限制", "premium_cycle_label": "约3天", "premium_cycle_detail": "T+1+转托管", "discount_cycle_label": "约3天", "discount_cycle_detail": "T+0买入/T+1赎", "capital": 10000, "premium_profit_gross": 380.0, "premium_profit_net": 357.0, "discount_profit_gross": 380.0, "discount_profit_net": 327.0, "arb_cycle_label": "约3天", "expected_profit": 357.0, "arb_type": "premium"}, {"full_code": "SH501043", "code6": "501043", "name": "沪深300LOF", "price": 1.627, "change": -2.05, "est": 1.568, "premium": 3.76, "est_date": "2026-07-20", "ref_premium": null, "status": "open", "status_text": "正常申购", "redeem_status": "open", "redeem_status_text": "正常赎回", "quota": null, "big_quota": null, "fund_type": "", "is_qdii": false, "confirm_days": 1, "confirm_days_label": "T+1", "yituo6": false, "yituo6_label": "仅深市", "quota_label": "无限制", "premium_cycle_label": "约3天", "premium_cycle_detail": "T+1+转托管", "discount_cycle_label": "约3天", "discount_cycle_detail": "T+0买入/T+1赎", "capital": 10000, "premium_profit_gross": 376.0, "premium_profit_net": 353.0, "discount_profit_gross": 376.0, "discount_profit_net": 323.0, "arb_cycle_label": "约3天", "expected_profit": 353.0, "arb_type": "premium"}, {"full_code": "SZ161130", "code6": "161130", "name": "纳斯达克100LOF", "price": 4.47, "change": 0.13, "est": 4.321, "premium": 3.45, "est_date": "2026-07-17", "ref_premium": 3.48, "status": "closed", "status_text": "暂停申购", "redeem_status": "open", "redeem_status_text": "正常赎回", "quota": 10.0, "big_quota": null, "fund_type": "", "is_qdii": true, "confirm_days": 2, "confirm_days_label": "T+2", "yituo6": true, "yituo6_label": "推荐", "quota_label": "10元", "premium_cycle_label": "约4天", "premium_cycle_detail": "T+2+转托管", "discount_cycle_label": "约4天", "discount_cycle_detail": "T+0买入/T+2赎", "capital": 10.0, "premium_profit_gross": 0.34, "premium_profit_net": 0.32, "discount_profit_gross": 0.34, "discount_profit_net": 0.29}, {"full_code": "SZ160225", "code6": "160225", "name": "新能源汽车LOF", "price": 1.721, "change": -0.17, "est": 1.666, "premium": 3.3, "est_date": "2026-07-20", "ref_premium": null, "status": "open", "status_text": "正常申购", "redeem_status": "open", "redeem_status_text": "正常赎回", "quota": null, "big_quota": null, "fund_type": "", "is_qdii": false, "confirm_days": 1, "confirm_days_label": "T+1", "yituo6": true, "yituo6_label": "支持", "quota_label": "无限制", "premium_cycle_label": "约3天", "premium_cycle_detail": "T+1+转托管", "discount_cycle_label": "约3天", "discount_cycle_detail": "T+0买入/T+1赎", "capital": 10000, "premium_profit_gross": 330.0, "premium_profit_net": 307.0, "discount_profit_gross": 330.0, "discount_profit_net": 277.0, "arb_cycle_label": "约3天", "expected_profit": 307.0, "arb_type": "premium"}, {"full_code": "SZ161812", "code6": "161812", "name": "深证100LOF", "price": 1.42, "change": 0.07, "est": 1.376, "premium": 3.2, "est_date": "2026-07-20", "ref_premium": null, "status": "open", "status_text": "正常申购", "redeem_status": "open", "redeem_status_text": "正常赎回", "quota": null, "big_quota": null, "fund_type": "", "is_qdii": false, "confirm_days": 1, "confirm_days_label": "T+1", "yituo6": true, "yituo6_label": "支持", "quota_label": "无限制", "premium_cycle_label": "约3天", "premium_cycle_detail": "T+1+转托管", "discount_cycle_label": "约3天", "discount_cycle_detail": "T+0买入/T+1赎", "capital": 10000, "premium_profit_gross": 320.0, "premium_profit_net": 297.0, "discount_profit_gross": 320.0, "discount_profit_net": 267.0, "arb_cycle_label": "约3天", "expected_profit": 297.0, "arb_type": "premium"}, {"full_code": "SZ162719", "code6": "162719", "name": "石油LOF", "price": 2.846, "change": 4.98, "est": 2.769, "premium": 2.78, "est_date": "2026-07-17", "ref_premium": 2.84, "status": "closed", "status_text": "暂停申购", "redeem_status": "open", "redeem_status_text": "正常赎回", "quota": 10.0, "big_quota": null, "fund_type": "", "is_qdii": true, "confirm_days": 2, "confirm_days_label": "T+2", "yituo6": true, "yituo6_label": "推荐", "quota_label": "10元", "premium_cycle_label": "约4天", "premium_cycle_detail": "T+2+转托管", "discount_cycle_label": "约4天", "discount_cycle_detail": "T+0买入/T+2赎", "capital": 10.0, "premium_profit_gross": 0.28, "premium_profit_net": 0.25, "discount_profit_gross": 0.28, "discount_profit_net": 0.22}, {"full_code": "SZ160416", "code6": "160416", "name": "石油基金LOF", "price": 2.117, "change": 4.39, "est": 2.063, "premium": 2.62, "est_date": "2026-07-17", "ref_premium": 2.65, "status": "closed", "status_text": "暂停申购", "redeem_status": "open", "redeem_status_text": "正常赎回", "quota": 2.0, "big_quota": null, "fund_type": "", "is_qdii": true, "confirm_days": 2, "confirm_days_label": "T+2", "yituo6": true, "yituo6_label": "推荐", "quota_label": "2元", "premium_cycle_label": "约4天", "premium_cycle_detail": "T+2+转托管", "discount_cycle_label": "约4天", "discount_cycle_detail": "T+0买入/T+2赎", "capital": 2.0, "premium_profit_gross": 0.05, "premium_profit_net": 0.05, "discount_profit_gross": 0.05, "discount_profit_net": 0.04}, {"full_code": "SZ161125", "code6": "161125", "name": "标普500LOF", "price": 3.142, "change": -0.1, "est": 3.073, "premium": 2.25, "est_date": "2026-07-17", "ref_premium": 2.22, "status": "closed", "status_text": "暂停申购", "redeem_status": "open", "redeem_status_text": "正常赎回", "quota": 10.0, "big_quota": null, "fund_type": "", "is_qdii": true, "confirm_days": 2, "confirm_days_label": "T+2", "yituo6": true, "yituo6_label": "推荐", "quota_label": "10元", "premium_cycle_label": "约4天", "premium_cycle_detail": "T+2+转托管", "discount_cycle_label": "约4天", "discount_cycle_detail": "T+0买入/T+2赎", "capital": 10.0, "premium_profit_gross": 0.23, "premium_profit_net": 0.2, "discount_profit_gross": 0.23, "discount_profit_net": 0.17}, {"full_code": "SZ161128", "code6": "161128", "name": "标普信息科技LOF", "price": 6.54, "change": 0.29, "est": 6.405, "premium": 2.11, "est_date": "2026-07-17", "ref_premium": 2.11, "status": "closed", "status_text": "暂停申购", "redeem_status": "open", "redeem_status_text": "正常赎回", "quota": 10.0, "big_quota": null, "fund_type": "", "is_qdii": true, "confirm_days": 2, "confirm_days_label": "T+2", "yituo6": true, "yituo6_label": "推荐", "quota_label": "10元", "premium_cycle_label": "约4天", "premium_cycle_detail": "T+2+转托管", "discount_cycle_label": "约4天", "discount_cycle_detail": "T+0买入/T+2赎", "capital": 10.0, "premium_profit_gross": 0.21, "premium_profit_net": 0.19, "discount_profit_gross": 0.21, "discount_profit_net": 0.16}, {"full_code": "SZ162411", "code6": "162411", "name": "华宝油气LOF", "price": 0.92, "change": 4.9, "est": 0.901, "premium": 2.11, "est_date": "2026-07-17", "ref_premium": 2.13, "status": "closed", "status_text": "暂停申购", "redeem_status": "open", "redeem_status_text": "正常赎回", "quota": 10.0, "big_quota": null, "fund_type": "", "is_qdii": true, "confirm_days": 2, "confirm_days_label": "T+2", "yituo6": true, "yituo6_label": "推荐", "quota_label": "10元", "premium_cycle_label": "约4天", "premium_cycle_detail": "T+2+转托管", "discount_cycle_label": "约4天", "discount_cycle_detail": "T+0买入/T+2赎", "capital": 10.0, "premium_profit_gross": 0.21, "premium_profit_net": 0.19, "discount_profit_gross": 0.21, "discount_profit_net": 0.16}, {"full_code": "SZ163109", "code6": "163109", "name": "申万深成LOF", "price": 0.764, "change": -1.67, "est": 0.75, "premium": 1.87, "est_date": "2026-07-20", "ref_premium": null, "status": "open", "status_text": "正常申购", "redeem_status": "open", "redeem_status_text": "正常赎回", "quota": null, "big_quota": null, "fund_type": "", "is_qdii": false, "confirm_days": 1, "confirm_days_label": "T+1", "yituo6": true, "yituo6_label": "支持", "quota_label": "无限制", "premium_cycle_label": "约3天", "premium_cycle_detail": "T+1+转托管", "discount_cycle_label": "约3天", "discount_cycle_detail": "T+0买入/T+1赎", "capital": 10000, "premium_profit_gross": 187.0, "premium_profit_net": 164.0, "discount_profit_gross": 187.0, "discount_profit_net": 134.0, "arb_cycle_label": "约3天", "expected_profit": 164.0, "arb_type": "premium"}, {"full_code": "SZ163208", "code6": "163208", "name": "全球油气能源LOF", "price": 1.314, "change": 3.79, "est": 1.292, "premium": 1.7, "est_date": "2026-07-17", "ref_premium": 1.67, "status": "closed", "status_text": "暂停申购", "redeem_status": "open", "redeem_status_text": "正常赎回", "quota": 500.0, "big_quota": null, "fund_type": "", "is_qdii": true, "confirm_days": 2, "confirm_days_label": "T+2", "yituo6": true, "yituo6_label": "推荐", "quota_label": "500元", "premium_cycle_label": "约4天", "premium_cycle_detail": "T+2+转托管", "discount_cycle_label": "约4天", "discount_cycle_detail": "T+0买入/T+2赎", "capital": 500.0, "premium_profit_gross": 8.5, "premium_profit_net": 7.35, "discount_profit_gross": 8.5, "discount_profit_net": 5.85}, {"full_code": "SZ161227", "code6": "161227", "name": "国投深证100LOF", "price": 1.65, "change": -1.32, "est": 1.623, "premium": 1.66, "est_date": "2026-07-20", "ref_premium": null, "status": "open", "status_text": "正常申购", "redeem_status": "open", "redeem_status_text": "正常赎回", "quota": null, "big_quota": null, "fund_type": "", "is_qdii": false, "confirm_days": 1, "confirm_days_label": "T+1", "yituo6": true, "yituo6_label": "支持", "quota_label": "无限制", "premium_cycle_label": "约3天", "premium_cycle_detail": "T+1+转托管", "discount_cycle_label": "约3天", "discount_cycle_detail": "T+0买入/T+1赎", "capital": 10000, "premium_profit_gross": 166.0, "premium_profit_net": 143.0, "discount_profit_gross": 166.0, "discount_profit_net": 113.0, "arb_cycle_label": "约3天", "expected_profit": 143.0, "arb_type": "premium"}, {"full_code": "SZ160706", "code6": "160706", "name": "沪深300LOF", "price": 1.192, "change": 0.25, "est": 1.173, "premium": 1.62, "est_date": "2026-07-20", "ref_premium": null, "status": "open", "status_text": "正常申购", "redeem_status": "open", "redeem_status_text": "正常赎回", "quota": null, "big_quota": null, "fund_type": "", "is_qdii": false, "confirm_days": 1, "confirm_days_label": "T+1", "yituo6": true, "yituo6_label": "支持", "quota_label": "无限制", "premium_cycle_label": "约3天", "premium_cycle_detail": "T+1+转托管", "discount_cycle_label": "约3天", "discount_cycle_detail": "T+0买入/T+1赎", "capital": 10000, "premium_profit_gross": 162.0, "premium_profit_net": 139.0, "discount_profit_gross": 162.0, "discount_profit_net": 109.0, "arb_cycle_label": "约3天", "expected_profit": 139.0, "arb_type": "premium"}, {"full_code": "SZ164906", "code6": "164906", "name": "中概互联网LOF", "price": 0.97, "change": 2.43, "est": 0.955, "premium": 1.57, "est_date": "2026-07-17", "ref_premium": -0.09, "status": "open", "status_text": "正常申购", "redeem_status": "open", "redeem_status_text": "正常赎回", "quota": null, "big_quota": null, "fund_type": "", "is_qdii": true, "confirm_days": 2, "confirm_days_label": "T+2", "yituo6": true, "yituo6_label": "支持", "quota_label": "无限制", "premium_cycle_label": "约4天", "premium_cycle_detail": "T+2+转托管", "discount_cycle_label": "约4天", "discount_cycle_detail": "T+0买入/T+2赎", "capital": 10000, "premium_profit_gross": 157.0, "premium_profit_net": 134.0, "discount_profit_gross": 157.0, "discount_profit_net": 104.0, "arb_cycle_label": "约4天", "expected_profit": 134.0, "arb_type": "premium"}, {"full_code": "SH501025", "code6": "501025", "name": "香港银行LOF", "price": 1.822, "change": 3.52, "est": 1.8, "premium": 1.22, "est_date": "2026-07-20", "ref_premium": null, "status": "open", "status_text": "正常申购", "redeem_status": "open", "redeem_status_text": "正常赎回", "quota": null, "big_quota": null, "fund_type": "", "is_qdii": true, "confirm_days": 1, "confirm_days_label": "T+1", "yituo6": false, "yituo6_label": "仅深市", "quota_label": "无限制", "premium_cycle_label": "约3天", "premium_cycle_detail": "T+1+转托管", "discount_cycle_label": "约3天", "discount_cycle_detail": "T+0买入/T+1赎", "capital": 10000, "premium_profit_gross": 122.0, "premium_profit_net": 99.0, "discount_profit_gross": 122.0, "discount_profit_net": 69.0, "arb_cycle_label": "约3天", "expected_profit": 99.0, "arb_type": "premium"}, {"full_code": "SZ161815", "code6": "161815", "name": "抗通胀LOF", "price": 1.043, "change": 2.25, "est": 1.036, "premium": 0.68, "est_date": "2026-07-17", "ref_premium": 0.62, "status": "open", "status_text": "正常申购", "redeem_status": "open", "redeem_status_text": "正常赎回", "quota": null, "big_quota": null, "fund_type": "", "is_qdii": true, "confirm_days": 2, "confirm_days_label": "T+2", "yituo6": true, "yituo6_label": "支持", "quota_label": "无限制", "premium_cycle_label": "约4天", "premium_cycle_detail": "T+2+转托管", "discount_cycle_label": "约4天", "discount_cycle_detail": "T+0买入/T+2赎", "capital": 10000, "premium_profit_gross": 68.0, "premium_profit_net": 45.0, "discount_profit_gross": 68.0, "discount_profit_net": 15.0, "arb_cycle_label": "约4天", "expected_profit": 45.0, "arb_type": "premium"}, {"full_code": "SZ161005", "code6": "161005", "name": "富国天惠LOF", "price": 3.045, "change": -0.59, "est": 3.027, "premium": 0.59, "est_date": "2026-07-20", "ref_premium": null, "status": "limited", "status_text": "限制大额", "redeem_status": "open", "redeem_status_text": "正常赎回", "quota": 20000.0, "big_quota": null, "fund_type": "", "is_qdii": false, "confirm_days": 1, "confirm_days_label": "T+1", "yituo6": true, "yituo6_label": "推荐", "quota_label": "2万", "premium_cycle_label": "约3天", "premium_cycle_detail": "T+1+转托管", "discount_cycle_label": "约3天", "discount_cycle_detail": "T+0买入/T+1赎", "capital": 10000, "premium_profit_gross": 59.0, "premium_profit_net": 36.0, "discount_profit_gross": 59.0, "discount_profit_net": 6.0, "arb_cycle_label": "约3天", "expected_profit": 36.0, "arb_type": "premium"}, {"full_code": "SZ163407", "code6": "163407", "name": "兴全沪深300LOF", "price": 2.627, "change": 0.54, "est": 2.631, "premium": -0.15, "est_date": "2026-07-20", "ref_premium": null, "status": "limited", "status_text": "限制大额", "redeem_status": "open", "redeem_status_text": "正常赎回", "quota": 10000000.0, "big_quota": null, "fund_type": "", "is_qdii": false, "confirm_days": 1, "confirm_days_label": "T+1", "yituo6": true, "yituo6_label": "支持", "quota_label": "1000万", "premium_cycle_label": "约3天", "premium_cycle_detail": "T+1+转托管", "discount_cycle_label": "约3天", "discount_cycle_detail": "T+0买入/T+1赎", "capital": 10000, "premium_profit_gross": 15.0, "premium_profit_net": -8.0, "discount_profit_gross": 15.0, "discount_profit_net": -38.0}, {"full_code": "SH501302", "code6": "501302", "name": "恒生指数基金LOF", "price": 1.131, "change": 1.98, "est": 1.133, "premium": -0.18, "est_date": "2026-07-20", "ref_premium": null, "status": "open", "status_text": "正常申购", "redeem_status": "open", "redeem_status_text": "正常赎回", "quota": null, "big_quota": null, "fund_type": "", "is_qdii": true, "confirm_days": 1, "confirm_days_label": "T+1", "yituo6": false, "yituo6_label": "仅深市", "quota_label": "无限制", "premium_cycle_label": "约3天", "premium_cycle_detail": "T+1+转托管", "discount_cycle_label": "约3天", "discount_cycle_detail": "T+0买入/T+1赎", "capital": 10000, "premium_profit_gross": 18.0, "premium_profit_net": -5.0, "discount_profit_gross": 18.0, "discount_profit_net": -35.0}, {"full_code": "SZ164705", "code6": "164705", "name": "恒生LOF", "price": 1.12, "change": 1.63, "est": 1.122, "premium": -0.18, "est_date": "2026-07-20", "ref_premium": null, "status": "open", "status_text": "正常申购", "redeem_status": "open", "redeem_status_text": "正常赎回", "quota": null, "big_quota": null, "fund_type": "", "is_qdii": true, "confirm_days": 1, "confirm_days_label": "T+1", "yituo6": true, "yituo6_label": "支持", "quota_label": "无限制", "premium_cycle_label": "约3天", "premium_cycle_detail": "T+1+转托管", "discount_cycle_label": "约3天", "discount_cycle_detail": "T+0买入/T+1赎", "capital": 10000, "premium_profit_gross": 18.0, "premium_profit_net": -5.0, "discount_profit_gross": 18.0, "discount_profit_net": -35.0}, {"full_code": "SZ162415", "code6": "162415", "name": "美国消费LOF", "price": 2.836, "change": -0.28, "est": 2.843, "premium": -0.25, "est_date": "2026-07-17", "ref_premium": -0.28, "status": "limited", "status_text": "限制大额", "redeem_status": "open", "redeem_status_text": "正常赎回", "quota": 1000.0, "big_quota": null, "fund_type": "", "is_qdii": true, "confirm_days": 2, "confirm_days_label": "T+2", "yituo6": true, "yituo6_label": "推荐", "quota_label": "1000元", "premium_cycle_label": "约4天", "premium_cycle_detail": "T+2+转托管", "discount_cycle_label": "约4天", "discount_cycle_detail": "T+0买入/T+2赎", "capital": 1000.0, "premium_profit_gross": 2.5, "premium_profit_net": 0.2, "discount_profit_gross": 2.5, "discount_profit_net": -2.8}, {"full_code": "SZ161726", "code6": "161726", "name": "生物医药LOF", "price": 0.389, "change": 0.78, "est": 0.39, "premium": -0.26, "est_date": "2026-07-20", "ref_premium": null, "status": "open", "status_text": "正常申购", "redeem_status": "open", "redeem_status_text": "正常赎回", "quota": null, "big_quota": null, "fund_type": "", "is_qdii": true, "confirm_days": 2, "confirm_days_label": "T+2", "yituo6": true, "yituo6_label": "支持", "quota_label": "无限制", "premium_cycle_label": "约4天", "premium_cycle_detail": "T+2+转托管", "discount_cycle_label": "约4天", "discount_cycle_detail": "T+0买入/T+2赎", "capital": 10000, "premium_profit_gross": 26.0, "premium_profit_net": 3.0, "discount_profit_gross": 26.0, "discount_profit_net": -27.0}, {"full_code": "SZ167301", "code6": "167301", "name": "保险主题LOF", "price": 1.053, "change": 2.83, "est": 1.056, "premium": -0.28, "est_date": "2026-07-20", "ref_premium": null, "status": "open", "status_text": "正常申购", "redeem_status": "open", "redeem_status_text": "正常赎回", "quota": null, "big_quota": null, "fund_type": "", "is_qdii": false, "confirm_days": 1, "confirm_days_label": "T+1", "yituo6": true, "yituo6_label": "支持", "quota_label": "无限制", "premium_cycle_label": "约3天", "premium_cycle_detail": "T+1+转托管", "discount_cycle_label": "约3天", "discount_cycle_detail": "T+0买入/T+1赎", "capital": 10000, "premium_profit_gross": 28.0, "premium_profit_net": 5.0, "discount_profit_gross": 28.0, "discount_profit_net": -25.0}, {"full_code": "SZ161725", "code6": "161725", "name": "白酒基金LOF", "price": 0.551, "change": 3.96, "est": 0.553, "premium": -0.36, "est_date": "2026-07-20", "ref_premium": null, "status": "limited", "status_text": "限制大额", "redeem_status": "open", "redeem_status_text": "正常赎回", "quota": 500000.0, "big_quota": null, "fund_type": "", "is_qdii": false, "confirm_days": 1, "confirm_days_label": "T+1", "yituo6": true, "yituo6_label": "支持", "quota_label": "50万", "premium_cycle_label": "约3天", "premium_cycle_detail": "T+1+转托管", "discount_cycle_label": "约3天", "discount_cycle_detail": "T+0买入/T+1赎", "capital": 10000, "premium_profit_gross": 36.0, "premium_profit_net": 13.0, "discount_profit_gross": 36.0, "discount_profit_net": -17.0}, {"full_code": "SZ160632", "code6": "160632", "name": "酒LOF", "price": 0.267, "change": 3.09, "est": 0.268, "premium": -0.37, "est_date": "2026-07-20", "ref_premium": null, "status": "limited", "status_text": "限制大额", "redeem_status": "open", "redeem_status_text": "正常赎回", "quota": 200000.0, "big_quota": null, "fund_type": "", "is_qdii": false, "confirm_days": 1, "confirm_days_label": "T+1", "yituo6": true, "yituo6_label": "支持", "quota_label": "20万", "premium_cycle_label": "约3天", "premium_cycle_detail": "T+1+转托管", "discount_cycle_label": "约3天", "discount_cycle_detail": "T+0买入/T+1赎", "capital": 10000, "premium_profit_gross": 37.0, "premium_profit_net": 14.0, "discount_profit_gross": 37.0, "discount_profit_net": -16.0}, {"full_code": "SZ160140", "code6": "160140", "name": "美国REIT精选LOF", "price": 1.489, "change": -0.4, "est": 1.495, "premium": -0.4, "est_date": "2026-07-17", "ref_premium": -0.4, "status": "open", "status_text": "正常申购", "redeem_status": "open", "redeem_status_text": "正常赎回", "quota": null, "big_quota": null, "fund_type": "", "is_qdii": true, "confirm_days": 2, "confirm_days_label": "T+2", "yituo6": true, "yituo6_label": "支持", "quota_label": "无限制", "premium_cycle_label": "约4天", "premium_cycle_detail": "T+2+转托管", "discount_cycle_label": "约4天", "discount_cycle_detail": "T+0买入/T+2赎", "capital": 10000, "premium_profit_gross": 40.0, "premium_profit_net": 17.0, "discount_profit_gross": 40.0, "discount_profit_net": -13.0}, {"full_code": "SZ161126", "code6": "161126", "name": "标普医疗保健LOF", "price": 1.971, "change": -0.5, "est": 1.979, "premium": -0.4, "est_date": "2026-07-17", "ref_premium": -0.43, "status": "closed", "status_text": "暂停申购", "redeem_status": "open", "redeem_status_text": "正常赎回", "quota": 10.0, "big_quota": null, "fund_type": "", "is_qdii": true, "confirm_days": 2, "confirm_days_label": "T+2", "yituo6": true, "yituo6_label": "推荐", "quota_label": "10元", "premium_cycle_label": "约4天", "premium_cycle_detail": "T+2+转托管", "discount_cycle_label": "约4天", "discount_cycle_detail": "T+0买入/T+2赎", "capital": 10.0, "premium_profit_gross": 0.04, "premium_profit_net": 0.02, "discount_profit_gross": 0.04, "discount_profit_net": -0.01}, {"full_code": "SZ161116", "code6": "161116", "name": "黄金主题LOF", "price": 1.49, "change": 0.4, "est": 1.497, "premium": -0.47, "est_date": "2026-07-17", "ref_premium": -0.52, "status": "closed", "status_text": "暂停申购", "redeem_status": "open", "redeem_status_text": "正常赎回", "quota": 10.0, "big_quota": null, "fund_type": "", "is_qdii": true, "confirm_days": 2, "confirm_days_label": "T+2", "yituo6": true, "yituo6_label": "推荐", "quota_label": "10元", "premium_cycle_label": "约4天", "premium_cycle_detail": "T+2+转托管", "discount_cycle_label": "约4天", "discount_cycle_detail": "T+0买入/T+2赎", "capital": 10.0, "premium_profit_gross": 0.05, "premium_profit_net": 0.02, "discount_profit_gross": 0.05, "discount_profit_net": -0.01}, {"full_code": "SZ161124", "code6": "161124", "name": "港股小盘LOF", "price": 0.869, "change": 0.7, "est": 0.874, "premium": -0.57, "est_date": "2026-07-20", "ref_premium": null, "status": "limited", "status_text": "限制大额", "redeem_status": "open", "redeem_status_text": "正常赎回", "quota": 3000.0, "big_quota": null, "fund_type": "", "is_qdii": true, "confirm_days": 1, "confirm_days_label": "T+1", "yituo6": true, "yituo6_label": "推荐", "quota_label": "3000元", "premium_cycle_label": "约3天", "premium_cycle_detail": "T+1+转托管", "discount_cycle_label": "约3天", "discount_cycle_detail": "T+0买入/T+1赎", "capital": 3000.0, "premium_profit_gross": 17.1, "premium_profit_net": 10.2, "discount_profit_gross": 17.1, "discount_profit_net": 1.2}, {"full_code": "SZ164701", "code6": "164701", "name": "黄金LOF", "price": 1.559, "change": 0.32, "est": 1.568, "premium": -0.57, "est_date": "2026-07-17", "ref_premium": -0.61, "status": "limited", "status_text": "限制大额", "redeem_status": "open", "redeem_status_text": "正常赎回", "quota": 500.0, "big_quota": null, "fund_type": "", "is_qdii": true, "confirm_days": 2, "confirm_days_label": "T+2", "yituo6": true, "yituo6_label": "推荐", "quota_label": "500元", "premium_cycle_label": "约4天", "premium_cycle_detail": "T+2+转托管", "discount_cycle_label": "约4天", "discount_cycle_detail": "T+0买入/T+2赎", "capital": 500.0, "premium_profit_gross": 2.85, "premium_profit_net": 1.7, "discount_profit_gross": 2.85, "discount_profit_net": 0.2}, {"full_code": "SZ160719", "code6": "160719", "name": "嘉实黄金LOF", "price": 1.789, "change": 0.06, "est": 1.8, "premium": -0.61, "est_date": "2026-07-17", "ref_premium": -0.67, "status": "closed", "status_text": "暂停申购", "redeem_status": "open", "redeem_status_text": "正常赎回", "quota": 5.0, "big_quota": null, "fund_type": "", "is_qdii": true, "confirm_days": 2, "confirm_days_label": "T+2", "yituo6": true, "yituo6_label": "推荐", "quota_label": "5元", "premium_cycle_label": "约4天", "premium_cycle_detail": "T+2+转托管", "discount_cycle_label": "约4天", "discount_cycle_detail": "T+0买入/T+2赎", "capital": 5.0, "premium_profit_gross": 0.03, "premium_profit_net": 0.02, "discount_profit_gross": 0.03, "discount_profit_net": 0.0}, {"full_code": "SZ168204", "code6": "168204", "name": "煤炭LOF", "price": 2.016, "change": 5.49, "est": 2.029, "premium": -0.64, "est_date": "2026-07-20", "ref_premium": null, "status": "open", "status_text": "正常申购", "redeem_status": "open", "redeem_status_text": "正常赎回", "quota": null, "big_quota": null, "fund_type": "", "is_qdii": false, "confirm_days": 1, "confirm_days_label": "T+1", "yituo6": true, "yituo6_label": "支持", "quota_label": "无限制", "premium_cycle_label": "约3天", "premium_cycle_detail": "T+1+转托管", "discount_cycle_label": "约3天", "discount_cycle_detail": "T+0买入/T+1赎", "capital": 10000, "premium_profit_gross": 64.0, "premium_profit_net": 41.0, "discount_profit_gross": 64.0, "discount_profit_net": 11.0}, {"full_code": "SZ160216", "code6": "160216", "name": "国泰商品LOF", "price": 0.611, "change": 1.33, "est": 0.615, "premium": -0.65, "est_date": "2026-07-17", "ref_premium": -0.73, "status": "limited", "status_text": "限制大额", "redeem_status": "open", "redeem_status_text": "正常赎回", "quota": 300000.0, "big_quota": null, "fund_type": "", "is_qdii": true, "confirm_days": 2, "confirm_days_label": "T+2", "yituo6": true, "yituo6_label": "支持", "quota_label": "30万", "premium_cycle_label": "约4天", "premium_cycle_detail": "T+2+转托管", "discount_cycle_label": "约4天", "discount_cycle_detail": "T+0买入/T+2赎", "capital": 10000, "premium_profit_gross": 65.0, "premium_profit_net": 42.0, "discount_profit_gross": 65.0, "discount_profit_net": 12.0}, {"full_code": "SH501312", "code6": "501312", "name": "海外科技LOF", "price": 2.19, "change": 0.37, "est": 2.206, "premium": -0.73, "est_date": "2026-07-17", "ref_premium": -0.82, "status": "limited", "status_text": "限制大额", "redeem_status": "open", "redeem_status_text": "正常赎回", "quota": 20.0, "big_quota": null, "fund_type": "", "is_qdii": true, "confirm_days": 2, "confirm_days_label": "T+2", "yituo6": false, "yituo6_label": "仅深市", "quota_label": "20元", "premium_cycle_label": "约4天", "premium_cycle_detail": "T+2+转托管", "discount_cycle_label": "约4天", "discount_cycle_detail": "T+0买入/T+2赎", "capital": 20.0, "premium_profit_gross": 0.15, "premium_profit_net": 0.1, "discount_profit_gross": 0.15, "discount_profit_net": 0.04}, {"full_code": "SZ160639", "code6": "160639", "name": "高铁LOF", "price": 0.81, "change": 0.12, "est": 0.816, "premium": -0.74, "est_date": "2026-07-20", "ref_premium": null, "status": "open", "status_text": "正常申购", "redeem_status": "open", "redeem_status_text": "正常赎回", "quota": null, "big_quota": null, "fund_type": "", "is_qdii": false, "confirm_days": 1, "confirm_days_label": "T+1", "yituo6": true, "yituo6_label": "支持", "quota_label": "无限制", "premium_cycle_label": "约3天", "premium_cycle_detail": "T+1+转托管", "discount_cycle_label": "约3天", "discount_cycle_detail": "T+0买入/T+1赎", "capital": 10000, "premium_profit_gross": 74.0, "premium_profit_net": 51.0, "discount_profit_gross": 74.0, "discount_profit_net": 21.0}, {"full_code": "SZ160644", "code6": "160644", "name": "港美互联网LOF", "price": 1.626, "change": -1.57, "est": 1.639, "premium": -0.79, "est_date": "2026-07-17", "ref_premium": -1.42, "status": "closed", "status_text": "暂停申购", "redeem_status": "open", "redeem_status_text": "正常赎回", "quota": 10000.0, "big_quota": null, "fund_type": "", "is_qdii": true, "confirm_days": 2, "confirm_days_label": "T+2", "yituo6": true, "yituo6_label": "推荐", "quota_label": "1万", "premium_cycle_label": "约4天", "premium_cycle_detail": "T+2+转托管", "discount_cycle_label": "约4天", "discount_cycle_detail": "T+0买入/T+2赎", "capital": 10000.0, "premium_profit_gross": 79.0, "premium_profit_net": 56.0, "discount_profit_gross": 79.0, "discount_profit_net": 26.0}, {"full_code": "SZ161831", "code6": "161831", "name": "恒生国企LOF", "price": 0.72, "change": 2.27, "est": 0.726, "premium": -0.83, "est_date": "2026-07-20", "ref_premium": null, "status": "open", "status_text": "正常申购", "redeem_status": "open", "redeem_status_text": "正常赎回", "quota": null, "big_quota": null, "fund_type": "", "is_qdii": true, "confirm_days": 1, "confirm_days_label": "T+1", "yituo6": true, "yituo6_label": "支持", "quota_label": "无限制", "premium_cycle_label": "约3天", "premium_cycle_detail": "T+1+转托管", "discount_cycle_label": "约3天", "discount_cycle_detail": "T+0买入/T+1赎", "capital": 10000, "premium_profit_gross": 83.0, "premium_profit_net": 60.0, "discount_profit_gross": 83.0, "discount_profit_net": 30.0}, {"full_code": "SZ165513", "code6": "165513", "name": "中信保诚商品LOF", "price": 0.94, "change": -0.53, "est": 0.948, "premium": -0.84, "est_date": "2026-07-17", "ref_premium": -0.91, "status": "closed", "status_text": "暂停申购", "redeem_status": "closed", "redeem_status_text": "暂停赎回", "quota": null, "big_quota": null, "fund_type": "", "is_qdii": true, "confirm_days": 2, "confirm_days_label": "T+2", "yituo6": true, "yituo6_label": "支持", "quota_label": "无限制", "premium_cycle_label": "约4天", "premium_cycle_detail": "T+2+转托管", "discount_cycle_label": "约4天", "discount_cycle_detail": "T+0买入/T+2赎", "capital": 10000, "premium_profit_gross": 84.0, "premium_profit_net": 61.0, "discount_profit_gross": 84.0, "discount_profit_net": 31.0}, {"full_code": "SH501300", "code6": "501300", "name": "美元债LOF", "price": 0.933, "change": 0.0, "est": 0.941, "premium": -0.85, "est_date": "2026-07-17", "ref_premium": -0.82, "status": "limited", "status_text": "限制大额", "redeem_status": "open", "redeem_status_text": "正常赎回", "quota": 50000000.0, "big_quota": null, "fund_type": "", "is_qdii": true, "confirm_days": 2, "confirm_days_label": "T+2", "yituo6": false, "yituo6_label": "仅深市", "quota_label": "5000万", "premium_cycle_label": "约4天", "premium_cycle_detail": "T+2+转托管", "discount_cycle_label": "约4天", "discount_cycle_detail": "T+0买入/T+2赎", "capital": 10000, "premium_profit_gross": 85.0, "premium_profit_net": 62.0, "discount_profit_gross": 85.0, "discount_profit_net": 32.0}, {"full_code": "SZ163113", "code6": "163113", "name": "申万证券LOF", "price": 0.934, "change": -0.32, "est": 0.942, "premium": -0.85, "est_date": "2026-07-20", "ref_premium": null, "status": "open", "status_text": "正常申购", "redeem_status": "open", "redeem_status_text": "正常赎回", "quota": null, "big_quota": null, "fund_type": "", "is_qdii": false, "confirm_days": 1, "confirm_days_label": "T+1", "yituo6": true, "yituo6_label": "支持", "quota_label": "无限制", "premium_cycle_label": "约3天", "premium_cycle_detail": "T+1+转托管", "discount_cycle_label": "约3天", "discount_cycle_detail": "T+0买入/T+1赎", "capital": 10000, "premium_profit_gross": 85.0, "premium_profit_net": 62.0, "discount_profit_gross": 85.0, "discount_profit_net": 32.0}, {"full_code": "SZ162412", "code6": "162412", "name": "医疗基金LOF", "price": 0.556, "change": 0.0, "est": 0.561, "premium": -0.89, "est_date": "2026-07-20", "ref_premium": null, "status": "open", "status_text": "正常申购", "redeem_status": "open", "redeem_status_text": "正常赎回", "quota": null, "big_quota": null, "fund_type": "", "is_qdii": true, "confirm_days": 2, "confirm_days_label": "T+2", "yituo6": true, "yituo6_label": "支持", "quota_label": "无限制", "premium_cycle_label": "约4天", "premium_cycle_detail": "T+2+转托管", "discount_cycle_label": "约4天", "discount_cycle_detail": "T+0买入/T+2赎", "capital": 10000, "premium_profit_gross": 89.0, "premium_profit_net": 66.0, "discount_profit_gross": 89.0, "discount_profit_net": 36.0}, {"full_code": "SZ160924", "code6": "160924", "name": "恒生指数LOF", "price": 0.985, "change": 1.76, "est": 0.994, "premium": -0.91, "est_date": "2026-07-20", "ref_premium": null, "status": "open", "status_text": "正常申购", "redeem_status": "open", "redeem_status_text": "正常赎回", "quota": null, "big_quota": null, "fund_type": "", "is_qdii": true, "confirm_days": 1, "confirm_days_label": "T+1", "yituo6": true, "yituo6_label": "支持", "quota_label": "无限制", "premium_cycle_label": "约3天", "premium_cycle_detail": "T+1+转托管", "discount_cycle_label": "约3天", "discount_cycle_detail": "T+0买入/T+1赎", "capital": 10000, "premium_profit_gross": 91.0, "premium_profit_net": 68.0, "discount_profit_gross": 91.0, "discount_profit_net": 38.0}, {"full_code": "SZ160717", "code6": "160717", "name": "H股LOF", "price": 0.712, "change": 2.3, "est": 0.719, "premium": -0.97, "est_date": "2026-07-20", "ref_premium": null, "status": "open", "status_text": "正常申购", "redeem_status": "open", "redeem_status_text": "正常赎回", "quota": null, "big_quota": null, "fund_type": "", "is_qdii": true, "confirm_days": 1, "confirm_days_label": "T+1", "yituo6": true, "yituo6_label": "支持", "quota_label": "无限制", "premium_cycle_label": "约3天", "premium_cycle_detail": "T+1+转托管", "discount_cycle_label": "约3天", "discount_cycle_detail": "T+0买入/T+1赎", "capital": 10000, "premium_profit_gross": 97.0, "premium_profit_net": 74.0, "discount_profit_gross": 97.0, "discount_profit_net": 44.0}, {"full_code": "SZ161127", "code6": "161127", "name": "标普生物科技LOF", "price": 2.03, "change": 2.22, "est": 2.053, "premium": -1.12, "est_date": "2026-07-17", "ref_premium": -1.13, "status": "closed", "status_text": "暂停申购", "redeem_status": "open", "redeem_status_text": "正常赎回", "quota": 10.0, "big_quota": null, "fund_type": "", "is_qdii": true, "confirm_days": 2, "confirm_days_label": "T+2", "yituo6": true, "yituo6_label": "推荐", "quota_label": "10元", "premium_cycle_label": "约4天", "premium_cycle_detail": "T+2+转托管", "discount_cycle_label": "约4天", "discount_cycle_detail": "T+0买入/T+2赎", "capital": 10.0, "premium_profit_gross": 0.11, "premium_profit_net": 0.09, "discount_profit_gross": 0.11, "discount_profit_net": 0.06}, {"full_code": "SZ161032", "code6": "161032", "name": "煤炭龙头LOF", "price": 2.167, "change": 4.58, "est": 2.192, "premium": -1.14, "est_date": "2026-07-20", "ref_premium": null, "status": "open", "status_text": "正常申购", "redeem_status": "open", "redeem_status_text": "正常赎回", "quota": null, "big_quota": null, "fund_type": "", "is_qdii": false, "confirm_days": 1, "confirm_days_label": "T+1", "yituo6": true, "yituo6_label": "支持", "quota_label": "无限制", "premium_cycle_label": "约3天", "premium_cycle_detail": "T+1+转托管", "discount_cycle_label": "约3天", "discount_cycle_detail": "T+0买入/T+1赎", "capital": 10000, "premium_profit_gross": 114.0, "premium_profit_net": 91.0, "discount_profit_gross": 114.0, "discount_profit_net": 61.0}, {"full_code": "SZ164824", "code6": "164824", "name": "印度基金LOF", "price": 1.285, "change": -0.46, "est": 1.303, "premium": -1.38, "est_date": "2026-07-17", "ref_premium": -1.38, "status": "limited", "status_text": "限制大额", "redeem_status": "open", "redeem_status_text": "正常赎回", "quota": 500000.0, "big_quota": null, "fund_type": "", "is_qdii": true, "confirm_days": 2, "confirm_days_label": "T+2", "yituo6": true, "yituo6_label": "支持", "quota_label": "50万", "premium_cycle_label": "约4天", "premium_cycle_detail": "T+2+转托管", "discount_cycle_label": "约4天", "discount_cycle_detail": "T+0买入/T+2赎", "capital": 10000, "premium_profit_gross": 138.0, "premium_profit_net": 115.0, "discount_profit_gross": 138.0, "discount_profit_net": 85.0}, {"full_code": "SZ168401", "code6": "168401", "name": "红土创新精选LOF", "price": 5.889, "change": -7.16, "est": 6.249, "premium": -5.76, "est_date": "2026-07-20", "ref_premium": null, "status": "open", "status_text": "正常申购", "redeem_status": "open", "redeem_status_text": "正常赎回", "quota": null, "big_quota": null, "fund_type": "", "is_qdii": false, "confirm_days": 1, "confirm_days_label": "T+1", "yituo6": true, "yituo6_label": "支持", "quota_label": "无限制", "premium_cycle_label": "约3天", "premium_cycle_detail": "T+1+转托管", "discount_cycle_label": "约3天", "discount_cycle_detail": "T+0买入/T+1赎", "capital": 10000, "premium_profit_gross": 576.0, "premium_profit_net": 553.0, "discount_profit_gross": 576.0, "discount_profit_net": 523.0, "arb_cycle_label": "约3天", "expected_profit": 523.0, "arb_type": "discount"}], "prevPremiums": {"SH501225": 21.14, "SH501018": 19.9, "SZ160723": 17.02, "SZ161129": 16.65, "SZ160644": 14.54, "SZ161128": 3.66, "SZ161130": 3.44, "SZ162719": 2.84, "SZ161226": 2.57, "SZ160416": 2.51, "SZ163208": 2.3, "SZ162411": 1.71, "SH501312": 1.22, "SZ161125": 1.1, "SZ160216": 1.07, "SZ161831": 1.05, "SZ160717": 0.94, "SZ164705": 0.91, "SH501043": 0.84, "SZ161815": 0.62, "SZ160924": 0.58, "SH501300": 0.36, "SH501302": 0.19, "SZ161126": -0.13, "SZ161127": -0.15, "SZ161116": -0.18, "SZ162415": -0.18, "SH501025": -0.21, "SZ164701": -0.25, "SZ160140": -0.32, "SZ165513": -0.33, "SZ160719": -0.35, "SZ164824": -0.4, "SZ161124": -0.45, "SZ164906": -0.53}}